Workbook

Sheet Index
B1: Index
B3: Index
B9: Click on any section name to proceed directly to that part of the assessment
B10: Domain | D10: Section | I10: Questions remaining
B11: Introduction | D11: 1. Introduction | I11: N/A
D12: 2. Usage | I12: N/A
D13: 3. Change notes | J13: N/A
I14: Questions remaining
B15: General | D15: 1. Profile | I15: N/A
D16: 2. Scope | I16: N/A
I17: Questions remaining
B18: Business | D18: 1. Business drivers | I18: =CONCATENATE(COUNTIFS(_Output!A:A,"B 1*",_Output!B:B,1,_Output!L:L,"<>NIST MAPPING",_Output!D:D, 0,_Output!E:E, ">1"),"/", COUNTIFS(_Output!A:A,"B 1*",_Output!B:B,1,_Output!L:L,"<>NIST MAPPING",_Output!E:E, ">1")) -> 5/5
D19: 2. Customers & Stakeholders | I19: =CONCATENATE(COUNTIFS(_Output!A:A,"B 2*",_Output!B:B,1,_Output!L:L,"<>NIST MAPPING",_Output!D:D, 0,_Output!E:E, ">1"),"/",COUNTIFS(_Output!A:A,"B 2*",_Output!B:B,1,_Output!L:L,"<>NIST MAPPING",_Output!E:E, ">1")) -> 6/6
D20: 3. Charter | I20: =CONCATENATE(COUNTIFS(_Output!A:A,"B 3*",_Output!B:B,1,_Output!L:L,"<>NIST MAPPING",_Output!D:D, 0,_Output!E:E, ">1"),"/", COUNTIFS(_Output!A:A,"B 3*",_Output!B:B,1,_Output!L:L,"<>NIST MAPPING",_Output!E:E, ">1")) -> 4/4
D21: 4. Governance | I21: =CONCATENATE(COUNTIFS(_Output!A:A,"B 4*",_Output!B:B,1,_Output!L:L,"<>NIST MAPPING",_Output!D:D, 0,_Output!E:E, ">1"),"/",COUNTIFS(_Output!A:A,"B 4*",_Output!B:B,1,_Output!L:L,"<>NIST MAPPING",_Output!E:E, ">1")) -> 9/9
D22: 5. Privacy & Policy | I22: =CONCATENATE(COUNTIFS(_Output!A:A,"B 5*",_Output!B:B,1,_Output!L:L,"<>NIST MAPPING",_Output!D:D, 0,_Output!E:E, ">1"),"/",COUNTIFS(_Output!A:A,"B 5*",_Output!B:B,1,_Output!L:L,"<>NIST MAPPING",_Output!E:E, ">1")) -> 10/10
I23: Questions remaining
B24: People | D24: 1. Employees | I24: =CONCATENATE(COUNTIFS(_Output!A:A,"P 1*",_Output!B:B,1,_Output!L:L,"<>NIST MAPPING",_Output!D:D, 0,_Output!E:E, ">1"),"/",COUNTIFS(_Output!A:A,"P 1*",_Output!B:B,1,_Output!L:L,"<>NIST MAPPING",_Output!E:E, ">1")) -> 9/9
D25: 2. Roles and Hierarchy | I25: =CONCATENATE(COUNTIFS(_Output!A:A,"P 2*",_Output!B:B,1,_Output!L:L,"<>NIST MAPPING",_Output!D:D, 0,_Output!E:E, ">1"),"/",COUNTIFS(_Output!A:A,"P 2*",_Output!B:B,1,_Output!L:L,"<>NIST MAPPING",_Output!E:E, ">1")) -> 8/8
D26: 3. People Management | I26: =CONCATENATE(COUNTIFS(_Output!A:A,"P 3*",_Output!B:B,1,_Output!L:L,"<>NIST MAPPING",_Output!D:D, 0,_Output!E:E, ">1"),"/",COUNTIFS(_Output!A:A,"P 3*",_Output!B:B,1,_Output!L:L,"<>NIST MAPPING",_Output!E:E, ">1")) -> 14/14
D27: 4. Knowledge Management | I27: =CONCATENATE(COUNTIFS(_Output!A:A,"P 4*",_Output!B:B,1,_Output!L:L,"<>NIST MAPPING",_Output!D:D, 0,_Output!E:E, ">1"),"/",COUNTIFS(_Output!A:A,"P 4*",_Output!B:B,1,_Output!L:L,"<>NIST MAPPING",_Output!E:E, ">1")) -> 8/8
D28: 5. Training & Education | I28: =CONCATENATE(COUNTIFS(_Output!A:A,"P 5*",_Output!B:B,1,_Output!L:L,"<>NIST MAPPING",_Output!D:D, 0,_Output!E:E, ">1"),"/",COUNTIFS(_Output!A:A,"P 5*",_Output!B:B,1,_Output!L:L,"<>NIST MAPPING",_Output!E:E, ">1")) -> 7/7
I29: Questions remaining
B30: Process | D30: 1. SOC Management | I30: =CONCATENATE(COUNTIFS(_Output!A:A,"M 1*",_Output!B:B,1,_Output!L:L,"<>NIST MAPPING",_Output!D:D, 0,_Output!E:E, ">1"),"/",COUNTIFS(_Output!A:A,"M 1*",_Output!B:B,1,_Output!L:L,"<>NIST MAPPING",_Output!E:E, ">1")) -> 7/7
D31: 2. Operations and Facilities | I31: =CONCATENATE(COUNTIFS(_Output!A:A,"M 2*",_Output!B:B,1,_Output!L:L,"<>NIST MAPPING",_Output!D:D, 0,_Output!E:E, ">1"),"/",COUNTIFS(_Output!A:A,"M 2*",_Output!B:B,1,_Output!L:L,"<>NIST MAPPING",_Output!E:E, ">1")) -> 20/20
D32: 3. Reporting & Communication | I32: =CONCATENATE(COUNTIFS(_Output!A:A,"M 3*",_Output!B:B,1,_Output!L:L,"<>NIST MAPPING",_Output!D:D, 0,_Output!E:E, ">1"),"/", COUNTIFS(_Output!A:A,"M 3*",_Output!B:B,1,_Output!L:L,"<>NIST MAPPING",_Output!E:E, ">1")) -> 17/17
D33: 4. Use Case Management | I33: =CONCATENATE(COUNTIFS(_Output!A:A,"M 4*",_Output!B:B,1,_Output!L:L,"<>NIST MAPPING",_Output!D:D, 0,_Output!E:E, ">1"),"/",COUNTIFS(_Output!A:A,"M 4*",_Output!B:B,1,_Output!L:L,"<>NIST MAPPING",_Output!E:E, ">1")) -> 20/20
D34: 5. Detection Engineering & Validation | I34: =CONCATENATE(COUNTIFS(_Output!A:A,"M 5*",_Output!B:B,1,_Output!L:L,"<>NIST MAPPING",_Output!D:D, 0, _Output!E:E, ">1"),"/",COUNTIFS(_Output!A:A,"M 5*",_Output!B:B,1,_Output!L:L,"<>NIST MAPPING", _Output!E:E, ">1")) -> 18/18
D35: 6. Automation Engineering | J35: =CONCATENATE(COUNTIFS(_Output!A:A,"M 6*",_Output!B:B,1,_Output!L:L,"<>NIST MAPPING",_Output!D:D, 0, _Output!E:E, ">1"),"/",COUNTIFS(_Output!A:A,"M 6*",_Output!B:B,1,_Output!L:L,"<>NIST MAPPING", _Output!E:E, ">1")) -> 10/10
D36: 7. Log Management | J36: =CONCATENATE(COUNTIFS(_Output!A:A,"M 7*",_Output!B:B,1,_Output!L:L,"<>NIST MAPPING",_Output!D:D, 0, _Output!E:E, ">1"),"/",COUNTIFS(_Output!A:A,"M 7*",_Output!B:B,1,_Output!L:L,"<>NIST MAPPING", _Output!E:E, ">1")) -> 8/8
I37: Questions remaining
B38: Technology | D38: 1. Log Monitoring | I38: =CONCATENATE(COUNTIFS(_Output!A:A,"T 1*",_Output!B:B,1,_Output!L:L,"<>NIST MAPPING",_Output!D:D, 0, _Output!E:E, ">1"),"/",COUNTIFS(_Output!A:A,"T 1*",_Output!B:B,1,_Output!L:L,"<>NIST MAPPING", _Output!E:E, ">1")) -> 60/60
D39: 2. Network Monitoring | I39: =CONCATENATE(COUNTIFS(_Output!A:A,"T 2*",_Output!B:B,1,_Output!L:L,"<>NIST MAPPING",_Output!D:D, 0, _Output!E:E, ">1"),"/",COUNTIFS(_Output!A:A,"T 2*",_Output!B:B,1,_Output!L:L,"<>NIST MAPPING",_Output!E:E, ">1")) -> 56/56
D40: 3. Endpoint Monitoring | I40: =CONCATENATE(COUNTIFS(_Output!A:A,"T 3*",_Output!B:B,1,_Output!L:L,"<>NIST MAPPING",_Output!D:D, 0, _Output!E:E, ">1"),"/",COUNTIFS(_Output!A:A,"T 3*",_Output!B:B,1,_Output!L:L,"<>NIST MAPPING", _Output!E:E, ">1")) -> 71/71
D41: 4. SecOps Automation | I41: =CONCATENATE(COUNTIFS(_Output!A:A,"T 4*",_Output!B:B,1,_Output!L:L,"<>NIST MAPPING",_Output!D:D, 0,_Output!E:E, ">1"),"/",COUNTIFS(_Output!A:A,"T 4*",_Output!B:B,1,_Output!L:L,"<>NIST MAPPING",_Output!E:E, ">1")) -> 46/46
I42: Questions remaining
B43: Services | D43: 1. Security Monitoring | I43: =CONCATENATE(COUNTIFS(_Output!A:A,"S 1*",_Output!B:B,1,_Output!L:L,"<>NIST MAPPING",_Output!D:D, 0, _Output!E:E, ">1"),"/",COUNTIFS(_Output!A:A,"S 1*",_Output!B:B,1,_Output!L:L,"<>NIST MAPPING",_Output!E:E, ">1")) -> 41/41
D44: 2. Security Incident Management | I44: =CONCATENATE(COUNTIFS(_Output!A:A,"S 2*",_Output!B:B,1,_Output!L:L,"<>NIST MAPPING",_Output!D:D, 0, _Output!E:E, ">1"),"/",COUNTIFS(_Output!A:A,"S 2*",_Output!B:B,1,_Output!L:L,"<>NIST MAPPING", _Output!E:E, ">1")) -> 52/52
D45: 3. Security Analysis and Forensics | I45: =CONCATENATE(COUNTIFS(_Output!A:A,"S 3*",_Output!B:B,1,_Output!L:L,"<>NIST MAPPING",_Output!D:D, 0, _Output!E:E, ">1"),"/",COUNTIFS(_Output!A:A,"S 3*",_Output!B:B,1,_Output!L:L,"<>NIST MAPPING", _Output!E:E, ">1")) -> 38/38
D46: 4. Threat Intelligence | I46: =CONCATENATE(COUNTIFS(_Output!A:A,"S 4*",_Output!B:B,1,_Output!L:L,"<>NIST MAPPING",_Output!D:D, 0, _Output!E:E, ">1"),"/",COUNTIFS(_Output!A:A,"S 4*",_Output!B:B,1,_Output!L:L,"<>NIST MAPPING", _Output!E:E, ">1")) -> 55/55
D47: 5. Threat Hunting | I47: =CONCATENATE(COUNTIFS(_Output!A:A,"S 5*",_Output!B:B,1,_Output!L:L,"<>NIST MAPPING",_Output!D:D, 0, _Output!E:E, ">1"),"/",COUNTIFS(_Output!A:A,"S 5*",_Output!B:B,1,_Output!L:L,"<>NIST MAPPING",_Output!E:E, ">1")) -> 35/35
D48: 6. Vulnerability Management | I48: =CONCATENATE(COUNTIFS(_Output!A:A,"S 6*",_Output!B:B,1,_Output!L:L,"<>NIST MAPPING",_Output!D:D, 0, _Output!E:E, ">1"),"/",COUNTIFS(_Output!A:A,"S 6*",_Output!B:B,1,_Output!L:L,"<>NIST MAPPING", _Output!E:E, ">1")) -> 33/33
I49: Questions remaining
B50: Results | D50: 1. Results | I50: N/A
D51: 2. NIST CSF Scoring | J51: N/A
D52: 3. Results Sharing | J52: N/A
I53: Questions remaining
B54: Next steps | D54: 1. Next steps | I54: N/A

Sheet Introduction - INT
B1: Introduction
B3: 1. Introduction
B4: 2. Usage
B5: 3. Change notes
B19: General information
B20: Author | G20: Rob van Os
B21: Site | G21: https://www.soc-cmm.com/
B22: Contact | G22: info@soc-cmm.com
B23: Version | G23: 2.4.2, basic version
B24: Date | G24: April 16, 2026
B25: SOC-CMM training | G25: https://www.soc-cmm.com/services/training/
B26: SOC-CMM Support partners (for 3rd party assessment) | G26: https://www.soc-cmm.com/services/support/
B28: Background
B29: The SOC-CMM® model is a capability maturity model that can be used to perform a self-assessment of your Security Operations Center (SOC). The model is based on review conducted on literature regarding SOC setup and existing SOC models as well as literature on specific elements within a SOC. The literature analysis was then validated by questioning several Security Operations Centers in different sectors and on different maturity levels to determine which elements were actually in place. The output from the survey, combined with the initial analysis is the basis for this self-assessment. For more information regarding the scientific background and the literature used to create the SOC-CMM self-assessment tool, please refer to the thesis document as available through: https://www.soc-cmm.com/ If you have any questions or comments regarding the contents of this document, please use the above information to contact SOC-CMM®.
B38: Purpose and intended audience
B39: The purpose of the SOC-CMM is to gain insight into the strengths and weaknesses of the SOC. This enables the SOC management to make informed decisions about which elements of the SOC require additional attention and/or budget. By regularly assessing the SOC for maturity and capability, progress can be monitored. Besides the primary purpose of performing an assessment of the SOC, the assessment can also be used for extensive discussions about the SOC and can thus provide valuable insights. This tool is intended for use by SOC and security managers, experts within the SOC and SOC consultants.
B46: Navigation
B47: Navigation through this tool is done using the navigation bar at the top of each page. Each of the numbered sections can be clicked to proceed directly to that section. Furthermore, the icons can be used to navigate through sections within a domain and between domains. The icons are as follows:
C49: navigate to previous domain | H49: navigate to previous section within the domain
C51: navigate to index | H51: navigate to next section within the domain
C53: navigate to next domain | H53: navigate directly to results
B55: Assessment Model
B56: The assessment model consists of 5 domains and 27 aspects. All domains are evaluated for maturity (blue), only technology and services are evaluated for both maturity and capability (purple)
B78: Maturity Levels
B79: CMMI defines maturity as a means for an organization "to characterize its performance" for a specific entity (here: the SOC). The SOC-CMM calculates a maturity score using 6 maturity levels: - Level 0: non-existent - Level 1: initial - Level 2: managed - Level 3: defined - Level 4: quantitatively managed - Level 5: optimizing These maturity levels are measured across 5 domains: business, people, process, technology and services. The maturity levels as implemented in this tool are not staged with pre-requisites for each level. Instead, every element adds individually to the maturity score: a continuous maturity model.
B88: Capability Levels
B89: Capabilities are indicators of completeness. In essence, capabilities can support maturity. The SOC-CMM calculates a capability score using 4 capability levels, similar to CMMi: - Level 0: incomplete - Level 1: performed - Level 2: managed - Level 3: defined These capability levels have a strong technical focus and are measured across 2 domains: technology and services. Similar to maturity levels, progress to a higher capability level is continuous. There are no prerequisites for advancing to a higher level, thus the capability growth is continuous as well.
B97: Disclaimer
B98: The SOC-CMM is provided without warranty of any kind. The author of the document cannot assure its accuracy and is not liable for any cost as a result of decisions based on the output of this tool. The usage of this tool does not in any way entitle the user to support or consultancy. By using this tool, you agree to these conditions.
B101: License
B102: Copyright (C) 2025 - SOC-CMM® The SOC-CMM advanced version is part of the SOC-CMM®. The SOC-CMM® assessment tool is free software, released under the CC SA-BY license: https://creativecommons.org/licenses/by-sa/4.0/ You are free to: Share — copy and redistribute the material in any medium or format Adapt — remix, transform, and build upon the material for any purpose, even commercially. Under the following terms: Attribution — You must give appropriate credit, provide a link to the license, and indicate if changes were made. You may do so in any reasonable manner, but not in any way that suggests the licensor endorses you or your use. ShareAlike — If you remix, transform, or build upon the material, you must distribute your contributions under the same license as the original. No additional restrictions — You may not apply legal terms or technological measures that legally restrict others from doing anything the license permits. This license is acceptable for Free Cultural Works. The licensor cannot revoke these freedoms as long as you follow the license terms. This program is distributed in the hope that it will be useful, but WITHOUT ANY WARRANTY; without even the implied warranty of MERCHANTABILITY or FITNESS FOR A PARTICULAR PURPOSE.

Sheet Introduction - USG
B1: Introduction
B3: 1. Introduction
B4: 2. Usage
B5: 3. Change notes
B9: How to use the SOC-CMM assessment tool
B10: The SOC-CMM® assessement tool has an embedded workflow that guides the assessment. First, the profile sheet is filled in and the scope for assessment is selected. Then, the 5 domains of the SOC-CMM® model (i.e. Business, People, Process, Technology and Services) are each evaluated in separate sections of this tool. The evaluation is based on questions that can be answered using a drop-down that presents a 5-point scale. This scale relates to the maturity level as explained below under 'Scoring mechanism'. This tool should be used by assessing each sheet in order. When all domains are completed, the sheet 'Results' will provide you with the total scoring and detailed scoring for each domain. A sheet 'Next steps' is also included to provide pointers for follow-up. In the advanced version only, there is also a weighing mechanism in place. For each question, the importance of that element can be changed. The standard importance is 'normal', which means that the score is not modified. Changing to importance to 'low' will cause the element to have less impact on the score. Changing it to 'High' or 'Critical' will cause the element to have more impact on the score. Setting it to 'none' will ignore the element in scoring entirely, as explained under 'Weighing mechanism'. This feature should be used with care. Some additional remarks regarding the usage of the SOC-CMM® assessment tool: 1. Some elements are not used directly for scoring (this is also indicated), but are a guideline for answering other questions. These elements have a lighter colour. For example, question 3.1 (part of maturity score) can be answered by using the elements in 3.2 (not part of maturity score) as a guideline. 2. Elements with a green colour are calculated fields. These will be filled in automatically by filling in those parts of the assessment. 3. The services and Technology domains evaluate both maturity and capability. These capabilities do not have a 5-point scale and an importance, but use a 6-point scale instead. This is to reduce the amount of clicks and answers. The sixth element in the scale is 'not required'. Use this if you do not feel like you need that particular capability and to exclude it from scoring. 4. Every sheet has a part where you can fill in some comments or remarks. Discussing the questions in this self-assessments will likely uncover some improvements. This is added value for a self-assessment, so it is worthwhile to create notes. 5. The weighing mechanisms allows for manipulation of the maturity score. Therefore, it is important to strongly consider and possibly document why you wish to deviate from the standard. The goal of the SOC-CMM is to provide insight into strengths and weaknesses and to improve the SOC, not to obtain the highest score possible. 6. The NIST score is calculated automatically as explained below 7. Performing a full SOC-CMM® assessment can take a significant amount of time, depending on the level of detail you put into the assessment. Before you start, ensure that you have allocated sufficient time. A way to reduce effort is to have a single knowledgeable SOC employee perform a quick scan and subsequently focus on areas that are debatable. Also, reducing scope for an initial assessment is a way to reduce the assessment effort.
B31: Scoring mechanism
B32: Each question that is part of the maturity scoring can be answered by selecting one of 5 options. These options vary based on the type of question. For example, for questions regarding completeness, the following applies: - Incomplete, score: 0 - Partially complete, score: 1,25 - Averagely complete, score: 2,5 - Mostly complete, score: 3,75 - Fully complete, score: 5 As indicated, the score can be modified by using the weighing mechanism (use with care)
B39: Guidance
B40: For each of the maturity questions, guidance is available. When a value is selected from the dropdown box, guidance for that value is show under the guidance column. This guidance can be used to help determine the correct level. Note that this is truly meant as guidance on interpretation and scoring, not as mandatory and prescriptive.
B43: Weighing mechanism (advanced version only)
B44: The weighing mechanism in the tool works by applying a factor to the element score as follows: - Importance 'None', factor = 0 (not included in scoring) - Importance 'Low', factor = 0.5 (score divided by 2) - Importance 'Normal', factor = 1 (score not affected) - Importance 'High', factor = 2 (score doubled) - Importance 'Critical', factor = 4 (score quadrupled)
... B53: The SOC-CMM® assessment tool is built using standard Excel features without macros. The sheets are not locked or password protected. Therefore, adding columns and rows and applying other changes such as changing guidance or adding elements is possible. To show columns and rows, go to 'View' --> 'Show' and check 'Headings'. To show all the tabs underlying the SOC-CMM, go top 'File' --> 'Options' --> 'Advanced' --> 'Display options' and check 'Show sheet tabs'. Customizing calculations will require understanding of the calculations done in the '_Output' sheet. However, guidance for this type of customization is not provided, as it requires an understanding of the way the SOC-CMM® assessment tool sheets are connected.

Sheet Introduction - CHG
B1: Introduction
B3: 1. Introduction
B4: 2. Usage
B5: 3. Change notes
B9: Version 2.4.2 | D9: 16.4.2026
B11: General
C12: Updated scoped out visualization. Scope out elements now shown in red strike-through tekst
B14: Profile
C15: Scope
D16: Updated scoping element to make them clickable links
B18: Business
C19: Governance
D20: Updated guidance and description for external collaboration (4.11)
C21: Privacy & Policy
D22: Added 'interaction with public media' and 'SOC internet presence' to SOC policy to increase alignment with SIM3
B24: People
C25: Employees
D26: Added a question on retention strategy
B28: Process
C29: Operations & Facilities
D30: Question 2.2.6 added on emergency reachability to increase alignment with SIM3
D31: 2.4.1.6: Messaging system update to resilient messaging system to increase alignment with SIM3
D32: 2.4.1.7: added Resilient internet access to increase alignment with SIM3
D33: Fixed several incorrect references (non-functional)
B35: Services
C36: Security incident management
D37: Rearranged capabilities using the structure of NIST SP 800-61
D38: Renumbering applied for the new structure
D39: Escalation to press (2.17.25) and escalation to legal (2.17.26) functions added to increase alignment with SIM3
D40: (dedicated) information platform' renamed to '(dedicated/consolidated) information platform' to increase alignment with SIM3
B42: Results
C43: Results
D44: Calculation error for process domain average score corrected
B47: Version 2.4.1 | D47: 2.12.2025
B49: General
C50: Set all support questions to 'No' by default
C51: Left aligned some tekst for increased readability
C52: Corrected references in the Technology domain to named technologies from version 2.3
C53: Corrected 'Customers / Stakeholders' to 'Customers & Stakeholders' to align with the model
B55: Version 2.4 | D55: 1.11.2025
B57: General
C58: Added remarks lines for all questions, not just maturity questions
C59: All URLs checked and updated where requried, links added where relevant
B61: Introduction
C62: Improved tekst under introduction and usage
C63: Replaced model figure to represent the new model
C64: Replaced capbility and maturity growth figures
B66: Business domain
C67: Customers
D68: Renamed to customers / stakeholders as a section and in the questions, guidance, and remarks
B69: Process domain
C71: Operations & facilities
D72: Reduced number of maturity questions by introducing more supporting questions for assessment flow optimization purposes
C74: Reporting & communication
D75: Changed answer type for question 3.7
C77: Automation engineering
D78: New section in the SOC-CMM model. Addresses both automation engineering practice as well as the implementation of AI
C80: Log management
D81: New section, based on capabilities from the log management service previously found in the services domain
B83: Technology domain
C84: Log monitoring
D85: Replaces SIEM/UEBA for technology agnistic approach. No difference in maturity or capability questions
C87: Network monitoring
D88: Replaces NDR for technology agnistic approach. No difference in maturity or capability questions
D89: Incorrect usage of YARA in one capability question fixed
C91: Endpoint monitoring
D92: Fixed heading reference to access managenet
D93: Replaces EDR for technology agnistic approach. No difference in maturity or capability questions
C95: SecOps automation
D96: Replaces SOAR for technology agnistic approach. No difference in maturity or capability questions
B98: Services domain
C100: Security incident management
D101: Updated reference to NIST IR standard
C103: Forensic analysis
D104: Replaces security analysis for clarification purposes. No difference in maturity or capability questions
C106: Threat hunting
D107: Fixed reference error
C109: Cyber Threat Intelligences
D110: Replaces threat intelligence for clarification purposes
D111: Capabilities regrouped using the threat intelligence life cycle model
D112: Capabilities extended based on gap analysis with CTI-CMM
D113: Fixed typo on
C115: Log management
D116: Removed from services domain and implemented in the process domain
B118: Results
C119: Results
D120: Section updated to reflect the new model
C122: NIST CSF scoring
D123: Removed NIST CSF 1.1 mapping
C125: Results sharing
D126: Fixed incorrect references in the results sharing template
B128: Version 2.3
B130: Business domain:
C131: Governance
D132: 4.3.13: included SOC risk management into governance elements
D133: 4.7: Added question on governance meetings
D134: 4.7 - 4.10: renumbered to 4.8 - 4.11
C135: Privacy & Policy:
D136: 5.2: SOC policy added as a new question, 5.3 outlines the elements in the policy
D137: 5.4 - 5.11: renumbered from 5.2 - 5.9
...

Sheet General - PRO
B1: Profile
B3: 1. Profile
B4: 2. Scope
B8: Please fill in the information below to create a short profile of the SOC and the assessment
B10: Assessment Details
B11: Date of assessment
B12: Name(s)
B16: Department(s)
B17: Intended purpose of the assessment and associated assessment objectives
B24: Assessment scope / SOC scope of operations
B28: Assessment type | K28: Click on the dropdown box for more information
B29: Assessment style | K29: Click on the dropdown box for more information
B31: Organisation & SOC Profile
B32: Business size (FTE)
B33: Sector
B34: Number of years of SOC operations
B35: SOC size (FTE's)
B36: SOC organisational model | K36: Click on the dropdown box for more information
B37: SOC region
B38: Geographic operation
B40: Target Maturity (optional)
B41: Target maturity level business domain | G41: 3 | K41: Indicate a score from 1 to 5. Decimals can be used
B42: Target maturity level people domain | G42: 3 | K42: Indicate a score from 1 to 5. Decimals can be used
B43: Target maturity level process domain | G43: 3 | K43: Indicate a score from 1 to 5. Decimals can be used
B44: Target maturity level technology domain | G44: 3 | K44: Indicate a score from 1 to 5. Decimals can be used
B45: Target maturity level services domain | G45: 3 | K45: Indicate a score from 1 to 5. Decimals can be used
B46: Target overall maturity level | G46: =IFERROR(SUM(G41:J45)/5, 0) -> 3
B48: Target Capability (optional)
B49: Target capability level technology domain | G49: 2 | K49: Indicate a score from 1 to 3. Decimals can be used
B50: Target capability level services domain | G50: 2 | K50: Indicate a score from 1 to 3. Decimals can be used
B51: Target overall capability level | G51: =IFERROR(SUM(G49:J50)/COUNT(G49:J50), 0) -> 2
B53: Notes or comments

Sheet General - SCP
B1: Profile
B3: 1. Profile
B4: 2. Scope
B8: Please select the services and technologies that should be included into the assessment. Excluding a service or technology here will exclude it from scoring. Note: changes to these values take some time to process
B10: SOC Tooling (Technology domain) | J10: Remarks
B11: 1. Log monitoring | J11: Log monitoring is used to gather logging, telemetry, and other relevant security data from company assets and centralise this information for alerting and analysis purposes
B12: 2. Network monitoring | J12: Network monitoring is to used detect network exploits, anomalous network activity, lateral movement, and to perform network forensics
B13: 3. Endpoint monitoring | J13: Endpoint monitoring used to prevent, detect, and respond to threats on end-points
B14: 4. SecOps automation | J14: SecOps atuomation is used to automate workflows and SOC actions, support incident response, and orchestrate between different security products
B16: SOC Services (services domain) | J16: Remarks
B17: 1. Security Monitoring | J17: Security monitoring aims at detecting security incidents and anomalies through centralised collection, processing and analysis of security events
B18: 2. Security Incident Management | J18: Security incident management aims at responding to security incidents in a timely, accurate and organized fashion to limit or negate incident impact
B19: 3. Forensic Analysis | J19: Forensic analysis supports security incident management by introducing forensic and malware analysis capabilities
B20: 4. Cyber Threat Intelligence | J20: Threat intelligence is the act of collecting and analysing information about potential threats and threat actors that can be used in security monitoring, security incident response, security analysis and threat hunting
B21: 5. Threat Hunting | J21: Threat hunting is a proactive monitoring activity used to uncovering threats in the infrastructure through searcing for TTPs, based on threat intelligence and the "assume breach" principle
B22: 6. Vulnerability Management | J22: Vulnerability management is the act of detecting vulnerabilities in assets by actively scanning assets for known vulnerabilities, analysing outcomes, and following up through remediation

Sheet Business - BSD
B1: Business
B3: 1. Business Drivers | G3: 5. Privacy & Policy
B4: 2. Customers & Stakeholders
B5: 3. Charter
B6: 4. Governance
A9: 1 | B9: Business Drivers | L9: Answer | N9: Guidance | O9: Remarks
B10: 1.1 | C10: Have you identified the main business drivers? | N10: =VLOOKUP(_Output!D4,_Guidance!B4:C9,2,FALSE) | O10: Example business drivers: cyber crime prevention, risk reduction, law / regulation, audit / compliance, business continuity
B11: 1.2 | C11: Have you documented the main business drivers? | N11: =VLOOKUP(_Output!D5,_Guidance!B10:C15,2,FALSE) | O11: Documentation of business drivers is important for demonstrable business alignment
B12: 1.3 | C12: Do you use business drivers in the decision making process? | N12: =VLOOKUP(_Output!D6,_Guidance!B16:C21,2,FALSE) | O12: e.g. to determine priorities or make decisions regarding the on-boarding of new services or operations
B13: 1.4 | C13: Do you regularly check if the current service catalogue is aligned with business drivers? | N13: =VLOOKUP(_Output!D7,_Guidance!B22:C27,2,FALSE) | O13: i.e. do you check for services or operations that outside the scope of business drivers?
B14: 1.5 | C14: Have the business drivers been validated with business stakeholders? | N14: =VLOOKUP(_Output!D8,_Guidance!B28:C33,2,FALSE) | O14: Business stakeholders can be C-level management
B16: Comments and/or Remarks
B17: 1.6 | C17: Specify rationale for chosen values or any additional comments | L17: 1.1
L18: 1.2
L19: 1.3
L20: 1.4
L21: 1.5

Sheet Business - CST
B1: Business
B3: 1. Business Drivers | G3: 5. Privacy & Policy
B4: 2. Customers & Stakeholders
B5: 3. Charter
B6: 4. Governance
A9: 2 | B9: Customers / Stakeholders | L9: Answer | N9: Guidance | O9: Remarks
B10: 2.1 | C10: Have you identified the SOC customers & stakeholders? | N10: =VLOOKUP(_Output!D12,_Guidance!B35:C40,2,FALSE) | O10: Types of customers and stakeholders, their requirements, expectations, etc.
B11: 2.2 | C11: Please specify your customers & stakeholders: | O11: Use this a guideline for answering 2.1 This is also potentially useful for insights and comparison with previous assessments
B12: 2.2.1 | C12: Legal | O12: Legal department, may be a stakeholder for privacy, or may request forensic investigation to the SOC
B13: 2.2.2 | C13: Audit | O13: The audit department can be supported by logging provided by the SOC
B14: 2.2.3 | C14: Engineering / R&D | O14: The engineering departments deal with Intellectual Property that may require additional access monitoring
B15: 2.2.4 | C15: IT | O15: IT departments can be supported by monitoring for anomalies in their infrastructure and systems
B16: 2.2.5 | C16: Business | O16: Business should be the most important customers & stakeholders, as all SOC activities ultimately support business processes
B17: 2.2.6 | C17: External customers & stakeholders | O17: External customers mostly apply to managed service providers. External stakeholders can by regulatory bodies
B18: 2.2.7 | C18: (Senior) Management | O18: Senior management may be a direct SOC customer & stakeholder, depending on organization hierarchy
B19: 2.2.8 | C19: Other customers & stakeholders: | O19: Specify any additional customers & stakeholders
B20: 2.3 | C20: Have you documented the main SOC customers & stakeholders? | N20: =VLOOKUP(_Output!D22,_Guidance!B41:C46,2,FALSE) | O20: Formal registration of customer & stakeholder contact details, function, agreements, etc.
B21: 2.4 | C21: Do you differentiate output towards these specific customers & stakeholders? | N21: =VLOOKUP(_Output!D23,_Guidance!B47:C52,2,FALSE) | O21: Differentiating output is helpful to match expectations of customers & stakeholders
B22: 2.5 | C22: Do you have service level agreements with these customers & stakeholders? | N22: =VLOOKUP(_Output!D24,_Guidance!B53:C58,2,FALSE) | O22: Service level agreements are used to provide standardized services operating within known boundaries
B23: 2.6 | C23: Do you regularly send updates to your customers & stakeholders? | N23: =VLOOKUP(_Output!D25,_Guidance!B59:C64,2,FALSE) | O23: For example: changes in service scope or delivery. Can also be reports, dashboards, etc.
B24: 2.7 | C24: Do you actively measure and manage customer & stakeholder satisfaction? | N24: =VLOOKUP(_Output!D26,_Guidance!B65:C70,2,FALSE) | O24: Understanding customer & stakeholder satisfaction will help to better align with business needs
B26: Comments and/or Remarks
B27: 2.8 | C27: Specify rationale for chosen values or any additional comments | L27: 2.1
L28: 2.2
L29: 2.3
L30: 2.4
L31: 2.5
L32: 2.6
L33: 2.7

Sheet Business - CHT
B1: Business
B3: 1. Business Drivers | G3: 5. Privacy & Policy
B4: 2. Customers & Stakeholders
B5: 3. Charter
B6: 4. Governance
A9: 3 | B9: Charter | L9: Answer | N9: Guidance | O9: Remarks
B10: 3.1 | C10: Does the SOC have a formal charter document in place? | N10: =VLOOKUP(_Output!D30,_Guidance!B72:C77,2,FALSE) | O10: See 3.2 for charter document elements
B11: 3.2 | C11: Please specify elements of the charter document:
B12: 3.2.1 | C12: Mission | O12: A SOC mission should be established to provide insight into the reason for existence of the SOC
B13: 3.2.2 | C13: Vision | O13: A vision should be created to determine long-term goals for the SOC
B14: 3.2.3 | C14: Strategy | O14: A strategy should be in place to show how to meet goals and targets set by mission and vision
B15: 3.2.4 | C15: Service Scope | O15: Service scope is documented to provide insight into SOC service delivery
B16: 3.2.5 | C16: Deliverables | O16: The output provided by the SOC, for example: reports, incidents, investigations, advisories, etc.
B17: 3.2.6 | C17: Responsibilities | O17: Responsibilities of the SOC
B18: 3.2.7 | C18: Accountability | O18: Accountability for the SOC for actions taken
B19: 3.2.8 | C19: Operational Hours | O19: Operational hours of the SOC
B20: 3.2.9 | C20: Stakeholders | O20: All relevant stakeholders for the SOC
B21: 3.2.10 | C21: Objectives / Goals | O21: Objectives and goals should be concrete and measurable so that they are fit for reporting purposes
B22: 3.2.11 | C22: Statement of success | O22: A statement of success is used to determine when the SOC is successful. Should be aligned with goals and objectives
C23: Completeness | L23: =VLOOKUP(SUM(_Output!D32:D42),_SUM_Completeness!A3:B14,2,FALSE) -> Incomplete | O23: Use this outcome as a guideline to determine the score for 3.1
B24: 3.3 | C24: Is the SOC charter document regularly updated? | N24: =VLOOKUP(_Output!D43,_Guidance!B78:C83,2,FALSE) | O24: Regularity should be matched to your own internal policy. At least yearly is recommended
B25: 3.4 | C25: Is the SOC charter document approved by the business / CISO? | N25: =VLOOKUP(_Output!D44,_Guidance!B84:C89,2,FALSE) | O25: Approval from the relevant stakeholders will aid in business support for SOC operations
B26: 3.5 | C26: Are all stakeholders familiar with the SOC charter document contents? | N26: =VLOOKUP(_Output!D45,_Guidance!B90:C95,2,FALSE) | O26: Making stakeholders aware of the contents helps in getting organizational support for security operations
B28: Comments and/or Remarks
B29: 3.6 | C29: Specify rationale for chosen values or any additional comments | L29: 3.1
L30: 3.2
L31: 3.3
L32: 3.4
L33: 3.5

Sheet Business - GOV
B1: Business
B3: 1. Business Drivers | G3: 5. Privacy & Policy
B4: 2. Customers & Stakeholders
B5: 3. Charter
B6: 4. Governance
A9: 4 | B9: Governance | L9: Answer | N9: Guidance | O9: Remarks
B10: 4.1 | C10: Does the SOC have a governance process in place? | N10: =VLOOKUP(_Output!D49,_Guidance!B97:C102,2,FALSE) | O10: A governance process is required to determine the way the SOC should be managed
B11: 4.2 | C11: Have all governance elements been identified? | N11: =VLOOKUP(_Output!D50,_Guidance!B103:C108,2,FALSE) | O11: Possible governance elements can be found in under 4.3
B12: 4.3 | C12: Please specify identified governance elements
B13: 4.3.1 | C13: Business Alignment | O13: Aligning SOC operations to business needs
B14: 4.3.2 | C14: Accountability | O14: Note that this can be part of the SOC charter document. This does not automatically make it part of the governance process
B15: 4.3.3 | C15: Sponsorship | O15: Can be part of stakeholder management
B16: 4.3.4 | C16: Mandate | O16: Mandate for the SOC should be established so that the SOC can take action in crisis situations
B17: 4.3.5 | C17: Relationships & Third Party Management | O17: Both management of internal and external relationships
B18: 4.3.6 | C18: Vendor Engagement | O18: For example: active involvement of vendors in the creation of a vision and strategy for the SOC
B19: 4.3.7 | C19: Service Commitment | O19: For example: service level agreements and IT controls
B20: 4.3.8 | C20: Project / Program Management | O20: Project management for individual projects within the SOC / program management for larger transitions
B21: 4.3.9 | C21: Continual Improvement | O21: Improvement of the SOC and of SOC management
B22: 4.3.10 | C22: Span of control / federation governance | O22: Especially important for SOC setups where multiple SOCs exist within the same company
B23: 4.3.11 | C23: Outsourced service management | O23: Especially important for hybrid SOC setups. When using outsourcing, SLAs and oversight should be in place
B24: 4.3.12 | C24: SOC KPIs & Metrics | O24: These are discussed in more detail in the Process section regarding reporting
... B26: 4.3.14 | C26: Customer Engagement / Satisfaction | O26: Are customers an integral part of your security operations? Is their satisfaction of SOC services every inquired about?
C27: Completeness | L27: =VLOOKUP(SUM(_Output!D52:D65),_SUM_Completeness!A17:B31,2,FALSE) -> Incomplete | O27: Use this outcome as a guideline to determine the score for 4.2
B28: 4.4 | C28: Is cost management in place? | N28: =VLOOKUP(_Output!D66,_Guidance!B109:C114,2,FALSE) | O28: Managing costs is required to justify budget allocation for the SOC and ensure continued service delivery in the future
B29: 4.5 | C29: Please specify cost management elements
B30: 4.5.1 | C30: People cost | O30: Costs associated with employees. Should be managed to prove FTE requirements to stakeholders
B31: 4.5.2 | C31: Process cost | O31: Cost associated with processes. Should be managed to ensure process elements can be delivered
B32: 4.5.3 | C32: Technology cost | O32: Cost associated with technology. Should be managed to prove budget requirements for new technology or replacement
B33: 4.5.4 | C33: Services cost | O33: Cost associated with service delivery. Especially important for managed service providers to ensure a healthy business model
B34: 4.5.5 | C34: Facility cost | O34: Cost associated with facilities used by the SOC
B35: 4.5.6 | C35: Budget forecasting | O35: Forecasting of required budget over time. Should be aligned with business needs; increased spending must be justified
B36: 4.5.7 | C36: Budget alignment | O36: Alignment of budget with business requirements and drivers to ensure balanced spending on the SOC
B37: 4.5.8 | C37: Return on investment | O37: Prove the return on investment to stakeholders to ensure continued budget allocation
C38: Completeness | L38: =VLOOKUP(SUM(_Output!D68:D75),_SUM_Completeness!A34:B42,2,FALSE) -> Incomplete | O38: Use this outcome as a guideline to determine the score for 4.4
B39: 4.6 | C39: Are all governance elements formally documented? | N39: =VLOOKUP(_Output!D76,_Guidance!B115:C120,2,FALSE) | O39: Formal documentation should be signed off and stored in a quality management system
B40: 4.7 | C40: Are SOC governance meetings regularly held? | N40: =VLOOKUP(_Output!D1078,_Guidance!B121:C126,2,FALSE) | O40: Meetings at different levels (operational, tactical, strategic) should be formalised in Terms of Reference (ToR) and driven by metrics
B41: 4.8 | C41: Is the governance process regularly reviewed? | N41: =VLOOKUP(_Output!D77,_Guidance!B127:C132,2,FALSE) | O41: Frequency should be matched to your own internal policy. At least yearly is recommended
B42: 4.9 | C42: Is the governance process aligned with all stakeholders? | N42: =VLOOKUP(_Output!D78,_Guidance!B133:C138,2,FALSE) | O42: Alignment will help the SOC obtain required mandate, budget and management support
B43: 4.10 | C43: Is the SOC regularly audited or subjected to (external) assessments? | N43: =VLOOKUP(_Output!D79,_Guidance!B139:C144,2,FALSE) | O43: Frequency should be matched to the SOC policy. At least yearly is recommended. 3rd party assessments have a higher objectivity
B44: 4.11 | C44: Is there an active cooperation with other SOCs (external)? | N44: =VLOOKUP(_Output!D985,_Guidance!B145:C150,2,FALSE) | O44: External collaboration and networking, exchaning best practices, threat intelligence, and response actions with other SOCs
B46: Comments and/or Remarks
B47: 4.12 | C47: Specify rationale for chosen values or any additional comments | L47: 4.1
L48: 4.2
L49: 4.3
L50: 4.4
L51: 4.5
L52: 4.6
L53: 4.7
L54: 4.8
L55: 4.9
L56: 4.10
L57: 4.11

Sheet Business - PRV
B1: Business
B3: 1. Business Drivers | G3: 5. Privacy & Policy
B4: 2. Customers & Stakeholders
B5: 3. Charter
B6: 4. Governance
A9: 5 | B9: Privacy & Policy | L9: Answer | N9: Guidance | O9: Remarks
B10: 5.1 | C10: Is there an information security policy in place that supports the SOC activities? | N10: =VLOOKUP(_Output!D987,_Guidance!B152:C157,2,FALSE) | O10: A clear security policy that supports SOC operations provides guidance and helps to enforce mandate for the SOC in the organisation
B11: 5.2 | C11: Has a SOC policy been created? | N11: =VLOOKUP(_Output!D1079,_Guidance!B158:C163,2,FALSE) | O11: A SOC policy is to outline the rules to which SOC personnel and SOC management needs to adhere
B12: 5.3 | C12: Please specify elements of the SOC policy
B13: 5.3.1 | C13: Code of conduct | O13: How to behave in the SOC, mandatory and optional meetings, SOC culture, repercussions for non-compliance, etc.
B14: 5.3.2 | C14: Rules of engagement & responsibilities | O14: What activities can and can not be performed as part of the job
B15: 5.3.3 | C15: Review frequency of documentation | O15: What documentation is subjected to review and how often that documentation needs to be reviewed
B16: 5.3.4 | C16: SOC assessment frequency and type | O16: How often the SOC is assessed and in what manner (self-assessment, audit, external assessment, etc.)
B17: 5.3.5 | C17: Knowledge exchange and maintenance | O17: The means (meetings and platforms) for knowledge exchange and rules for maintenance of knowledge bases
B18: 5.3.6 | C18: Exercise frequency | O18: Frequency and type (table top, cyber range, red team, etc.) of exercises in the SOC
B19: 5.3.7 | C19: Usage of TLP / Classification and information handling | O19: Information exchange protocols. Especially important for collaborations outside the organisation
B20: 5.3.8 | C20: Interaction with public media | O20: Guidelines on how to deal with public media inquiries
B21: 5.3.9 | C21: SOC internet presence | O21: Presence on the internet for the SOC, including contact for abuse or other security related questions, and social media usage
B22: 5.3.10 | C22: Working agreements | O22: Agreements on length of meetings, length of agile sprints, transparency of completed work, etc.
C23: Completeness | L23: =VLOOKUP(SUM(_Output!D1081:D1088) + SUM(_Output!D1468:D1469),_SUM_Completeness!A155:B165,2,FALSE) -> Incomplete | O23: Use this outcome as a guideline to determine the score for 5.2
B24: 5.4 | C24: Is the SOC consulted in the creation and updates of operational security policy? | N24: =VLOOKUP(_Output!D989,_Guidance!B164:C169,2,FALSE) | O24: Consulting the SOC in the creation of security policy will ensure that SOC activities are properly mentioned and enforceable
B25: 5.5 | C25: Is a reporting policy for security incidents in place? | N25: =VLOOKUP(_Output!D991,_Guidance!B170:C175,2,FALSE) | O25: A reporting policy for security incidents will aid the SOC in identifying incidents and threats in the organization
B26: 5.6 | C26: Is a privacy policy regarding security monitoring of employees in place? | N26: =VLOOKUP(_Output!D83,_Guidance!B176:C181,2,FALSE) | O26: A privacy policy should state that monitoring of employees is possible within acceptable limits
B27: 5.7 | C27: Does the SOC operate in compliance with all applicable privacy laws and regulations? | N27: =VLOOKUP(_Output!D84,_Guidance!B182:C187,2,FALSE) | O27: Local laws and regulations as well as company policy may apply and should all be considered
B28: 5.8 | C28: Does the SOC cooperate with legal departments regarding privacy matters? | N28: =VLOOKUP(_Output!D87,_Guidance!B188:C193,2,FALSE) | O28: Cooperation will ensure that the SOC is enabled to perform activities, rather than blocked
B29: 5.9 | C29: Are specific procedures in place for dealing with privacy related investigations? | N29: =VLOOKUP(_Output!D88,_Guidance!B194:C199,2,FALSE) | O29: Privacy related issues require careful examination, especially those potentially leading to court cases
B30: 5.10 | C30: Is the SOC aware of all information that it processes and is subject to privacy regulations? | N30: =VLOOKUP(_Output!D89,_Guidance!B200:C205,2,FALSE) | O30: Such information includes IP addresses, customer identifiers, user names, host names (for personally owned devices), etc.
B31: 5.11 | C31: Is a Privacy Impact Assessment (PIA) regularly conducted? | N31: =VLOOKUP(_Output!D90,_Guidance!B206:C211,2,FALSE) | O31: Can be used to determine the impact of monitoring on privacy, and can help uncover potential violations
B33: Comments and/or Remarks
B34: 5.10 | C34: Specify rationale for chosen values or any additional comments | L34: 5.1
L35: 5.2
L36: 5.3
L37: 5.4
L38: 5.5
L39: 5.6
L40: 5.7
L41: 5.8
L42: 5.9
L43: 5.10
L44: 5.11

Sheet People - EMP
B1: People
B3: 1. Employees | G3: 5. Training & Education
B4: 2. Roles and Hierarchy
B5: 3. People Management
B6: 4. Knowledge Management
A9: 1 | B9: Employees | L9: Answer | N9: Guidance | O9: Remarks
B10: 1.1 | C10: How many FTE’s are in your SOC? | L10: ='General - PRO'!G35 -> 0 | O10: Include both internal and external FTE's
B11: 1.2 | C11: Do you use external employees / contractors in your SOC? | O11: External employees can be hired experts to fill in vacant positions or perform project activities
B12: 1.2.1 | C12: If yes, specify the number of external FTE's | O12: =IFERROR(CONCATENATE("Current ratio: ", ROUND(L12/L10*100, 2), "%"),"Current ratio: 0%") -> Current ratio: 0%
B13: 1.3 | C13: Does the current size of the SOC meet FTE requirements? | N13: =VLOOKUP(_Output!D98,_Guidance!B215:C220,2,FALSE) | O13: i.e. is the SOC size sufficient to realize business goals?
B14: 1.4 | C14: Does the SOC meet requirements for internal to external employee FTE ratio? | N14: =VLOOKUP(_Output!D99,_Guidance!B221:C226,2,FALSE) | O14: Note: requirements do not need to be explicit. Set importance to 'None' if you have no external employees.
B15: 1.5 | C15: Does the SOC meet requirements for internal to external employee skillset? | N15: =VLOOKUP(_Output!D100,_Guidance!B227:C232,2,FALSE) | O15: i.e. Are there any crucial skills amongst external employees? Set importance to 'None' if you have no external employees
B16: 1.6 | C16: Are all positions filled? | N16: =VLOOKUP(_Output!D101,_Guidance!B233:C238,2,FALSE) | O16: Unfilled positions may be due to deficiencies in the recruitment process
B17: 1.7 | C17: Do you have a recruitment process in place? | N17: =VLOOKUP(_Output!D102,_Guidance!B239:C244,2,FALSE) | O17: A recruitment process is required to obtain new employees in a market where talent is scarce
B18: 1.8 | C18: Do you have a talent acquisition process in place? | N18: =VLOOKUP(_Output!D103,_Guidance!B245:C250,2,FALSE) | O18: Talent sourcing can be vital for SOC success
B19: 1.9 | C19: Do you have specific KSAOs established for SOC personnel? | N19: =VLOOKUP(_Output!D995,_Guidance!B251:C256,2,FALSE) | O19: Knowledge, Skills, Abilities and Other attributes (KSAOs) should be in place: technical, cognitive, social and character
B20: 1.10 | C20: Do you actively seek to create a psychologically safe environment for SOC personnel? | N20: =VLOOKUP(_Output!D996,_Guidance!B257:C262,2,FALSE) | O20: A psychologically safe environment is an environment where everyone is able to speak their mind and feel valued
B21: 1.11 | C21: Do you have a defined retention strategy? | O21: A retention strategy is used to ensure that talent and key personnel is not lost
B24: Comments and/or Remarks
B25: 1.12 | C25: Specify rationale for chosen values or any additional comments | L25: 1.1
L26: 1.2
L27: 1.3
L28: 1.4
L29: 1.5
L30: 1.6
L31: 1.7
L32: 1.8
L33: 1.9
L34: 1.10
B35: References | L35: 1.11
B36: CISRT social maturity handbook

Sheet People - R&H
B1: People
B3: 1. Employees | G3: 5. Training & Education
B4: 2. Roles and Hierarchy
B5: 3. People Management
B6: 4. Knowledge Management
A9: 2 | B9: Roles and Hierarchy | L9: Answer | N9: Guidance | O9: Remarks
B10: 2.1 | C10: Do you formally differentiate roles within the SOC? | N10: =VLOOKUP(_Output!D107,_Guidance!B264:C269,2,FALSE) | O10: Use the roles in 2.2 to determine if you have all roles required in the SOC
B11: 2.2 | C11: Which of the following roles are present in your SOC?
B12: 2.2.1 | C12: Security Analyst | O12: Primarily responsible for triage and analysis of security alerts
B13: 2.2.2 | C13: Security / Systems Engineer | O13: Primarily responsible for technical / functional maintenance of security systems
B14: 2.2.3 | C14: Forensic Analyst | O14: Primarily responsible for in-depth analysis and security projects
B15: 2.2.4 | C15: Security Architect | O15: Primarily responsible for technical architecture for security systems used within the SOC
B16: 2.2.5 | C16: Threat Intelligence Analyst | O16: Primarily responsible for analysis of threat intelligence
B17: 2.2.6 | C17: Data Scientist | O17: Primarily responsible for big data security analytics
B18: 2.2.7 | C18: SOC Manager | O18: Primarily responsible for managing SOC services
B19: 2.2.8 | C19: Team Leader | O19: Primarily responsible for leading a team of other, for example, analysts and engineers
B20: 2.2.9 | C20: Incident Handler | O20: Primarily responsible for executing security incident management workflows
B21: 2.2.10 | C21: Incident Manager | O21: Primarily responsible for ensuring correct and timely management and escalation of security incidents
B22: 2.2.11 | C22: Penetration Tester | O22: Primarily responsible for testing applications and systems for security weaknesses
B23: 2.2.12 | C23: Detection engineer | O23: Primarily responsible for creating and updating detection analytics
... B25: 2.2.14 | C25: Others, specify: | O25: Specify any additional roles
B26: 2.3 | C26: Do you differentiate tiers within these roles? | N26: =VLOOKUP(_Output!D123,_Guidance!B270:C275,2,FALSE) | O26: If you have no tiers, and you feel this is not a restriction, select importance 'None'
B27: 2.4 | C27: Are all roles sufficiently staffed? | N27: =VLOOKUP(_Output!D125,_Guidance!B276:C281,2,FALSE) | O27: Consider the staffing levels (desired FTE count) as well as knowledge and experience for all roles
B28: 2.5 | C28: Is there a role-based hierarchy in your SOC? | N28: =VLOOKUP(_Output!D127,_Guidance!B282:C287,2,FALSE) | O28: If you have no hierarchy, and you feel this is not a restriction, select importance 'None'
B29: 2.6 | C29: Have you formally documented all SOC roles? | N29: =VLOOKUP(_Output!D128,_Guidance!B288:C293,2,FALSE) | O29: Possible documentation elements can be found in under 2.7
B30: 2.7 | C30: Please specify elements in the role documentation:
B31: 2.7.1 | C31: Role description | O31: A formal description of the role
B32: 2.7.2 | C32: Role tasks | O32: A description of tasks that are part of the role
B33: 2.7.3 | C33: Role responsibilities | O33: The responsibilities of the role
B34: 2.7.4 | C34: Role expectations | O34: This is an extension of responsibilities. Example expectation: take a pro-active leading role in case of security incidents
B35: 2.7.5 | C35: Required technical skills | O35: e.g. experience with specific technologies or products
B36: 2.7.6 | C36: Required soft skills | O36: e.g. communication skills, presentation skills
B37: 2.7.7 | C37: Required educational level | O37: e.g. university college, university
B38: 2.7.8 | C38: Required or preferred certifications | O38: e.g. technical security certifications or security management certifications
C39: Completeness | L39: =VLOOKUP(SUM(_Output!D132:D139),_SUM_Completeness!A58:B66,2,FALSE) -> Incomplete | O39: Use this outcome as a guideline to determine the score for 2.6
B40: 2.8 | C40: Are responsibilities for each role understood? | N40: =VLOOKUP(_Output!D140,_Guidance!B294:C299,2,FALSE) | O40: Responsibilities for each role should be clearly understood by all SOC personnel
B41: 2.9 | C41: Have you documented career progression requirements for each of these roles? | N41: =VLOOKUP(_Output!D143,_Guidance!B300:C305,2,FALSE) | O41: Career progression for roles can be documented through training, certification, experience and soft skills requirements
B42: 2.10 | C42: Do you regularly revise or update the role descriptions? | N42: =VLOOKUP(_Output!D144,_Guidance!B306:C311,2,FALSE) | O42: To revise is to review and verify whether to documentation is still correct or requires an update
B44: Comments and/or Remarks
B45: 2.11 | C45: Specify rationale for chosen values or any additional comments | L45: 2.1
L46: 2.2
L47: 2.3
L48: 2.4
L49: 2.5
L50: 2.6
L51: 2.7
L52: 2.8
L53: 2.9
L54: 2.10
B55: References
B56: NIST NICE framework, specifically the Cyber Defense Analyst and Incident Responder roles:
C57: https://www.nist.gov/itl/applied-cybersecurity/nice/nice-framework-resource-center/nice-framework-current-versions

Sheet People - PEM
B1: People
B3: 1. Employees | G3: 5. Training & Education
B4: 2. Roles and Hierarchy
B5: 3. People Management
B6: 4. Knowledge Management
A9: 3 | B9: People Management | L9: Answer | N9: Guidance | O9: Remarks
B10: 3.1 | C10: Do you have a job rotation plan in place? | N10: =VLOOKUP(_Output!D148,_Guidance!B314:C319,2,FALSE) | O10: Job rotation can be used to train employees in a variety of tasks and avoid too much routine
B11: 3.2 | C11: Do you have a career progression process in place? | N11: =VLOOKUP(_Output!D149,_Guidance!B320:C325,2,FALSE) | O11: Career development, promotion, etc.
B12: 3.3 | C12: Do you have a talent management process in place? | N12: =VLOOKUP(_Output!D150,_Guidance!B326:C331,2,FALSE) | O12: Talent should be adequately managed to retain such staff and fully develop their potential.
B13: 3.4 | C13: Do you have team diversity goals? | N13: =VLOOKUP(_Output!D151,_Guidance!B332:C337,2,FALSE) | O13: e.g. background diversity, ethnic diversity, gender diversity, etc.
B14: 3.5 | C14: Have you established team goals? | N14: =VLOOKUP(_Output!D997,_Guidance!B338:C343,2,FALSE) | O14: Team goals help to bring focus to the team and monitor progress
B15: 3.6 | C15: Do you document and track individual team member goals? | N15: =VLOOKUP(_Output!D998,_Guidance!B344:C349,2,FALSE) | O15: Individual team member goals should be set to help grow the employee to full potential
B16: 3.7 | C16: Do you periodically evaluate SOC employees? | N16: =VLOOKUP(_Output!D152,_Guidance!B350:C355,2,FALSE) | O16: Can also be included in the regular organization evaluation process
B17: 3.8 | C17: Do you have a 'new hire' process in place? | N17: =VLOOKUP(_Output!D153,_Guidance!B356:C361,2,FALSE) | O17: i.e. a defined process to quickly let new employees find their place and perform well in the SOC
B18: 3.9 | C18: Are all SOC employees subjected to screening? | N18: =VLOOKUP(_Output!D154,_Guidance!B362:C367,2,FALSE) | O18: Personnel screening is performed to avoid infiltration or misbehaviour by SOC employees
B19: 3.10 | C19: Do you measure employee satisfaction for improving the SOC? | N19: =VLOOKUP(_Output!D155,_Guidance!B368:C373,2,FALSE) | O19: Employee satisfaction should be taken seriously as lack of satisfaction may lead to key personnel leaving
B20: 3.11 | C20: Are there regular 1-on-1 meetings between the SOC manager and the employees? | N20: =VLOOKUP(_Output!D156,_Guidance!B374:C379,2,FALSE) | O20: Such informal 1-on-1 conversations are used to coach employees and help the SOC manager gain insight in personal challenges
B21: 3.12 | C21: Do you perform regular teambuilding exercises? | N21: =VLOOKUP(_Output!D157,_Guidance!B380:C385,2,FALSE) | O21: Teambuilding exercises are used to promote collaboration between individuals in the team and to raise team spirit
B22: 3.13 | C22: Do you perform regular teambuilding exercises with other teams relevant to the SOC? | N22: =VLOOKUP(_Output!D999,_Guidance!B386:C391,2,FALSE) | O22: In multi-team systems (MTS), the SOC collaborates with other teams. Use cross-team teambuilding to maximize performance
B23: 3.14 | C23: Do you periodically evaluate team performance? | N23: =VLOOKUP(_Output!D1000,_Guidance!B392:C397,2,FALSE) | O23: Besides individual performance, team performance and dynamics are also important to measure and improve on
B25: Comments and/or Remarks
B26: 3.15 | C26: Specify rationale for chosen values or any additional comments | L26: 3.1
L27: 3.2
L28: 3.3
L29: 3.4
L30: 3.5
L31: 3.6
L32: 3.7
L33: 3.8
L34: 3.9
L35: 3.10
L36: 3.11
L37: 3.12
L38: 3.13
L39: 3.14

Sheet People - KNM
B1: People
B3: 1. Employees | G3: 5. Training & Education
B4: 2. Roles and Hierarchy
B5: 3. People Management
B6: 4. Knowledge Management
A9: 4 | B9: Knowledge Management | L9: Answer | N9: Guidance | O9: Remarks
B10: 4.1 | C10: Do you have a formal knowledge management process in place? | N10: =VLOOKUP(_Output!D161,_Guidance!B400:C405,2,FALSE) | O10: Formal knowledge management helps to optimize knowledge creation and distribution
B11: 4.2 | C11: Do you have a skill matrix in place? | N11: =VLOOKUP(_Output!D1092,_Guidance!B406:C411,2,FALSE) | O11: A matrix may consist of: SOC skills, SOC employees and skill levels (novice, intermediate, expert)
B12: 4.3 | C12: Please specify elements of the skill matrix:
B13: 4.3.1 | C13: All SOC employees | O13: The skill matrix should cover all SOC employees, both internal and external
B14: 4.3.2 | C14: Hard skills | O14: e.g. ability to effectively use analysis tools
B15: 4.3.3 | C15: Soft skills | O15: e.g. communication skills
B16: 4.3.4 | C16: Skill levels (novice, intermediate, expert) | O16: Determining and documenting skill levels helps to identify areas where limited expertise is available
C17: Completeness | L17: =VLOOKUP(SUM(_Output!D1093:D1096),_SUM_Completeness!A197:B201,2,FALSE) -> Incomplete | O17: Use this outcome as a guideline to determine the score for 4.2
B18: 4.4 | C18: Is the skill matrix actively used for team and personal improvement? | N18: =VLOOKUP(_Output!D1097,_Guidance!B412:C417,2,FALSE) | O18: Personal improvement is essential, team improvement requires insight in team dynamics and skill distribution
B19: 4.5 | C19: Do you have a knowledge matrix in place? | N19: =VLOOKUP(_Output!D1098,_Guidance!B418:C423,2,FALSE)
B20: 4.6 | C20: Please specify elements of the knowledge matrix:
B21: 4.6.1 | C21: All SOC employees | O21: The knowledge matrix should cover all SOC employees, both internal and external
B22: 4.6.2 | C22: All relevant knowledge areas | O22: Knowledge for service delivery: technical (i.e. support), functional (i.e. configuration) and foundational (e.g. networking, encryption)
B23: 4.6.3 | C23: Knowledge levels (novice, intermediate, expert) | O23: Determining and documenting knowledge levels helps to identify areas where limited expertise is available
C24: Completeness | L24: =VLOOKUP(SUM(_Output!D1099:D1101),_SUM_Completeness!A204:B207,2,FALSE) -> Incomplete | O24: Use this outcome as a guideline to determine the score for 4.5
B25: 4.7 | C25: Is the knowledge matrix actively used to determine training and education needs? | N25: =VLOOKUP(_Output!D1102,_Guidance!B424:C429,2,FALSE) | O25: The matrix should be used as a means to identify and resolve knowledge gaps
B26: 4.8 | C26: Have you documented SOC team member abilities? | N26: =VLOOKUP(_Output!D1001,_Guidance!B430:C435,2,FALSE) | O26: Besides knowledge and skills, team member abilities are also important to document
B27: 4.9 | C27: Do you regularly assess and revise the knowledge management process? | N27: =VLOOKUP(_Output!D175,_Guidance!B436:C441,2,FALSE) | O27: This refers to the knowledge management process as a whole
B28: 4.10 | C28: Is there effective tooling in place to support knowledge documentation and distribution? | N28: =VLOOKUP(_Output!D176,_Guidance!B442:C447,2,FALSE) | O28: Such tooling can help to avoid investigation similar issues multiple times by integrating into the security monitoring process
B30: Comments and/or Remarks
B31: 4.11 | C31: Specify rationale for chosen values or any additional comments | L31: 4.1
L32: 4.2
L33: 4.3
L34: 4.4
L35: 4.5
L36: 4.6
L37: 4.7
L38: 4.8
L39: 4.9
L40: 4.10

Sheet People - T&E
B1: People
B3: 1. Employees | G3: 5. Training & Education
B4: 2. Roles and Hierarchy
B5: 3. People Management
B6: 4. Knowledge Management
A9: 5 | B9: Training and Education | L9: Answer | N9: Guidance | O9: Remarks
B10: 5.1 | C10: Do you have a training program in place? | N10: =VLOOKUP(_Output!D180,_Guidance!B450:C455,2,FALSE) | O10: A training program is used to ensure a minimal level of knowledge for employees
B11: 5.2 | C11: Please specify elements of the training program:
B12: 5.2.1 | C12: Training on the Job | O12: Training on the job can be done internally by senior employees or using external consultants
B13: 5.2.2 | C13: Product-specific training | O13: Product-specific training may be required for new technologies or complex solutions
B14: 5.2.3 | C14: Internal company training | O14: e.g. training on internal policies
B15: 5.2.4 | C15: Role-based specific training | O15: For example: security analysis training for the security analyst role
B16: 5.2.5 | C16: Soft-skill training | O16: To complement hard skills, soft skills should be trained as well
B17: 5.2.6 | C17: Formal education | O17: Formal education may be university or university college degrees
C18: Completeness | L18: =VLOOKUP(SUM(_Output!D182:D187),_SUM_Completeness!A69:B75,2,FALSE) -> Incomplete | O18: Use this outcome as a guideline to determine the score for 5.1
B19: 5.3 | C19: Do you have a certification program in place? | N19: =VLOOKUP(_Output!D188,_Guidance!B456:C461,2,FALSE) | O19: A certification program is used to provide a demonstrable minimum level of knowledge and skills
B20: 5.4 | C20: Please specify elements of the certification program:
B21: 5.4.1 | C21: Internal certification track | O21: Internal certifications may be in place to demonstrate knowledge of company processes and policies
B22: 5.4.2 | C22: External certification track | O22: Certification track with external certification organizations (e.g. ISACA, (ISC)2, SANS
B23: 5.4.3 | C23: Re-certification track (continuous education) | O23: Permanent education (PE) may be part of the certification itself
C24: Completeness | L24: =VLOOKUP(SUM(_Output!D190:D192),_SUM_Completeness!A78:B81,2,FALSE) -> Incomplete | O24: Use this outcome as a guideline to determine the score for 5.3
B25: 5.5 | C25: Is the training and certification program connected to evaluation and career progression? | N25: =VLOOKUP(_Output!D193,_Guidance!B462:C467,2,FALSE) | O25: e.g. certain training and certifications are required to grow from a junior level function to a more senior level function
B26: 5.6 | C26: Is there a reserved budget for education and training? | N26: =VLOOKUP(_Output!D194,_Guidance!B468:C473,2,FALSE) | O26: i.e. a fixed percentage of the total SOC budget that is allocated for education and cannot be used for other purposes
B27: 5.7 | C27: Is there a reserved amount of time for education and training? | N27: =VLOOKUP(_Output!D195,_Guidance!B474:C479,2,FALSE) | O27: This is an extension of education budget
B28: 5.8 | C28: Do you have regular workshops for knowledge development? | N28: =VLOOKUP(_Output!D196,_Guidance!B480:C485,2,FALSE) | O28: Workshops are an informal way of distributing knowledge
B29: 5.9 | C29: Do you regularly revise and update the training and certification programs? | N29: =VLOOKUP(_Output!D197,_Guidance!B486:C491,2,FALSE) | O29: Training and certification must be a relevant reflection of SOC knowledge and skill requirements
B31: Comments and/or Remarks
B32: 5.10 | C32: Specify rationale for chosen values or any additional comments | L32: 5.1
L33: 5.2
L34: 5.3
L35: 5.4
L36: 5.5
L37: 5.6
L38: 5.7
L39: 5.8
L40: 5.9

Sheet Process - MGT
B1: Process
B3: 1. SOC Management | G3: 5. Detection Engineering & Validation
B4: 2. Operations & Facilities | G4: 6. Automation Engineering
B5: 3. Reporting & Communication | G5: 7. Log Management
B6: 4. Use Case Management
A9: 1 | B9: SOC Management | L9: Answer | N9: Guidance | P9: Remarks
B10: 1.1 | C10: Is there a SOC management process in place? | N10: =VLOOKUP(_Output!D202,_Guidance!B495:C500,2,FALSE) | P10: A SOC management process is used to manage all aspects SOC service delivery and quality
B11: 1.2 | C11: Are SOC management elements formally identified and documented? | N11: =VLOOKUP(_Output!D203,_Guidance!B501:C506,2,FALSE) | P11: Possible SOC management elements can be found in under 1.3
B12: 1.3 | C12: Please specify identified SOC management elements:
B13: 1.3.1 | C13: Internal relationship management | P13: Relationship management within the organization
B14: 1.3.2 | C14: External relationship management | P14: Relationship management outside of the organization
B15: 1.3.3 | C15: Vendor management | P15: Relationship management with relevant vendors for SOC technologies
B16: 1.3.4 | C16: Continuous service improvement | P16: A methodology for continuously improving on SOC service delivery and internal processes supporting service delivery
B17: 1.3.5 | C17: Project methodology | P17: For example: LEAN or agile project approach
B18: 1.3.6 | C18: Process documentation and diagrams | P18: Any documentation on SOC processes or services. May contains diagrams explaining relationships between processes
B19: 1.3.7 | C19: RACI matrix | P19: A description of all SOC responsibilities, accountabilities and cases in which the SOC is informed or consulted
B20: 1.3.8 | C20: Service Catalogue | P20: A description of all SOC services and service levels
B21: 1.3.9 | C21: Service on-boarding procedure | P21: Procedure for intake, evaluation and move-to-production for requests for new services or customers
B22: 1.3.10 | C22: Service off-loading procedure | P22: Procedure to remove existing services and customers from service delivery
C23: Completeness | L23: =VLOOKUP(SUM(_Output!D205:D214),_SUM_Completeness!A45:B55,2,FALSE) -> Incomplete | P23: Use this outcome as a guideline to determine the score for 1.2
B24: 1.4 | C24: Is the SOC management process regularly reviewed? | N24: =VLOOKUP(_Output!D215,_Guidance!B507:C512,2,FALSE) | P24: Regular review of the SOC management process ensures optimal performance
B25: 1.5 | C25: Is the SOC management process aligned with all stakeholders? | N25: =VLOOKUP(_Output!D216,_Guidance!B513:C518,2,FALSE) | P25: Alignment with stakeholders will ensure the SOC delivers services that meet customer expectations
B26: 1.6 | C26: Have you implemented a process for continuous improvement (CI)? | N26: =VLOOKUP(_Output!D1104,_Guidance!B519:C524,2,FALSE) | P26: Continuous improvement is a vital process for SOCs to evolve their capabilities
B27: 1.7 | C27: Specify elements of the continuous improvement program:
B28: 1.7.1 | C28: Daily progress tracking | P28: Daily progress tracking is used to identify (blocking) issues, determine priorities and request help for certain activities
B29: 1.7.2 | C29: Weekly planning | P29: Weekly planning is done to create a balanced improvement workload for the team
B30: 1.7.3 | C30: Backlog management | P30: Managing the backlog includes structuring the backlog and grooming the backlog
B31: 1.7.4 | C31: Work item effort estimation | P31: Work item estimation (through t-shirt sizing, or more accurate estimation) is essential to realistic planning
B32: 1.7.5 | C32: Work item prioritisation | P32: Prioritisation of work items should follow a defined prioritisation method and be done by the owner of the backlog
B33: 1.7.6 | C33: Refinement | P33: Refinement of items, including a definition of ready, is required to ensure all team members understand the task at hand
B34: 1.7.7 | C34: Capacity for change | P34: Having a reserved capacity for change ensures the improvement is continuous, and not overtaken by operational tasks
B35: 1.7.8 | C35: Velocity measurement & improvement | P35: Measuring and improving team velocity is a good way to accelerate continuous improvement in the SOC
B36: 1.7.9 | C36: Retrospectives | P36: Retrospectives are useful for evalaution of the improvement process
C37: Completeness | L37: =VLOOKUP(SUM(_Output!D1299:D1305,_Output!D1378:D1379),_SUM_Completeness!A210:B219,2,FALSE) -> Incomplete | P37: Use this outcome as a guideline to determine the score for 1.6
B38: 1.8 | C38: Have you implemented a process to manage SOC quality assurance (QA)? | N38: =VLOOKUP(_Output!D1105,_Guidance!B525:C530,2,FALSE) | P38: Quality assurance is aimed at ensuring SOC processes, technology and services meet their quality requirements
B39: 1.9 | C39: Please specify elements of the quality assurance program:
B40: 1.9.1 | C40: Ticket quality assurance | P40: Correct and timely analysis of alerts, including correct usage of playbooks
B41: 1.9.2 | C41: Incident quality assurance | P41: Correct and timely follow-up of incidents, including correctly following the incident response procedures
B42: 1.9.3 | C42: Service quality assurance | P42: Delivery of services in accordance with established quality criteria
B43: 1.9.4 | C43: Process quality assurance | P43: Execution of processes in accordance with established quality criteria
B44: 1.9.5 | C44: Report quality assurance | P44: Correct and timely report provisioning
B45: 1.9.6 | C45: Peer review | P45: Peer review is a good tool to check the quality and accuracy of SOC deliverables
C46: Completeness | L46: =VLOOKUP(SUM(_Output!D1307:D1311,_Output!D1380),_SUM_Completeness!A222:B228,2,FALSE) -> Incomplete | P46: Use this outcome as a guideline to determine the score for 1.8
B47: 1.10 | C47: Have you implemented a SOC architecture process? | N47: =VLOOKUP(_Output!D1312,_Guidance!B531:C536,2,FALSE) | P47: A SOC architecture describes how different components
B48: 1.11 | C48: Please specify elements of the SOC architecture:
B49: 1.11.1 | C49: SOC process architecture | P49: A process architecture outlines the different processes within the SOC and how they interact / integrate
B50: 1.11.2 | C50: SOC technology architecture | P50: A technology architecture outlines the different technologies used within the SOC and how they interact / integrate
B51: 1.11.3 | C51: SOC service architecture | P51: A service architecture outlines the different services used within the SOC and how they interact / integrate
B52: 1.11.4 | C52: Architecture diagrams | P52: Architecture diagrams are visualisations of components and integrations
B53: 1.11.5 | C53: Architecture principles | P53: Architecture principles are guidelines for implementing processes, technology & services
C54: Completeness | L54: =VLOOKUP(SUM(_Output!D1314:D1318),_SUM_Completeness!A231:B236,2,FALSE) -> Incomplete | P54: Use this outcome as a guideline to determine the score for 1.10
B56: Comments and/or Remarks
B57: 1.8 | C57: Specify rationale for chosen values or any additional comments | L57: 1.1
L58: 1.2
L59: 1.3
L60: 1.4
L61: 1.5
L62: 1.6
L63: 1.7
L64: 1.8
L65: 1.9
L66: 1.10
L67: 1.11

Sheet Process - O&F
B1: Process
B3: 1. SOC Management | G3: 5. Detection Engineering & Validation
B4: 2. Operations & Facilities | G4: 6. Automation Engineering
B5: 3. Reporting & Communication | G5: 7. Log Management
B6: 4. Use Case Management
A9: 2 | B9: Operations and Facilities | L9: Answer | N9: Guidance | P9: Remarks
B10: 2.1 | C10: Security operations exercises
B11: 2.1.1 | C11: Do you have a documented exercise plan? | N11: =VLOOKUP(_Output!D1109,_Guidance!B538:C543,2,FALSE) | P11: An exercise plan lists the type of exercises to be conducted, the frequency and the exercise goals
B12: 2.1.2 | C12: Please specify types of exercises included in the plan
B13: 2.1.2.1 | C13: Table-top exercises | P13: Table-top exercises are an easy way to go through a scenario and determine if all procedures and actions are clear
B14: 2.1.2.2 | C14: Playbook drills | P14: Playbook drills are low-level exercises to test the accuracy, effectiveness, and efficiency of playbooks
B15: 2.1.2.3 | C15: Cyber range | P15: Cyber range exercises provide a simulated environment that is used to train analysts. A simulation of the actual IT environment is preferred
B16: 2.1.2.4 | C16: Capture the flag | P16: A capture the flag event is a gamification for security analysts, in which they must achieve a specified goal
B17: 2.1.2.5 | C17: Purple/Red/Black team exercises | P17: These are types of exercises to conduct an actual attack against the organisation, without malicious intent
B18: 2.1.2.6 | C18: Public exercises [1] | P18: Public exercises are exercises that the organisation can participate in. Often, these are large-scale exercises
C19: Completeness | L19: =VLOOKUP(SUM(_Output!D1110:D1115),_SUM_Completeness!A168:B174,2,FALSE) -> Incomplete | P19: Use this outcome as a guideline to determine the score for 2.1.1
B20: 2.1.3 | C20: Do you perform security operations exercises regularly? | N20: =VLOOKUP(_Output!D221,_Guidance!B544:C549,2,FALSE) | P20: Regularity should be matched to your own internal policy
B21: 2.1.4 | C21: Are the results from exercises documented? | N21: =VLOOKUP(_Output!D1116,_Guidance!B550:C555,2,FALSE) | P21: Results from exercises should be structurally documented for future reference and identification of improvements
B22: 2.1.5 | C22: Is the output from exercises actively used to improve security operations? | N22: =VLOOKUP(_Output!D1117,_Guidance!B556:C561,2,FALSE) | P22: Exercise output should be used to structurally improve security operations
B23: 2.2 | C23: Service delivery standardization
B24: 2.2.1 | C24: Do you have standard operating procedures? | N24: =VLOOKUP(_Output!D222,_Guidance!B562:C567,2,FALSE) | P24: Standard operating procedures are used to provide consistent output
B25: 2.2.2 | C25: Do you use checklists for recurring activities? | N25: =VLOOKUP(_Output!D223,_Guidance!B568:C573,2,FALSE) | P25: Checklists can be useful to avoid recurring activities from being overlooked
B26: 2.2.3 | C26: Do you use documented workflows? | N26: =VLOOKUP(_Output!D224,_Guidance!B574:C579,2,FALSE) | P26: Workflows are used to standardize steps in, for example, security analysis
B27: 2.2.4 | C27: Do you have a SOC operational handbook? | N27: =VLOOKUP(_Output!D225,_Guidance!B580:C585,2,FALSE) | P27: A SOC operational handbook contains an overview of SOC tasks, as well as rules of engagement and expected behaviour
B28: 2.2.5 | C28: Have you established an Operational Security (OPSEC) program? | N28: =VLOOKUP(_Output!D1003,_Guidance!B586:C591,2,FALSE) | P28: An OPSEC program dictates security rules to ensure the integrity and confidentiality of SOC processes, tools and information
B29: 2.2.6 | C29: Have you defined emergency reachability for the SOC? | P29: An emergency reachability process ensures availability of SOC incident response and escalation
B30: 2.3 | C30: Process integration
B31: 2.3.1 | C31: Are ITSM processes integrated in the SOC? | N31: =VLOOKUP(_Output!D1383,_Guidance!B598:C603,2,FALSE) | P31: SOC services and procedures should be aligned and integrated with the organization's ITSM processes
B32: 2.3.2 | C32: Please specify the ITSM processes integrated in the SOC
B33: 2.3.2.1 | C33: configuration management | P33: Configuration management means including SOC tooling configurations into the CMDB, and knowledge of IT/OT asset configuration
B34: 2.3.2.2 | C34: change management | P34: Change management applies to changes to SOC tooling, and informing the SOC of upcoming changes
B35: 2.3.2.3 | C35: problem management | P35: Problem management applies to recurring incidents in the SOC, both operational and security incidents
B36: 2.3.2.4 | C36: incident management | P36: Incident management applies to operational and security incidents in the SOC
B37: 2.3.2.5 | C37: asset management | P37: Asset management means including SOC tooling assets into the CMDB, and knowledge of organisational IT/OT assets
C38: Completeness | L38: =VLOOKUP(SUM(_Output!D1384:D1388),_SUM_Completeness!A239:B2422,2,FALSE) -> Incomplete | P38: Use this outcome as a guideline to determine the score for 2.3.1
B39: 2.3.3 | C39: Are ITSM processes integrations regularly evaluated? | N39: =VLOOKUP(_Output!D1389,_Guidance!B604:C609,2,FALSE) | P39: ITSM process integrations must be regularly evaluated to find optimizations and shortcomings
B40: 2.4 | C40: SOC Facilities
B41: 2.4.1 | C41: Do you have a dedicated physical SOC location? | N41: =VLOOKUP(_Output!D1390,_Guidance!B610:C615,2,FALSE) | P41: A dedicated physical location decreases likelihood of unauthorized access and provides confidentiality for security incidents
B42: 2.4.2 | C42: Please specify the physical elements in the SOC
B43: 2.4.1.1 | C43: SOC war room | P43: A dedicated facility for coordination of major security incidents
B44: 2.4.1.2 | C44: Dedicated SOC network | P44: Given the confidentiality of the SOC and the importance of monitoring, it is recommended to use a separate network
B45: 2.4.1.3 | C45: Physical access control | P45: e.g. key cards (badges) for access with access logging, biometrics, etc.
B46: 2.4.1.4 | C46: Secure physical storage | P46: Secure storage facilities can be used to store evidence collected during investigations or other operational security purposes
B47: 2.4.1.5 | C47: Video wall | P47: A video wall can be used to display the real-time security status and can be used for decision making as well as PR
B48: 2.4.1.6 | C48: Resilient messaging capability | P48: Messaging system to support communication and coordination, that matches SOC requirements
B49: 2.4.1.7 | C49: Resilient internet access | P49: Internet access for the SOC, set up according to SOC requirements. May include dedicated internet lines
B50: 2.4.1.9 | C50: Specialized analyst workstations | P50: e.g. multiple screen setup, virtual machines, etc.
C51: Completeness | L51: =VLOOKUP(SUM(_Output!D1391:D1397) + _Output!D1472,_SUM_Completeness!A247:B2523,2,FALSE) -> Incomplete | P51: Use this outcome as a guideline to determine the score for 2.4.1
B52: 2.4.3 | C52: Have you optimized secure remote working capabilities for SOC employees? | N52: =VLOOKUP(_Output!D1006,_Guidance!B616:C621,2,FALSE) | P52: Secure working enabled means secure access (MFA, encryption, etc.), secure working facilitated also means equipped and optimized
B53: 2.5 | C53: Operational shifts
B54: 2.5.1 | C54: Have you implemented shifts in the SOC? | N54: =VLOOKUP(_Output!D1398,_Guidance!B622:C627,2,FALSE) | P54: Shifts are required for reliable and consistent service delivery in the SOC
B55: 2.5.2 | C55: Please specify the elements and artefacts of your shift
B56: 2.5.2.1 | C56: Shift schedule | P56: Shift schedules are used to ensure full shift coverage
B57: 2.5.2.2 | C57: Shift log | P57: A shift log covers all exceptions found during the shift, running investigations, etc.
B58: 2.5.2.3 | C58: Shift turnover | P58: i.e. a procedure for handing over a shift and exchanging information regarding running tasks or issues for further follow-up
B59: 2.5.2.4 | C59: Shift checklist | P59: i.e. a checklist of activities and tasks that need to be conducted during the shift
B60: 2.5.2.5 | C60: Shift completeness | P60: A complete shift covers all operational hours, with backups in case of unexpected events
C61: Completeness | L61: =VLOOKUP(SUM(_Output!D1399:D1403),_SUM_Completeness!A258:B263,2,FALSE) -> Incomplete | P61: Use this outcome as a guideline to determine the score for 2.5.1
B62: 2.5.2 | C62: Have schedules been optimized for vigilance during shifts? | N62: =VLOOKUP(_Output!D1007,_Guidance!B628:C633,2,FALSE) | P62: Schedules should be created to optimize vigilance. Thus, shift should include mandatory breaks and not be too long
B63: 2.5.3 | C63: Do you have a daily SOC operational stand-up? | N63: =VLOOKUP(_Output!D243,_Guidance!B634:C639,2,FALSE) | P63: This can also be a call in case physical attendance is not possible for all attendees
B64: 2.5.4 | C64: Do you have stand-by arrangements with employees within the SOC? | N64: =VLOOKUP(_Output!D244,_Guidance!B640:C645,2,FALSE) | P64: i.e. is there a formal stand-by function that obligates employees to be able to be reached within a certain time?
B65: 2.6 | C65: Knowledge & document management
B66: 2.6.1 | C66: Do you have a Document Management System in place? | N66: =VLOOKUP(_Output!D246,_Guidance!B646:C651,2,FALSE) | P66: The system should support different file types, authorizations and version management; possibly even encryption
B67: 2.6.2 | C67: Do you have a knowledge & collaboration platform in place? | N67: =VLOOKUP(_Output!D247,_Guidance!B652:C657,2,FALSE) | P67: e.g. a wiki space or SharePoint that allows collaboration and supports team efforts
B69: Comments and/or Remarks
B70: 2.7 | C70: Specify rationale for chosen values or any additional comments | L70: 2.1.1
L71: 2.1.2
L72: 2.1.3
C73: References | L73: 2.1.4
C74: [1] public exercises may include exercises like: | L74: 2.1.5
C75: - FS-ISAC CAPS (payment systems) | L75: 2.2.1
C76: https://www.fsisac.com/resilience/exercises | L76: 2.2.2
C77: - CISA Cyber Storm | L77: 2.2.3
C78: https://www.cisa.gov/cyber-storm-securing-cyber-space | L78: 2.2.4
L79: 2.2.5
C80: [2] Methodologies for setting up exercises may include: | L80: 2.3.1
C81: https://www.enisa.europa.eu/publications/the-enisa-cybersecurity-exercise-methodology | L81: 2.3.2
L82: 2.3.3
L83: 2.4.1
L84: 2.4.2
L85: 2.4.3
L86: 2.5.1
L87: 2.5.2
L88: 2.5.3
L89: 2.5.4
L90: 2.6.1
L91: 2.6.2

Sheet Process - RPT
B1: Process
B3: 1. SOC Management | G3: 5. Detection Engineering & Validation
B4: 2. Operations & Facilities | G4: 6. Automation Engineering
B5: 3. Reporting & Communication | G5: 7. Log Management
B6: 4. Use Case Management
A9: 3 | B9: Reporting & communication | L9: Answer | N9: Guidance | P9: Remarks
B10: 3.1 | C10: Reports
B11: 3.1.1 | C11: Do you regularly provide reports? | N11: =VLOOKUP(_Output!D251,_Guidance!B660:C665,2,FALSE) | P11: Regular reports help to keep customers informed of SOC activities
B12: 3.1.2 | C12: Are these reports tailored to the recipients? | N12: =VLOOKUP(_Output!D252,_Guidance!B666:C671,2,FALSE) | P12: e.g. management reports for senior management, technical reports for the IT organization
B13: 3.1.3 | C13: Are the report contents approved by or reviewed by the recipients? | N13: =VLOOKUP(_Output!D253,_Guidance!B672:C677,2,FALSE) | P13: formal sign-off can be part of a larger service delivery sign-off
B14: 3.1.4 | C14: Do you have established reporting lines within the organization? | N14: =VLOOKUP(_Output!D254,_Guidance!B678:C683,2,FALSE) | P14: e.g. reporting lines could be: SOC management, IT management, senior management
B15: 3.1.5 | C15: Do you regularly revise and update the report templates? | N15: =VLOOKUP(_Output!D255,_Guidance!B684:C689,2,FALSE) | P15: Report templates should be regularly optimized to ensure continued
B16: 3.1.6 | C16: Do you have formal agreements with the recipients regarding reports? | N16: =VLOOKUP(_Output!D256,_Guidance!B690:C695,2,FALSE) | P16: For example: timelines of delivery, report contents, etc.
B17: 3.1.7 | C17: Do you provide different types of reports to your recipients? | N17: =VLOOKUP(_Output!D1118,_Guidance!B696:C701,2,FALSE) | P17: Different types of reports provide more insight into security operations
B18: 3.1.8 | C18: Please specify SOC report types:
B19: 3.1.8.1 | C19: Technical security reports | P19: i.e. reports regarding technical issues or technical solutions to security issues
B20: 3.1.8.2 | C20: Executive security reports | P20: i.e. reports aimed at senior executives to inform them of SOC services
B21: 3.1.8.3 | C21: Operational reports | P21: i.e. reports regarding security operations in general
B22: 3.1.8.4 | C22: Incident reports | P22: Ad-hoc reports created to provide insight into incidents. This can also be part of incident management
B23: 3.1.8.5 | C23: Newsletter or digest | P23: A newsletter can be an informal way to provide updates to the organization
B24: 3.1.8.6 | C24: KPI reports | P24: KPI reports are used to measure service performance
B25: 3.1.8.7 | C25: Trend reports | P25: Trend reports can be used to determine changes over time
B26: 3.1.8.8 | C26: Real-time reporting dashboards | P26: Real-time reporting dashboards provide immediate insight into the current performance level
C27: Completeness | L27: =VLOOKUP(SUM(_Output!D1119:D1126),_SUM_Completeness!A177:B185,2,FALSE) -> Incomplete | P27: Use this outcome as a guideline to determine the score for 3.1.7
B28: 3.2 | C28: Metrics
B29: 3.2.1 | C29: Do you use different types of metrics in your reports? | N29: =VLOOKUP(_Output!D1127,_Guidance!B702:C707,2,FALSE) | P29: Different types of metrics provide more insight into security operations
B30: 3.2.2 | C30: Please specify SOC metric types[1]
B31: 3.2.2.1 | C31: Are quantitative metrics used in reports? | P31: Event count, false-positive rate, number of service requests, etc.
B32: 3.2.2.2 | C32: Are qualitative metrics used in reports? | P32: i.e. risk level, customer satisfaction
B33: 3.2.2.3 | C33: Are incident & case metrics used in reports? | P33: e.g. the number of cases and incidents, number of incidents detected by SOC, average cost per incident, etc.
B34: 3.2.2.4 | C34: Are timing metrics used in reports? | P34: Time to detect, time to contain, time to eradicate
B35: 3.2.2.5 | C35: Are metrics regarding SLAs used in reports? | P35: e.g. service availability, incidents handled within agreed time period, etc.
B36: 3.2.2.6 | C36: Are proactive and reactive metrics used in reports? | P36: Proactive metrics can help to show how the team is actively preventing incidents from occurring
C37: Completeness | L37: =VLOOKUP(SUM(_Output!D1128:D1133),_SUM_Completeness!A188:B194,2,FALSE) -> Incomplete | P37: Use this outcome as a guideline to determine the score for 3.2.1
B38: 3.3 | C38: Advisories
B39: 3.3.1 | C39: Do you provide advisories to the organization regarding threats and vulnerabilities? | N39: =VLOOKUP(_Output!D273,_Guidance!B708:C713,2,FALSE) | P39: Advisories are used to inform customers of security threats and vulnerabilities
B40: 3.3.2 | C40: Do you perform risk / impact assessments of these advisories? | N40: =VLOOKUP(_Output!D274,_Guidance!B714:C719,2,FALSE) | P40: i.e. do you add organizational context to these advisories?
B41: 3.3.3 | C41: Do you perform follow-up of these advisories? | N41: =VLOOKUP(_Output!D275,_Guidance!B720:C725,2,FALSE) | P41: i.e. do you assist in coordination when required?
B42: 3.4 | C42: Education and Awareness
B43: 3.4.1 | C43: Do you provide education and security awareness to the organization? | N43: =VLOOKUP(_Output!D1009,_Guidance!B726:C731,2,FALSE) | P43: The SOC may be involved in security awareness and education to make users in the organisation aware of their role in cyber security
B44: 3.4.2 | C44: Do you measure the effect of education and security awareness efforts? | N44: =VLOOKUP(_Output!D1010,_Guidance!B732:C737,2,FALSE) | P44: Measuring the efforts is necessary for improvement of the security awareness function
B45: 3.5 | C45: Communication
B46: 3.5.1 | C46: Do you use communication templates? | N46: =VLOOKUP(_Output!D1011,_Guidance!B738:C743,2,FALSE) | P46: Communication templates help to standardize and professionalize SOC communication to stakeholders
B47: 3.5.2 | C47: Do you have a communication matrix in place? | N47: =VLOOKUP(_Output!D1012,_Guidance!B744:C749,2,FALSE) | P47: A communication matrix can be used to decide when, how and with whom to communicate
B48: 3.5.3 | C48: Is communication training (verbal/written) available for SOC personnel? | N48: =VLOOKUP(_Output!D1013,_Guidance!B750:C755,2,FALSE) | P48: Communication training helps SOC personnel to communicate effectively
B49: 3.5.4 | C49: Are communication skills element of SOC role descriptions? | N49: =VLOOKUP(_Output!D1014,_Guidance!B756:C761,2,FALSE) | P49: Communication skills are important for analysts to explain their findings and recommendations
B51: Comments and/or Remarks
B52: 3.6 | C52: Specify rationale for chosen values or any additional comments | L52: 3.1.1
L53: 3.1.2
B54: [1] SOC-CMM has published a metrics suite that can serve as a starting point: | L54: 3.1.3
B55: https://www.soc-cmm.com/products/metrics/ | L55: 3.1.4
L56: 3.1.5
L57: 3.1.6
L58: 3.1.7
L59: 3.1.8
L60: 3.2.1
L61: 3.2.2
L62: 3.3.1
L63: 3.3.2
L64: 3.3.3
L65: 3.4.1
L66: 3.4.2
L67: 3.5.1
... L70: 3.5.4

Sheet Process - UCM
B1: Process
B3: 1. SOC Management | G3: 5. Detection Engineering & Validation
B4: 2. Operations & Facilities | G4: 6. Automation Engineering
B5: 3. Reporting & Communication | G5: 7. Log Management
B6: 4. Use Case Management
A9: 4 | B9: Use Case Management | L9: Answer | N9: Guidance | P9: Remarks
B10: 4.1 Use Case Management
B11: 4.1.1 | C11: Is there a use case management process or framework in place? | N11: =VLOOKUP(_Output!D279,_Guidance!B764:C769,2,FALSE) | P11: A framework, such as MaGMa UCF[1], can be used to guide use case lifecycle and document use case in a standardized format
B12: 4.1.2 | C12: Are use cases formally documented? | N12: =VLOOKUP(_Output!D282,_Guidance!B770:C775,2,FALSE) | P12: Formal documentation may include use case documentation templates
B13: 4.1.3 | C13: Are use cases approved by relevant stakeholders? | N13: =VLOOKUP(_Output!D285,_Guidance!B776:C781,2,FALSE) | P13: e.g. business stakeholders, IT stakeholders, CISOs, audit & compliance, risk management, etc.
B14: 4.1.4 | C14: Is the use case management process aligned with other important processes? | N14: =VLOOKUP(_Output!D288,_Guidance!B782:C787,2,FALSE) | P14: e.g. integration with the threat / risk management process to revise use cases when the threat landscape changes
B15: 4.1.5 | C15: Are use cases created using a standardized process? | N15: =VLOOKUP(_Output!D292,_Guidance!B788:C793,2,FALSE) | P15: i.e. a standardized approach to derive use cases from threats or business requirements
B16: 4.1.6 | C16: Are use cases created using a top-down approach? | N16: =VLOOKUP(_Output!D295,_Guidance!B794:C799,2,FALSE) | P16: e.g. use cases can be derived from business requirements, risk assessments, threat management / intelligence
B17: 4.1.7 | C17: Can use cases be traced from high-level drivers to low-level implementation? | N17: =VLOOKUP(_Output!D298,_Guidance!B800:C805,2,FALSE) | P17: Top-down traceability is important to determine completeness of implementation and demonstrable risk reduction
B18: 4.1.8 | C18: Can use cases be traced from low-level implementation to high-level drivers? | N18: =VLOOKUP(_Output!D301,_Guidance!B806:C811,2,FALSE) | P18: Bottom-up traceability is important for contextualizing use case output and business alignment
B19: 4.1.9 | C19: Are use cases measured for implementation and effectiveness? | N19: =VLOOKUP(_Output!D307,_Guidance!B812:C817,2,FALSE) | P19: Metrics can be applied to use cases to determine growth and maturity by measuring effectiveness and implementation
B20: 4.1.10 | C20: Are use cases scored and prioritized based on risk levels? | N20: =VLOOKUP(_Output!D310,_Guidance!B818:C823,2,FALSE) | P20: Risks can be (cyber)threats, but also non-compliance or penalties (laws & regulations)
B21: 4.1.11 | C21: Are use cases regularly revised and updated? | N21: =VLOOKUP(_Output!D313,_Guidance!B824:C829,2,FALSE) | P21: Use cases should be subjected to life cycle management and may require updates or may be outdated and decommissioned
B23: 4.2 Mitre ATT&CK® / Threat Intelligence
B24: 4.2.1 | C24: Do you measure use cases against the MITRE ATT&CK® framework for gap analysis purposes? | N24: =VLOOKUP(_Output!D1015,_Guidance!B830:C835,2,FALSE) | P24: By measuring use cases against MITRE ATT&CK®, it is possible to determine strengths and weaknesses in your layered detection approach
B25: 4.2.2 | C25: Are monitoring rules tagged with MITRE ATT&CK® framework identifiers? [2] | N25: =VLOOKUP(_Output!D1016,_Guidance!B836:C841,2,FALSE) | P25: Tagging monitoring rules with MITRE ATT&CK® identifiers allows for reporting on sightings of attack techniques
B26: 4.2.3 | C26: Have you created a MITRE ATT&CK® risk profile for your organization? | N26: =VLOOKUP(_Output!D1017,_Guidance!B842:C847,2,FALSE) | P26: The creation of a risk profile in MITRE ATT&CK® can help to identify relevant attack techniques
B27: 4.2.4 | C27: Have you prioritized MITRE ATT&CK® techniques for relevance? [3] | N27: =VLOOKUP(_Output!D1018,_Guidance!B848:C853,2,FALSE) | P27: Using organizational context (protection and detection mechanisms), ATT&CK® techniques can be prioritized
B28: 4.2.5 | C28: Is use case output (alerts) used in threat intelligence activities? | N28: =VLOOKUP(_Output!D1019,_Guidance!B854:C859,2,FALSE) | P28: Using MITRE ATT&CK®, it is possible to connect alerts to specific threat actors, or potentially even active campaigns
B29: 4.2.6 | C29: Is threat intelligence used for the creation and updates of use cases? | N29: =VLOOKUP(_Output!D1020,_Guidance!B860:C865,2,FALSE) | P29: Threat intelligence can provide input into security monitoring, especially when using MITRE ATT&CK® to connect both
B31: 4.3 Visibility
B32: 4.3.1 | C32: Do you determine and document visibility requirements for each use case? | N32: =VLOOKUP(_Output!D1021,_Guidance!B866:C871,2,FALSE) | P32: Data source requirements should be part of use case design
B33: 4.3.2 | C33: Do you measure visibility status for your use cases for gap analysis purposes? | N33: =VLOOKUP(_Output!D1022,_Guidance!B872:C877,2,FALSE) | P33: Measuring visibility status of use cases will help to identify use cases that require additional data sources for detection optimization
B34: 4.3.3 | C34: Do you map data source visibility to the MITRE ATT&CK® framework? [4] | N34: =VLOOKUP(_Output!D1023,_Guidance!B878:C883,2,FALSE) | P34: Mapping available data sources to MITRE ATT&CK® data source requirements will help identify gaps in visibility of attack techniques
B36: Comments and/or Remarks
B37: 4.4 | C37: Specify rationale for chosen values or any additional comments | L37: 4.1.1
L38: 4.1.2
B39: [1] The MaGMa Use Case Framework is a framework and tool for use case management created by the Dutch financial sector and can be obtained from the following location: | L39: 4.1.3
L40: 4.1.4
B41: https://www.betaalvereniging.nl/en/safety/magma/ | L41: 4.1.5
B42: [2] The OSSEM Detection Model can be useful: | L42: 4.1.6
B43: https://github.com/OTRF/OSSEM | L43: 4.1.7
B44: [3] A useful resource can be the Mitre Assistant | L44: 4.1.8
B45: https://www.allarounddefender.io/home | L45: 4.1.9
B46: [4] For example, using the DeTT&CT tooling: | L46: 4.1.10
B47: https://github.com/rabobank-cdc/DeTTECT | L47: 4.1.11
L48: 4.2.1
L49: 4.2.2
L50: 4.2.3
L51: 4.2.4
L52: 4.2.5
L53: 4.2.6
L54: 4.3.1
L55: 4.3.2
L56: 4.3.3

Sheet Process - DTE
B1: Process
B3: 1. SOC Management | G3: 5. Detection Engineering & Validation
B4: 2. Operations & Facilities | G4: 6. Automation Engineering
B5: 3. Reporting & Communication | G5: 7. Log Management
B6: 4. Use Case Management
A9: 5 | B9: Detection Engineering & Validation | L9: Answer | N9: Guidance | P9: Remarks
B10: 5.1 Detection Engineering
B11: 5.1.1 | C11: Do you have a detection engineering process in place? | N11: =VLOOKUP(_Output!D1026,_Guidance!B886:C891,2,FALSE) | P11: A detection engineering process supports the creation and deployment of detection rules for security monitoring purposes
B12: 5.1.2 | C12: Is the detection engineering process formally documented? | N12: =VLOOKUP(_Output!D1027,_Guidance!B892:C897,2,FALSE) | P12: Formal documentation supports process standardisation, and allows for faster training of new engineers
B13: 5.1.3 | C13: Are there specific roles and requirements for detection engineers? | N13: =VLOOKUP(_Output!D1028,_Guidance!B898:C10075,2,FALSE) | P13: Detection engineers have a skillset that is different from security analysts and security engineers
B14: 5.1.4 | C14: Is there active cooperation between the SOC analysts and the detection engineers? | N14: =VLOOKUP(_Output!D1029,_Guidance!B904:C10081,2,FALSE) | P14: SOC analyst deal with alerts resulting from detections created by engineers, so a tight interaction is required to optimize the ruleset
B15: 5.1.5 | C15: Is there active cooperation between the Threat Intelligence analysts and detection engineers? | N15: =VLOOKUP(_Output!D1030,_Guidance!B910:C915,2,FALSE) | P15: Threat intelligence is a major input into the creation or updating of detection rules
B16: 5.1.6 | C16: Are there formal hand-over to the analyst team? | N16: =VLOOKUP(_Output!D1031,_Guidance!B916:C921,2,FALSE) | P16: Once the detections are created, they must be operationalized. This should be done with a formal hand-over to production
B17: 5.1.7 | C17: Is there a testing enviroment to test and validate detections before deploying them? | N17: =VLOOKUP(_Output!D1032,_Guidance!B922:C927,2,FALSE) | P17: A testing environment allows for thorough testing of new detections, which ensures a higher level of quality
B18: 5.1.8 | C18: Is there a formal release process in place for new detections? | N18: =VLOOKUP(_Output!D1033,_Guidance!B928:C933,2,FALSE) | P18: A formal release process includes automated deployment of rules and adheres to organizational change management procedures
B19: 5.1.9 | C19: Do you apply a versioning system to detections? | N19: =VLOOKUP(_Output!D1034,_Guidance!B934:C939,2,FALSE) | P19: A versioning system will allow to revert back to previous versions of detections
B20: 5.1.10 | C20: Do you have a roll-back procedure in place in case of problems with detections? | N20: =VLOOKUP(_Output!D1035,_Guidance!B940:C945,2,FALSE) | P20: A roll-back procedure enabled reverting back to a good state if a deployment has an adverse effect on security monitoring
B22: 5.2 Detection validation
B23: 5.2.1 | C23: Do you perform adversary emulation or automated detection testing? [1] | N23: =VLOOKUP(_Output!D1036,_Guidance!B946:C951,2,FALSE) | P23: These validation activities provides insights into how well security monitoring is able to detect certain adversaries or attack techniques
B24: 5.2.2 | C24: Do you test for detection of MITRE ATT&CK® techniques? | N24: =VLOOKUP(_Output!D1037,_Guidance!B952:C957,2,FALSE) | P24: Testing for MITRE ATT&CK® techniques can augment mapping of use cases and visibility in Mitre ATT&CK
B25: 5.2.3 | C25: Do you test detection analytics not directly associated with MITRE ATT&CK®? | N25: =VLOOKUP(_Output!D1038,_Guidance!B958:C963,2,FALSE) | P25: Not all use cases and risks have a relationship to MITRE ATT&CK®. These use cases should be tested as well
B26: 5.2.4 | C26: Do you test response playbooks? | N26: =VLOOKUP(_Output!D1039,_Guidance!B964:C969,2,FALSE) | P26: Testing both detection and response provides a more complete view of SOC capabilities
B27: 5.2.5 | C27: Is detection validation fully integrated in the detection engineering process / pipeline? | N27: =VLOOKUP(_Output!D1040,_Guidance!B970:C975,2,FALSE) | P27: When deploying new or updated detection, automated detection testing should be executed as a quality gate
B28: 5.2.6 | C28: Is the outcome from detection validation used as input into monitoring and detection engineering? | N28: =VLOOKUP(_Output!D1041,_Guidance!B976:C981,2,FALSE) | P28: Output should lead to updates in detections and new detections, as well as instructions for SOC analysts
B29: 5.2.7 | C29: Do you monitor the data ingestion status for data sources? | N29: =VLOOKUP(_Output!D1134,_Guidance!B982:C987,2,FALSE) | P29: Monitoring data ingestion is used to identify data ingestion problems or inactive data sources
B30: 5.2.8 | C30: Do you actively measure and improve data source coverage? | N30: =VLOOKUP(_Output!D1136,_Guidance!B988:C993,2,FALSE) | P30: Data source coverage should be optimized to avoid blind spots in monitoring
B32: Comments and/or Remarks
B33: 5.3 | C33: Specify rationale for chosen values or any additional comments | L33: 5.1.1
L34: 5.1.2
C35: [1] example tools / resources include: | L35: 5.1.3
C36: - Atomic red team | L36: 5.1.4
C37: - MITRE Caldera | L37: 5.1.5
C38: - MAAD-AF | L38: 5.1.6
C39: - Breach & Attack Simulation (BAS) tools | L39: 5.1.7
C40: - CTID Adversary Emulation Library | L40: 5.1.8
L41: 5.1.9
L42: 5.1.10
L43: 5.2.1
L44: 5.2.2
L45: 5.2.3
L46: 5.2.4
L47: 5.2.5
L48: 5.2.6
L49: 5.2.7
L50: 5.2.8

Sheet Process - ATE
B1: Process
B3: 1. SOC Management | G3: 5. Detection Engineering & Validation
B4: 2. Operations & Facilities | G4: 6. Automation Engineering
B5: 3. Reporting & Communication | G5: 7. Log Management
B6: 4. Use Case Management
A9: 6 | B9: Automation Engineering | L9: Answer | N9: Guidance | P9: Remarks
B10: 6.1 Automation Engineering
B11: 6.1.1 | C11: Do you have an automation engineering process in place? | N11: =VLOOKUP(_Output!D1405,_Guidance!B995:C1000,2,FALSE) | P11: An automation engineering process supports the creation and deployment of automations in the SOC
B12: 6.1.2 | C12: Is the automation engineering process formally documented? | N12: =VLOOKUP(_Output!D1406,_Guidance!B1001:C1006,2,FALSE) | P12: Formal documentation supports process standardisation, and allows for faster training of new engineers
B13: 6.1.3 | C13: Please specify the elements of the automation engineering process
B14: 6.1.3.1 | C14: Analysis automation | P14: Automation of analysis and triage
B15: 6.1.3.2 | C15: Response automation | P15: Automation of response actions
B16: 6.1.3.3 | C16: Report automation | P16: Automation of reporting
B17: 6.1.3.4 | C17: Ticket automation | P17: Automation of ticket creation, updating, and handling
B18: 6.1.3.5 | C18: Enrichment automation | P18: Automation of event and ticket enrichment (asset information, CTI, OSINT, etc.)
B19: 6.1.3.6 | C19: Runbook / SOP automation | P19: Automation of existing runbooks and SOPs
B20: 6.1.3.7 | C20: False-positive automation | P20: Automated handling and closure of false-positives
B21: 6.1.3.8 | C21: Recurring task automation | P21: Automation of reccuring tasks in the SOC
C22: Completeness | L22: =VLOOKUP(SUM(_Output!D1407:D1414),_SUM_Completeness!A267:B275,2,FALSE) -> Incomplete | P22: Use this outcome as a guideline to determine the score for 6.1.2
B23: 6.1.4 | C23: Are there specific roles and requirements for automation engineers? | N23: =VLOOKUP(_Output!D1415,_Guidance!B1007:C1012,2,FALSE) | P23: Automation engineers have a skillset that is different from security analysts and security engineers
B24: 6.1.5 | C24: Are automations tracked and measured using defined metrics? | N24: =VLOOKUP(_Output!D1416,_Guidance!B1013:C1018,2,FALSE) | P24: Tracking automation effectiveness is important to measure and optimize the impact of automations on SOC effectiveness
B25: 6.1.6 | C25: Are all SOC use cases touched or resolved by automation? | N25: =VLOOKUP(_Output!D1417,_Guidance!B1019:C1024,2,FALSE) | P25: In an automation-first strategy, all SOC uses should be touch and resolved much as possible
B26: 6.1.7 | C26: Are custom automation playbooks developed in the SOC? | N26: =VLOOKUP(_Output!D1418,_Guidance!B1025:C1030,2,FALSE) | P26: Custom automation playbooks are tailored to specific needs of the SOC and its customers
B27: 6.1.8 | C27: Is there a testing procedure to test and validate automations? | N27: =VLOOKUP(_Output!D1419,_Guidance!B1031:C1036,2,FALSE) | P27: Validating automations should be done before deployment, and after major changes
B28: 6.1.9 | C28: Is there a formal release process in place for new automations? | N28: =VLOOKUP(_Output!D1420,_Guidance!B1037:C1042,2,FALSE) | P28: A release process ensures that automations are deployed in production in a predicatble and reliable way
B30: 6.2 Artificial Intelligence
B31: 6.2.1 | C31: Do you have a AI adoption strategy for the SOC in place? | N31: =VLOOKUP(_Output!D1421,_Guidance!B1043:C1048,2,FALSE) | P31: An AI adoption strategy will help define the direction of AI within the SOC
B32: 6.2.2 | C32: Please specify the elements of the AI adoption strategy
B33: 6.2.2.1 | C33: Overall strategy (smart follower, early adopter) | P33: The ambition for AI adoption and overall strategy of how the organisation intends to integrate AI into the SOC
B34: 6.2.2.2 | C34: AI types (agentic, LLMs, co-pilots, chatbots, etc.) | P34: Types of AI that will be used in the SOC
B35: 6.2.2.3 | C35: AI customization level (off-the-shelf, customized, internally trained) | P35: The level of customization that is intended for using AI in the SOC
B36: 6.2.2.4 | C36: SOC tasks to be replaced or augmented by AI | P36: A defined list of tasks within the SOC that will be replaced or augmented by AI
B37: 6.2.2.5 | C37: Risk & guardrails | P37: Any risks that are identified in the usage of AI and the guardrails to protect the SOC and organization from any unwanted side-effects
B38: 6.2.2.6 | C38: Metrics | P38: Metrics used to track AI performance and impact
B39: 6.2.2.7 | C39: Adoption timeline | P39: The timeline for integrating AI into the SOC, with defined milestones for AI integration
C40: Completeness | L40: =VLOOKUP(SUM(_Output!D1422:D1428),_SUM_Completeness!A278:B285,2,FALSE) -> Incomplete | P40: Use this outcome as a guideline to determine the score for 6.2.1
B41: 6.2.3 | C41: Is the AI adoption strategy internally aligned and approved by relevant stakeholders? | N41: =VLOOKUP(_Output!D1429,_Guidance!B1049:C1054,2,FALSE) | P41: Internal alignment with relevant stakeholders will ensure the SOC is operating in alignment with the broader AI strategy
B43: Comments and/or Remarks
B44: 6.3 | C44: Specify rationale for chosen values or any additional comments | L44: 6.1.1
L45: 6.1.2
L46: 6.1.3
L47: 6.1.4
L48: 6.1.5
L49: 6.1.6
L50: 6.1.7
L51: 6.1.8
L52: 6.1.9
L53: 6.2.1
L54: 6.2.2
L55: 6.2.3

Sheet Process - LOG
B1: Process
B3: 1. SOC Management | G3: 5. Detection Engineering & Validation
B4: 2. Operations & Facilities | G4: 6. Automation Engineering
B5: 3. Reporting & Communication | G5: 7. Log Management
B6: 4. Use Case Management
A9: 7 | B9: Log Management | L9: Answer | N9: Guidance | P9: Remarks
B10: 7.1 | C10: Is there a log management process in place? | N10: =VLOOKUP(_Output!D1432,_Guidance!B1056:C1061,2,FALSE) | P10: An log management process is used to manage logs throughout their lifecycle
B11: 7.2 | C11: Are log management elements formally identified and documented? | N11: =VLOOKUP(_Output!D1433,_Guidance!B1062:C1067,2,FALSE) | P11: Formal documentation supports process standardisation, and allows for faster training of new engineers
B12: 7.3 | C12: Please specify identified log management elements:
B13: 1.3.1 | C13: Data sources | P13: The SOC must have an understanding of the log sources that are in scope of the log management process
B14: 1.3.2 | C14: Data collection | P14: Active data collection from all relevant log sources
B15: 1.3.3 | C15: Data filtering | P15: Filtering is applied to logging to remove unwanted information (such as sensitive and personal information)
B16: 1.3.4 | C16: Data normalisation | P16: Data normalisation is used to restructure data to simplify log searching and analysis
B17: 1.3.5 | C17: Data retention | P17: Retention times must be configured for logging so that it is removed according to legal requirements
B18: 1.3.6 | C18: Data backup & restore | P18: Backup & restore of log data will ensure availability in case of operational issues
B19: 1.3.7 | C19: Data archival | P19: Archiving data will allow for more cost-efficient data storage
B20: 1.3.8 | C20: Data disposal | P20: Data must be disposed of properly by the end of its life cycle
B21: 1.3.9 | C21: Searching and analysis | P21: Log searching and analysis can be used to analyse incidents (security & operational)
B22: 1.3.10 | C22: Sensitive data handling | P22: Sensitive data must be handled with care
C23: Completeness | L23: =VLOOKUP(SUM(_Output!D205:D214),_SUM_Completeness!A45:B55,2,FALSE) -> Incomplete | P23: Use this outcome as a guideline to determine the score for 7.2
B24: 7.4 | C24: Is the log management process supported by corporate policy? | N24: =VLOOKUP(_Output!D1445,_Guidance!B1068:C1073,2,FALSE) | P24: The main relevant policies are auditing & logging policy, data handling and privacy policies
B25: 7.5 | C25: Is the log management process supported by appropriate centralised log management tooling? | N25: =VLOOKUP(_Output!D1447,_Guidance!B1074:C1079,2,FALSE) | P25: Centralised log management tooling provides technical capabilities that support the process. May be part of the SIEM solution
B26: 7.6 | C26: Is the log management process compliant with applicable standards & regulations? | N26: =VLOOKUP(_Output!D1448,_Guidance!B1080:C1085,2,FALSE) | P26: Logs must be handled in compliance with internal and external regulations, including privacy
B27: 7.7 | C27: Is the log management process aligned with all stakeholders? | N27: =VLOOKUP(_Output!D1449,_Guidance!B1086:C1091,2,FALSE) | P27: Relevant stakeholders include privacy office, data protection office, and other risk & security stakeholders
B28: 7.8 | C28: Is logging encrypted in transfer, in use, and at rest? | N28: =VLOOKUP(_Output!D1450,_Guidance!B1092:C1097,2,FALSE) | P28: Data encryption throughout the full lifecycle is a necessity for confidentiality
B29: 7.9 | C29: Is access to logging restricted to authorized personnel? | N29: =VLOOKUP(_Output!D1453,_Guidance!B1098:C1103,2,FALSE) | P29: Access must be restricted using leas privilege and need to know principles
B31: Comments and/or Remarks
B32: 7.10 | C32: Specify rationale for chosen values or any additional comments | L32: 7.1
L33: 7.2
L34: 7.3
L35: 7.4
L36: 7.5
L37: 7.6
L38: 7.7
L39: 7.8
L40: 7.9

Sheet Technology - LOG
B1: Technology
B3: 1. Log Monitoring
B4: 2. Network Monitoring
B5: 3. Endpoint Monitoring
B6: 4. SecOps Automation
A9: 1 | B9: Log Monitoring | L9: Answer | N9: Guidance | O9: Remarks
B10: Maturity
B11: 1.1 | C11: Accountability
B12: 1.1.1 | C12: Has functional ownership of the solution been formally assigned? | N12: =VLOOKUP(_Output!D322,_Guidance!B1105:C1110,2,FALSE) | O12: Functional ownership includes functional accountability
B13: 1.1.2 | C13: Has technical ownership of the solution been formally assigned? | N13: =VLOOKUP(_Output!D323,_Guidance!B1111:C1116,2,FALSE) | O13: Technical ownership includes technical accountability
B14: 1.2 | C14: Documentation
B15: 1.2.1 | C15: Has the solution been technically documented? | N15: =VLOOKUP(_Output!D325,_Guidance!B1117:C1122,2,FALSE) | O15: A technical description of the system's components and configuration
B16: 1.2.2 | C16: Has the solution been functionally documented? | N16: =VLOOKUP(_Output!D326,_Guidance!B1123:C1128,2,FALSE) | O16: A description of the system's functional configuration (workflows, integrations, etc.)
B17: 1.3 | C17: Personnel & support
B18: 1.3.1 | C18: Is there dedicated personnel for support? | N18: =VLOOKUP(_Output!D328,_Guidance!B1129:C1134,2,FALSE) | O18: Dedicated personnel should be in place to ensure that support is always available. Can also be staff with outsourced provider
B19: 1.3.2 | C19: Is the personnel for support formally trained? | N19: =VLOOKUP(_Output!D329,_Guidance!B1135:C1140,2,FALSE) | O19: Training helps to jump start new hires, and to learn a proper way of working with the tool
B20: 1.3.3 | C20: Is the personnel for support certified? | N20: =VLOOKUP(_Output!D330,_Guidance!B1141:C1146,2,FALSE) | O20: Certification demonstrates ability to handle the tooling properly
B21: 1.3.4 | C21: Is there a support contract for the solution? | N21: =VLOOKUP(_Output!D331,_Guidance!B1147:C1152,2,FALSE) | O21: A support contract may cover on-site support, support availability, response times, escalation and full access to resources
B22: 1.4 | C22: Maintenance & configuration
B23: 1.4.1 | C23: Is the system regularly maintained? | N23: =VLOOKUP(_Output!D1045,_Guidance!B1153:C1158,2,FALSE) | O23: Systems should be regularly maintained to keep up with the latest features and bug fixes
B24: 1.4.2 | C24: Is remote maintenance on the system managed? | N24: =VLOOKUP(_Output!D1046,_Guidance!B1159:C1164,2,FALSE) | O24: Remote maintenance by a third party may be part of system maintenance procedures
B25: 1.4.3 | C25: Are maintenance & configuration updates executed through the change management process? | N25: =VLOOKUP(_Output!D1047,_Guidance!B1165:C1170,2,FALSE) | O25: Maintenance and configuration updates should follow the formal change management process
B26: 1.4.4 | C26: Have you established maintenance and change windows? | N26: =VLOOKUP(_Output!D1048,_Guidance!B1171:C1176,2,FALSE) | O26: Setting maintenance windows helps to structure the maintenance process and make it more predictable
B27: 1.4.5 | C27: Is maintenance performed using authorised and trusted tooling? | N27: =VLOOKUP(_Output!D1049,_Guidance!B1177:C1182,2,FALSE) | O27: Performing maintenance with authorised and trusted tooling helps to ensure security and integrity of the system
B28: 1.5 | C28: Availability, integrity & continuity
B29: 1.5.1 | C29: Is there high availability (HA) in place for the solution? | N29: =VLOOKUP(_Output!D333,_Guidance!B1183:C1188,2,FALSE) | O29: Can be fully implemented HA, partially implemented, hot spare, etc.
B30: 1.5.2 | C30: Is there data backup / replication in place for the solution? | N30: =VLOOKUP(_Output!D334,_Guidance!B1189:C1194,2,FALSE) | O30: May not be feasible or applicable to all solutions
B31: 1.5.3 | C31: Is there configuration backup / replication in place for the solution? | N31: =VLOOKUP(_Output!D335,_Guidance!B1195:C1200,2,FALSE) | O31: Configuration synchronization could be part of a HA setup
B32: 1.5.4 | C32: Is there a Disaster Recovery plan in place for this solution? | N32: =VLOOKUP(_Output!D336,_Guidance!B1201:C1206,2,FALSE) | O32: A DR plan is required to restore service in case of catastrophic events
B33: 1.5.5 | C33: Is the Disaster Recovery plan regularly tested? | N33: =VLOOKUP(_Output!D337,_Guidance!B1207:C1212,2,FALSE) | O33: Testing the DR plan is required to ensure that it is complete, functional and tasks and responsibilities for involved personnel are understood
B34: 1.5.6 | C34: Is there a separate development / test environment for this solution? | N34: =VLOOKUP(_Output!D338,_Guidance!B1213:C1218,2,FALSE) | O34: A separate test environment allows for testing of new configurations before deployment in production
B35: 1.6 | C35: Access management
B36: 1.6.1 | C36: Is access to the solution limited to authorized personnel? | N36: =VLOOKUP(_Output!D340,_Guidance!B1219:C1224,2,FALSE) | O36: The system will contain confidential information and information that possibly impacts employee privacy
B37: 1.6.2 | C37: Are access rights regularly reviewed and revoked if required? | N37: =VLOOKUP(_Output!D342,_Guidance!B1225:C1230,2,FALSE) | O37: Revocation is part of normal employee termination. Special emergency revocation should be in place for suspected misuse
B38: 1.6.3 | C38: Is a break glass procedure in place? | N38: =VLOOKUP(_Output!D1139,_Guidance!B1231:C1236,2,FALSE) | O38: A break glass procedure and account is required to gain access to the tooling even in case of major IT outages
B40: Capability
B41: 1.7 | C41: Specify which technological capabilities and artefacts are present and implemented:
B42: Technical capabilities
B43: 1.7.1 | C43: Subtle event detection | N43: =VLOOKUP(_Output!D1143,_Guidance!$B$2234:$C$2240,2,FALSE) | O43: Capability to detect slight changes in systems, applications or network that may indicate malicious behavior
B44: 1.7.2 | C44: Automated alerting | N44: =VLOOKUP(_Output!D1144,_Guidance!$B$2234:$C$2240,2,FALSE) | O44: Alerting based on different alerting mechanisms (SMS, mail, etc.)
B45: 1.7.3 | C45: Alert acknowledgement | N45: =VLOOKUP(_Output!D1145,_Guidance!$B$2234:$C$2240,2,FALSE) | O45: Capability to acknowledge alerts so other analysts know the alert is being investigated
B46: 1.7.4 | C46: Case management system | N46: =VLOOKUP(_Output!D1146,_Guidance!$B$2234:$C$2240,2,FALSE) | O46: A case management system that supports SOC analyst workflows
B47: 1.7.5 | C47: Network model | N47: =VLOOKUP(_Output!D1147,_Guidance!$B$2234:$C$2240,2,FALSE) | O47: A full network model in which zones and segments are defined
B48: 1.7.6 | C48: Detailed audit trail of analyst activities | N48: =VLOOKUP(_Output!D1148,_Guidance!$B$2234:$C$2240,2,FALSE) | O48: The audit trail can be used to report on analyst activities and to uncover potential abuse of the big data solution
B49: 1.7.7 | C49: Historical activity detection | N49: =VLOOKUP(_Output!D1149,_Guidance!$B$2234:$C$2240,2,FALSE) | O49: Capability of detecting historical activity for recently uncovered threats
B50: 1.7.8 | C50: Flexible and scalable architecture | N50: =VLOOKUP(_Output!D1150,_Guidance!$B$2234:$C$2240,2,FALSE) | O50: A flexible and scalable architecture supports the SOC as it grows in size (FTE) and data (coverage)
B51: 1.7.9 | C51: MITRE ATT&CK® identifier tagging | N51: =VLOOKUP(_Output!D1151,_Guidance!$B$2234:$C$2240,2,FALSE) | O51: Add MITRE ATT&CK® tags to rules / analytics for mapping purposes
B53: Data ingestion and processing
B54: 1.7.10 | C54: Aggregation | N54: =VLOOKUP(_Output!D1152,_Guidance!$B$2234:$C$2240,2,FALSE) | O54: Capability to aggregate data and optimize the event flow
B55: 1.7.11 | C55: Normalisation | N55: =VLOOKUP(_Output!D1153,_Guidance!$B$2234:$C$2240,2,FALSE) | O55: Normalization of data is required for advanced searching and comparison of events from different sources
B56: 1.7.12 | C56: Correlation | N56: =VLOOKUP(_Output!D1154,_Guidance!$B$2234:$C$2240,2,FALSE) | O56: Capability to correlate multiple events
B57: 1.7.13 | C57: Multi-stage correlation | N57: =VLOOKUP(_Output!D1155,_Guidance!$B$2234:$C$2240,2,FALSE) | O57: Capability to detect attacks across multiple attack stages
B58: 1.7.14 | C58: Custom parsing | N58: =VLOOKUP(_Output!D1156,_Guidance!$B$2234:$C$2240,2,FALSE) | O58: Capability to create and maintain custom parsers for parsing and normalization needs
B59: 1.7.15 | C59: API Integration | N59: =VLOOKUP(_Output!D1157,_Guidance!$B$2234:$C$2240,2,FALSE) | O59: Both export of information / commands and import of data from API sources (such as cloud)
B60: 1.7.16 | C60: Secure Event Transfer | N60: =VLOOKUP(_Output!D1158,_Guidance!$B$2234:$C$2240,2,FALSE) | O60: Support for secure event transfer and the actual implementation of secure transfer (e.g. regular syslog is not secure)
B61: 1.7.17 | C61: Support for multiple event transfer technologies | N61: =VLOOKUP(_Output!D1159,_Guidance!$B$2234:$C$2240,2,FALSE) | O61: The system should support event transfer technologies for all possible data sources
B63: Integrations (technical & process)
B64: 1.7.18 | C64: Asset management integration | N64: =VLOOKUP(_Output!D1160,_Guidance!$B$2234:$C$2240,2,FALSE) | O64: Integration into the asset management process for automated adding of assets to the system for monitoring
B65: 1.7.19 | C65: Business context integration | N65: =VLOOKUP(_Output!D1161,_Guidance!$B$2234:$C$2240,2,FALSE) | O65: Integration of business context (business function, asset classification, etc.)
B66: 1.7.20 | C66: Identity context integration | N66: =VLOOKUP(_Output!D1162,_Guidance!$B$2234:$C$2240,2,FALSE) | O66: Integration of identity information into the system for enhanced monitoring of users and groups
B67: 1.7.21 | C67: Asset context integration | N67: =VLOOKUP(_Output!D1163,_Guidance!$B$2234:$C$2240,2,FALSE) | O67: Integration of asset management information into the system (asset owner, asset location, etc.)
B68: 1.7.22 | C68: Vulnerability context integration | N68: =VLOOKUP(_Output!D1164,_Guidance!$B$2234:$C$2240,2,FALSE) | O68: Integration of vulnerability management information into sysstem assets to determine risk levels for assets
B69: 1.7.23 | C69: Threat Intelligence integration | N69: =VLOOKUP(_Output!D1165,_Guidance!$B$2234:$C$2240,2,FALSE) | O69: Integration of threat intelligence information (observables / IoCs) into the security monitoring tooling
B70: 1.7.24 | C70: Threat hunting integration | N70: =VLOOKUP(_Output!D1166,_Guidance!$B$2234:$C$2240,2,FALSE) | O70: Integration of the tooling into the threat hunting process to support threat hunting investigations
B71: 1.7.25 | C71: Security incident management integration | N71: =VLOOKUP(_Output!D1167,_Guidance!$B$2234:$C$2240,2,FALSE) | O71: Integration of the security incident management process to support incident investigation
B72: 1.7.26 | C72: SecOps automation integration | N72: =VLOOKUP(_Output!D1168,_Guidance!$B$2234:$C$2240,2,FALSE) | O72: Integration with the SecOps automation (e.g. SOAR) tooling for automation purposes
B74: Rule-based detection
B75: 1.7.27 | C75: Standard detection rules | N75: =VLOOKUP(_Output!D1169,_Guidance!$B$2234:$C$2240,2,FALSE) | O75: Use of standard content packs in the security monitoring solution
B76: 1.7.28 | C76: Custom detection rules | N76: =VLOOKUP(_Output!D1170,_Guidance!$B$2234:$C$2240,2,FALSE) | O76: Use of custom content (correlation rules, etc.) in the security monitoring solution
B78: Anomaly detection
B79: 1.7.29 | C79: User anomalies | N79: =VLOOKUP(_Output!D1171,_Guidance!$B$2234:$C$2240,2,FALSE) | O79: Anomalous pattern detection for users
B80: 1.7.30 | C80: Application anomalies | N80: =VLOOKUP(_Output!D1174,_Guidance!$B$2234:$C$2240,2,FALSE) | O80: Anomalous pattern detection for applications
B81: 1.7.31 | C81: Device anomalies | N81: =VLOOKUP(_Output!D1176,_Guidance!$B$2234:$C$2240,2,FALSE) | O81: Anomalous pattern detection for devices
B82: 1.7.32 | C82: Network anomalies | N82: =VLOOKUP(_Output!D1178,_Guidance!$B$2234:$C$2240,2,FALSE) | O82: Anomalous pattern detection for network
B84: Visualisation and output
B85: 1.7.33 | C85: Reporting | N85: =VLOOKUP(_Output!D1181,_Guidance!$B$2234:$C$2240,2,FALSE) | O85: Custom reports for SOC customers and SOC analysts
B86: 1.7.34 | C86: Dashboards | N86: =VLOOKUP(_Output!D1182,_Guidance!$B$2234:$C$2240,2,FALSE) | O86: Custom dashboards used by analysts and managers
B87: 1.7.35 | C87: Data visualization techniques | N87: =VLOOKUP(_Output!D1183,_Guidance!$B$2234:$C$2240,2,FALSE) | O87: Graphing capabilities to support analysis
B88: 1.7.36 | C88: Data drilldowns | N88: =VLOOKUP(_Output!D1184,_Guidance!$B$2234:$C$2240,2,FALSE) | O88: Drilldowns on graphs to quickly 'zoom in' on details of visual anomalies
B89: 1.7.37 | C89: Central analysis console | N89: =VLOOKUP(_Output!D1185,_Guidance!$B$2234:$C$2240,2,FALSE) | O89: A central console used by SOC analysts
B90: 1.7.38 | C90: Advanced searching and querying | N90: =VLOOKUP(_Output!D1186,_Guidance!$B$2234:$C$2240,2,FALSE) | O90: Searching capabilities that support finding specific information based on characteristics
C91: Completeness (%) | L91: =IFERROR(ROUND(_Output!K372,0),0) -> 0
B93: Comments and/or Remarks
B94: 1.8 | C94: Specify rationale for chosen values or any additional comments | K94: Maturity | L94: 1.1.1
L95: 1.1.2
L96: 1.2.1
L97: 1.2.2
L98: 1.3.1
L99: 1.3.2
L100: 1.3.3
L101: 1.3.4
L102: 1.4.1
L103: 1.4.2
L104: 1.4.3
L105: 1.4.4
L106: 1.4.5
... L115: 1.6.3
K117: Capability | L117: 1.7.1
L118: 1.7.2
L119: 1.7.3
...

Sheet Technology - NET
B1: Technology
B3: 1. Log Monitoring
B4: 2. Network Monitoring
B5: 3. Endpoint Monitoring
B6: 4. SecOps Automation
A9: 2 | B9: Network Monitoring | L9: Answer | N9: Guidance | O9: Remarks
B10: Maturity
B11: 2.1 | C11: Accountability
B12: 2.1.1 | C12: Has functional ownership of the solution been formally assigned? | N12: =VLOOKUP(_Output!D378,_Guidance!B1239:C1244,2,FALSE) | O12: Functional ownership includes functional accountability
B13: 2.1.2 | C13: Has technical ownership of the solution been formally assigned? | N13: =VLOOKUP(_Output!D379,_Guidance!B1245:C1250,2,FALSE) | O13: Technical ownership includes technical accountability
B14: 2.2 | C14: Documentation
B15: 2.2.1 | C15: Has the solution been technically documented? | N15: =VLOOKUP(_Output!D381,_Guidance!B1251:C1256,2,FALSE) | O15: A technical description of the system's components and configuration
B16: 2.2.2 | C16: Has the solution been functionally documented? | N16: =VLOOKUP(_Output!D382,_Guidance!B1257:C1262,2,FALSE) | O16: A description of the system's functional configuration (workflows, integrations, etc.)
B17: 2.3 | C17: Personnel & support
B18: 2.3.1 | C18: Is there dedicated personnel for support? | N18: =VLOOKUP(_Output!D384,_Guidance!B1263:C1268,2,FALSE) | O18: Dedicated personnel should be in place to ensure that support is always available. Can also be staff with outsourced provider
B19: 2.3.2 | C19: Is the personnel for support formally trained? | N19: =VLOOKUP(_Output!D385,_Guidance!B1269:C1274,2,FALSE) | O19: Training helps to jump start new hires, and to learn a proper way of working with the tool
B20: 2.3.3 | C20: Is the personnel for support certified? | N20: =VLOOKUP(_Output!D386,_Guidance!B1275:C1280,2,FALSE) | O20: Certification demonstrates ability to handle the tooling properly
B21: 2.3.4 | C21: Is there a support contract for the solution? | N21: =VLOOKUP(_Output!D387,_Guidance!B1281:C1286,2,FALSE) | O21: A support contract may cover on-site support, support availability, response times, escalation and full access to resources
B22: 2.4 | C22: Maintenance & configuration
B23: 2.4.1 | C23: Is the system regularly maintained? | N23: =VLOOKUP(_Output!D1050,_Guidance!B1287:C1292,2,FALSE) | O23: Systems should be regularly maintained to keep up with the latest features and bug fixes
B24: 2.4.2 | C24: Is remote maintenance on the system managed? | N24: =VLOOKUP(_Output!D1051,_Guidance!B1293:C1298,2,FALSE) | O24: Remote maintenance by a third party may be part of system maintenance procedures
B25: 2.4.3 | C25: Are maintenance & configuration updates executed through the change management process? | N25: =VLOOKUP(_Output!D1052,_Guidance!B1299:C1304,2,FALSE) | O25: Maintenance and configuration updates should follow the formal change management process
B26: 2.4.4 | C26: Have you established maintenance and change windows? | N26: =VLOOKUP(_Output!D1053,_Guidance!B1305:C1310,2,FALSE) | O26: Setting maintenance windows helps to structure the maintenance process and make it more predictable
B27: 2.4.5 | C27: Is maintenance performed using authorised and trusted tooling? | N27: =VLOOKUP(_Output!D1054,_Guidance!B1311:C1316,2,FALSE) | O27: Performing maintenance with authorised and trusted tooling helps to ensure security and integrity of the system
B28: 2.5 | C28: Availability, integrity & continuity
B29: 2.5.1 | C29: Is there high availability (HA) in place for the solution? | N29: =VLOOKUP(_Output!D389,_Guidance!B1317:C1322,2,FALSE) | O29: Can be fully implemented HA, partially implemented, hot spare, etc.
B30: 2.5.2 | C30: Is there data backup / replication in place for the solution? | N30: =VLOOKUP(_Output!D390,_Guidance!B1323:C1328,2,FALSE) | O30: Data may include logs and PCAP files
B31: 2.5.3 | C31: Is there configuration backup / replication in place for the solution? | N31: =VLOOKUP(_Output!D391,_Guidance!B1329:C1334,2,FALSE) | O31: Configuration synchronization could be part of a HA setup
B32: 2.5.4 | C32: Is there a Disaster Recovery plan in place for this solution? | N32: =VLOOKUP(_Output!D392,_Guidance!B1335:C1340,2,FALSE) | O32: A DR plan is required to restore service in case of catastrophic events
B33: 2.5.5 | C33: Is the Disaster Recovery plan regularly tested? | N33: =VLOOKUP(_Output!D393,_Guidance!B1341:C1347,2,FALSE) | O33: Testing the DR plan is required to ensure that it is complete, functional and tasks and responsibilities for involved personnel are understood
B34: 2.5.6 | C34: Is there a separate development / test environment for this solution? | N34: =VLOOKUP(_Output!D394,_Guidance!B1347:C1352,2,FALSE) | O34: A separate test environment allows for testing of new configurations before deployment in production
B35: 2.6 | C35: Access Management
B36: 2.6.1 | C36: Is access to the solution limited to authorized personnel? | N36: =VLOOKUP(_Output!D396,_Guidance!B1353:C1358,2,FALSE) | O36: The system will contain confidential information and possibly information that impacts employee privacy
B37: 2.6.2 | C37: Are access rights regularly reviewed and revoked if required? | N37: =VLOOKUP(_Output!D398,_Guidance!B1359:C1364,2,FALSE) | O37: Revocation is part of normal employee termination. Special emergency revocation should be in place for suspected misuse
B38: 2.6.3 | C38: Is a break glass procedure in place? | N38: =VLOOKUP(_Output!D1140,_Guidance!B1365:C1370,2,FALSE) | O38: A break glass procedure and account is required to gain access to the tooling even in case of major IT outages
B40: Capability
B41: 2.7 | C41: Specify which technological capabilities and artefacts are present and implemented:
B42: Technical capabilities
B43: 2.7.1 | C43: Encrypted traffic analysis | N43: =VLOOKUP(_Output!D1187,_Guidance!$B$2234:$C$2240,2,FALSE) | O43: Helps to identify potentially malicious traffic in encrypted communications, using fingerprinting or certificate analysis
B44: 2.7.2 | C44: IDS signature matching | N44: =VLOOKUP(_Output!D1188,_Guidance!$B$2234:$C$2240,2,FALSE) | O44: The ability to use IDS signatures in network monitoring
B45: 2.7.3 | C45: Supervised machine learning | N45: =VLOOKUP(_Output!D1189,_Guidance!$B$2234:$C$2240,2,FALSE) | O45: Machine learning trained on a predefined data set with known good and bad traffic
B46: 2.7.4 | C46: Unsupervised machine learning | N46: =VLOOKUP(_Output!D1190,_Guidance!$B$2234:$C$2240,2,FALSE) | O46: Machine learning trained without a predefined data set
B47: 2.7.5 | C47: Traffic blocking | N47: =VLOOKUP(_Output!D1191,_Guidance!$B$2234:$C$2240,2,FALSE) | O47: In-line appliances can block malicious traffic as part of their response capability
B48: 2.7.6 | C48: Unauthorised device detection | N48: =VLOOKUP(_Output!D1192,_Guidance!$B$2234:$C$2240,2,FALSE) | O48: Detection of unauthorised devices accessing the network
B49: 2.7.7 | C49: MITRE ATT&CK® identifier tagging | N49: =VLOOKUP(_Output!D1193,_Guidance!$B$2234:$C$2240,2,FALSE) | O49: Add MITRE ATT&CK® tags to rules / analytics for mapping and hunting purposes
B50: 2.7.8 | C50: Deep packet inspection | N50: =VLOOKUP(_Output!D1194,_Guidance!$B$2234:$C$2240,2,FALSE) | O50: Detailed inspection of data sent across the network
B51: 2.7.9 | C51: Correlation | N51: =VLOOKUP(_Output!D1195,_Guidance!$B$2234:$C$2240,2,FALSE) | O51: Correlation of anomalies with previously detected anomalies or detection rules
B53: Data ingestion and processing
B54: 2.7.10 | C54: Full packet capture | N54: =VLOOKUP(_Output!D1196,_Guidance!$B$2234:$C$2240,2,FALSE) | O54: Full packet capture supports network forensic capabilities
B55: 2.7.11 | C55: Flow data ingestion | N55: =VLOOKUP(_Output!D1197,_Guidance!$B$2234:$C$2240,2,FALSE) | O55: Flow data (such as NetFlow, IPFIX, etc.) ingestion
B57: Monitoring capabilities
B58: 2.7.12 | C58: Monitoring north - south network traffic | N58: =VLOOKUP(_Output!D1198,_Guidance!$B$2234:$C$2240,2,FALSE) | O58: Monitoring capabilities for traffic crossing the perimeter
B59: 2.7.13 | C59: Monitoring east - west network traffic | N59: =VLOOKUP(_Output!D1200,_Guidance!$B$2234:$C$2240,2,FALSE) | O59: Monitoring capabilities for traffic traversing the internal network
B60: 2.7.14 | C60: Monitoring classified network segements | N60: =VLOOKUP(_Output!D1202,_Guidance!$B$2234:$C$2240,2,FALSE) | O60: Monitoring capabilities for classified network segments
B61: 2.7.15 | C61: Monitoring cloud environments | N61: =VLOOKUP(_Output!D1204,_Guidance!$B$2234:$C$2240,2,FALSE) | O61: Monitoring capabilities for cloud connections / environments
B62: 2.7.16 | C62: Monitoring ICS/SCADA networks | N62: =VLOOKUP(_Output!D1206,_Guidance!$B$2234:$C$2240,2,FALSE) | O62: Monitoring capabilities for ISC/SCADA networks
B63: 2.7.17 | C63: Monitoring DNS traffic | N63: =VLOOKUP(_Output!D1208,_Guidance!$B$2234:$C$2240,2,FALSE) | O63: Monitoring capabilities for DNS queries
B65: Integrations (technical & process)
B66: 2.7.18 | C66: Business context integration | N66: =VLOOKUP(_Output!D1210,_Guidance!$B$2234:$C$2240,2,FALSE) | O66: Integration of business context (business function, asset classification, etc.)
B67: 2.7.19 | C67: Identity context integration | N67: =VLOOKUP(_Output!D1211,_Guidance!$B$2234:$C$2240,2,FALSE) | O67: Integration of identity information into the system for enhanced monitoring of users and groups
B68: 2.7.20 | C68: Threat Intelligence integration | N68: =VLOOKUP(_Output!D1212,_Guidance!$B$2234:$C$2240,2,FALSE) | O68: Integration of threat intelligence information (observables / IoCs) into the system for reputation-based monitoring
B69: 2.7.21 | C69: Threat hunting integration | N69: =VLOOKUP(_Output!D1213,_Guidance!$B$2234:$C$2240,2,FALSE) | O69: Integration of the tooling into the threat hunting process to support threat hunting investigations
B70: 2.7.22 | C70: Security incident management integration | N70: =VLOOKUP(_Output!D1214,_Guidance!$B$2234:$C$2240,2,FALSE) | O70: Integration of the security incident management process to support incident investigation
B71: 2.7.23 | C71: Log monitoring integration | N71: =VLOOKUP(_Output!D1215,_Guidance!$B$2234:$C$2240,2,FALSE) | O71: Integration with the log monitoring tooling (e.g. SIEM or XDR) for centralised correlation
B72: 2.7.24 | C72: Malware sandbox integration | N72: =VLOOKUP(_Output!D1216,_Guidance!$B$2234:$C$2240,2,FALSE) | O72: Detonate potential malware samples in a sandbox environment
B74: Rule-based detection
B75: 2.7.25 | C75: Standard detection rules | N75: =VLOOKUP(_Output!D1217,_Guidance!$B$2234:$C$2240,2,FALSE) | O75: Use of standard content packs in the security monitoring solution
B76: 2.7.26 | C76: Custom detection rules | N76: =VLOOKUP(_Output!D1218,_Guidance!$B$2234:$C$2240,2,FALSE) | O76: Use of custom content (correlation rules, etc.) in the security monitoring solution
B78: Anomaly detection
B79: 2.7.27 | C79: Traffic baselining | N79: =VLOOKUP(_Output!D1219,_Guidance!$B$2234:$C$2240,2,FALSE) | O79: Creation of network baselines for anomaly detection purposes
B80: 2.7.28 | C80: Pattern analysis | N80: =VLOOKUP(_Output!D1220,_Guidance!$B$2234:$C$2240,2,FALSE) | O80: Detection of anomalous patterns, for example in (encrypted) sessions, using machines learning
B82: Visualisation and output
B83: 2.7.29 | C83: Reporting | N83: =VLOOKUP(_Output!D1221,_Guidance!$B$2234:$C$2240,2,FALSE) | O83: Custom reports for SOC customers and SOC analysts
B84: 2.7.30 | C84: Dashboards | N84: =VLOOKUP(_Output!D1222,_Guidance!$B$2234:$C$2240,2,FALSE) | O84: Custom dashboards used by analysts and managers
B85: 2.7.31 | C85: Data visualization techniques | N85: =VLOOKUP(_Output!D1223,_Guidance!$B$2234:$C$2240,2,FALSE) | O85: Graphing capabilities to support analysis
B86: 2.7.32 | C86: Data drilldowns | N86: =VLOOKUP(_Output!D1224,_Guidance!$B$2234:$C$2240,2,FALSE) | O86: Drilldowns on graphs to quickly 'zoom in' on details of visual anomalies
B87: 2.7.33 | C87: Central analysis console | N87: =VLOOKUP(_Output!D1225,_Guidance!$B$2234:$C$2240,2,FALSE) | O87: A central console used by SOC analysts
B88: 2.7.34 | C88: Advanced searching and querying | N88: =VLOOKUP(_Output!D1226,_Guidance!$B$2234:$C$2240,2,FALSE) | O88: Searching capabilities that support finding specific information based on characteristics, especially useful for network threat hunting
C89: Completeness (%) | L89: =IFERROR(ROUND(_Output!K419,0),0) -> 0
B91: Comments and/or Remarks
B92: 2.8 | C92: Specify rationale for chosen values or any additional comments | K92: Maturity | L92: 2.1.1
L93: 2.1.2
L94: 2.2.1
L95: 2.2.2
L96: 2.3.1
L97: 2.3.2
L98: 2.3.3
L99: 2.3.4
L100: 2.4.1
L101: 2.4.2
L102: 2.4.3
L103: 2.4.4
L104: 2.4.5
... L113: 2.6.3
K115: Capability | L115: 2.7.1
L116: 2.7.2
L117: 2.7.3
L118: 2.7.4
L119: 2.7.5
L120: 2.7.6
...

Sheet Technology - END
B1: Technology
B3: 1. Log Monitoring
B4: 2. Network Monitoring
B5: 3. Endpoint Monitoring
B6: 4. SecOps Automation
A9: 3 | B9: Endpoint monitoring | L9: Answer | N9: Guidance | O9: Remarks
B10: Maturity
B11: 3.1 | C11: Accountability
B12: 3.1.1 | C12: Has functional ownership of the solution been formally assigned? | N12: =VLOOKUP(_Output!D425,_Guidance!B1373:C1378,2,FALSE) | O12: Functional ownership includes functional accountability
B13: 3.1.2 | C13: Has technical ownership of the solution been formally assigned? | N13: =VLOOKUP(_Output!D426,_Guidance!B1379:C1384,2,FALSE) | O13: Technical ownership includes technical accountability
B14: 3.2 | C14: Documentation
B15: 3.2.1 | C15: Has the solution been technically documented? | N15: =VLOOKUP(_Output!D428,_Guidance!B1385:C1390,2,FALSE) | O15: A technical description of the system's components and configuration
B16: 3.2.2 | C16: Has the solution been functionally documented? | N16: =VLOOKUP(_Output!D429,_Guidance!B1391:C1396,2,FALSE) | O16: A description of the system's functional configuration (workflows, integrations, etc.)
B17: 3.3 | C17: Personnel & support
B18: 3.3.1 | C18: Is there dedicated personnel for support? | N18: =VLOOKUP(_Output!D431,_Guidance!B1397:C1402,2,FALSE) | O18: Dedicated personnel should be in place to ensure that support is always available. Can also be staff with outsourced provider
B19: 3.3.2 | C19: Is the personnel for support formally trained? | N19: =VLOOKUP(_Output!D432,_Guidance!B1403:C1408,2,FALSE) | O19: Training helps to jump start new hires, and to learn a proper way of working with the tool
B20: 3.3.3 | C20: Is the personnel for support certified? | N20: =VLOOKUP(_Output!D433,_Guidance!B1409:C1414,2,FALSE) | O20: Certification demonstrates ability to handle the tooling properly
B21: 3.3.4 | C21: Is there a support contract for the solution? | N21: =VLOOKUP(_Output!D434,_Guidance!B1415:C1420,2,FALSE) | O21: A support contract may cover on-site support, support availability, response times, escalation and full access to resources
B22: 3.4 | C22: Maintenance & configuration
B23: 3.4.1 | C23: Is the system regularly maintained? | N23: =VLOOKUP(_Output!D1055,_Guidance!B1421:C1426,2,FALSE) | O23: Systems should be regularly maintained to keep up with the latest features and bug fixes
B24: 3.4.2 | C24: Is remote maintenance on the system managed? | N24: =VLOOKUP(_Output!D1056,_Guidance!B1427:C1432,2,FALSE) | O24: Remote maintenance by a third party may be part of system maintenance procedures
B25: 3.4.3 | C25: Are maintenance & configuration updates executed through the change management process? | N25: =VLOOKUP(_Output!D1057,_Guidance!B1433:C1438,2,FALSE) | O25: Maintenance and configuration updates should follow the formal change management process
B26: 3.4.4 | C26: Have you established maintenance and change windows? | N26: =VLOOKUP(_Output!D1058,_Guidance!B1439:C1444,2,FALSE) | O26: Setting maintenance windows helps to structure the maintenance process and make it more predictable
B27: 3.4.5 | C27: Is maintenance performed using authorised and trusted tooling? | N27: =VLOOKUP(_Output!D1059,_Guidance!B1445:C1450,2,FALSE) | O27: Performing maintenance with authorised and trusted tooling helps to ensure security and integrity of the system
B28: 3.5 | C28: Availability, integrity & continuity
B29: 3.5.1 | C29: Is there high availability (HA) in place for the solution? | N29: =VLOOKUP(_Output!D436,_Guidance!B1451:C1456,2,FALSE) | O29: Can be fully implemented HA, partially implemented, hot spare, etc. May not be applicable
B30: 3.5.2 | C30: Is there data backup / replication in place for the solution? | N30: =VLOOKUP(_Output!D437,_Guidance!B1457:C1462,2,FALSE) | O30: May not be feasible or applicable to all solutions
B31: 3.5.3 | C31: Is there configuration backup / replication in place for the solution? | N31: =VLOOKUP(_Output!D438,_Guidance!B1463:C1468,2,FALSE) | O31: Configuration synchronization could be part of a HA setup
B32: 3.5.4 | C32: Is there a Disaster Recovery plan in place for this solution? | N32: =VLOOKUP(_Output!D439,_Guidance!B1469:C1474,2,FALSE) | O32: A DR plan is required to restore service in case of catastrophic events
B33: 3.5.5 | C33: Is the Disaster Recovery plan regularly tested? | N33: =VLOOKUP(_Output!D440,_Guidance!B1475:C1480,2,FALSE) | O33: Testing the DR plan is required to ensure that it is complete, functional and tasks and responsibilities for involved personnel are understood
B34: 3.5.6 | C34: Is there a separate development / test environment for this solution? | N34: =VLOOKUP(_Output!D441,_Guidance!B1481:C1486,2,FALSE) | O34: A separate test environment allows for testing of new configurations before deployment in production
B35: 3.6 | C35: Access management
B36: 3.6.1 | C36: Is access to the solution limited to authorized personnel? | N36: =VLOOKUP(_Output!D443,_Guidance!B1487:C1492,2,FALSE) | O36: The system will contain confidential information and information that possibly impacts employee privacy
B37: 3.6.2 | C37: Are access rights regularly reviewed and revoked if required? | N37: =VLOOKUP(_Output!D445,_Guidance!B1493:C1498,2,FALSE) | O37: Revocation is part of normal employee termination. Special emergency revocation should be in place for suspected misuse
B38: 3.6.3 | C38: Is a break glass procedure in place? | N38: =VLOOKUP(_Output!D1141,_Guidance!B1499:C1504,2,FALSE) | O38: A break glass procedure and account is required to gain access to the tooling even in case of major IT outages
B40: Capability
B41: 3.7 | C41: Specify which technological capabilities and artefacts are present and implemented:
B42: Technical capabilities | N42: =VLOOKUP(_Output!D448,_Guidance!$B$2234:$C$2240,2,FALSE)
B43: 3.7.1 | C43: OS support | N43: =VLOOKUP(_Output!D1227,_Guidance!$B$2234:$C$2240,2,FALSE) | O43: Support for common OS's (e.g. Windows, Linux, OSX, etc.)
B44: 3.7.2 | C44: Mobile device support | N44: =VLOOKUP(_Output!D1228,_Guidance!$B$2234:$C$2240,2,FALSE) | O44: Support for mobile devices (e.g. Android, IOS)
B45: 3.7.3 | C45: Physical, virtual & cloud deployment | N45: =VLOOKUP(_Output!D1229,_Guidance!$B$2234:$C$2240,2,FALSE) | O45: Deployment across physical and virtual devices and cloud-based workloads increases coverage and visibility
B46: 3.7.4 | C46: Vulnerability patching | N46: =VLOOKUP(_Output!D1230,_Guidance!$B$2234:$C$2240,2,FALSE) | O46: Remote patching of uncovered vulnerabilities. May be fully automated
B47: 3.7.5 | C47: Forensic information preservation | N47: =VLOOKUP(_Output!D1231,_Guidance!$B$2234:$C$2240,2,FALSE) | O47: Forensic information preservation is a capability that supports security incident management and forensic investigation
B48: 3.7.6 | C48: Historic data retention | N48: =VLOOKUP(_Output!D1233,_Guidance!$B$2234:$C$2240,2,FALSE) | O48: Historic data retention is especially important in threat hunting investigations. Multiple months of data should be retained
B49: 3.7.7 | C49: MITRE ATT&CK® identifier tagging | N49: =VLOOKUP(_Output!D1234,_Guidance!$B$2234:$C$2240,2,FALSE) | O49: Add MITRE ATT&CK® tags to rules / analytics for mapping and hunting purposes
B50: 3.7.8 | C50: Memory analysis | N50: =VLOOKUP(_Output!D1235,_Guidance!$B$2234:$C$2240,2,FALSE) | O50: Analysis of end-point memory
B51: 3.7.9 | C51: Correlation | N51: =VLOOKUP(_Output!D1236,_Guidance!$B$2234:$C$2240,2,FALSE) | O51: Correlation of events with previously detected events
N52: =VLOOKUP(_Output!D452,_Guidance!$B$2234:$C$2240,2,FALSE)
B53: Prevention capabilities
B54: 3.7.10 | C54: Exploit prevention | N54: =VLOOKUP(_Output!D1237,_Guidance!$B$2234:$C$2240,2,FALSE) | O54: Prevention of exploits being executed on the system
B55: 3.7.11 | C55: Fileless malware protection | N55: =VLOOKUP(_Output!D1238,_Guidance!$B$2234:$C$2240,2,FALSE) | O55: Protection against malware running only in memory
B56: 3.7.12 | C56: Application allowlisting | N56: =VLOOKUP(_Output!D1240,_Guidance!$B$2234:$C$2240,2,FALSE) | O56: Prevention of running unauthorised applications by means of allow listing
B57: 3.7.13 | C57: Ransomware protection | N57: =VLOOKUP(_Output!D1241,_Guidance!$B$2234:$C$2240,2,FALSE) | O57: Protection against ransomware, for example with the used of controlled access to sensitive files and folders
B58: 3.7.14 | C58: Attack surface reduction | N58: =VLOOKUP(_Output!D1242,_Guidance!$B$2234:$C$2240,2,FALSE) | O58: Attack surface reduction can be used to decrease the likelihood of compromise
B60: Detection capabilities [1] | N60: =VLOOKUP(_Output!D453,_Guidance!$B$2234:$C$2240,2,FALSE)
B61: 3.7.15 | C61: Vulnerability detection | N61: =VLOOKUP(_Output!D1243,_Guidance!$B$2234:$C$2240,2,FALSE) | O61: Detection of vulnerabilities on the local end-point
B62: 3.7.16 | C62: Process execution monitoring | N62: =VLOOKUP(_Output!D1245,_Guidance!$B$2234:$C$2240,2,FALSE) | O62: Detection of execution of potentially malicious processes and scripts
B63: 3.7.17 | C63: File system monitoring | N63: =VLOOKUP(_Output!D1247,_Guidance!$B$2234:$C$2240,2,FALSE) | O63: Detection of file creation, deletion and or modification (including encryption)
B64: 3.7.18 | C64: Task & service monitoring | N64: =VLOOKUP(_Output!D1249,_Guidance!$B$2234:$C$2240,2,FALSE) | O64: Detection of creation or modification of services and scheduled tasks
B65: 3.7.19 | C65: Network connection monitoring | N65: =VLOOKUP(_Output!D1251,_Guidance!$B$2234:$C$2240,2,FALSE) | O65: Detection of potentially malicious network traffic
B66: 3.7.20 | C66: Registry monitoring | N66: =VLOOKUP(_Output!D1253,_Guidance!$B$2234:$C$2240,2,FALSE) | O66: Detection of modifications to the system registry
B67: 3.7.21 | C67: User activity monitoring | N67: =VLOOKUP(_Output!D1255,_Guidance!$B$2234:$C$2240,2,FALSE) | O67: Detection of user activity, including logon and logoff
B68: 3.7.22 | C68: Configuration monitoring | N68: =VLOOKUP(_Output!D1257,_Guidance!$B$2234:$C$2240,2,FALSE) | O68: Detection of unauthorised changes to the local end-point configuration, including modifications to registry, files, services, tasks, drivers, etc.
B69: 3.7.23 | C69: Air-gaped end-point monitoring | N69: =VLOOKUP(_Output!D1259,_Guidance!$B$2234:$C$2240,2,FALSE) | O69: Monitoring capabilities for end-points not connected to the corporate network
B70: 3.7.24 | C70: File reputation service | N70: =VLOOKUP(_Output!D1261,_Guidance!$B$2234:$C$2240,2,FALSE) | O70: Detection of potentially malicious files using an (online) file reputation service
B71: 3.7.25 | C71: Deception techniques | N71: =VLOOKUP(_Output!D1263,_Guidance!$B$2234:$C$2240,2,FALSE) | O71: Detection of adversaries by employing deception techniques (such as honey tokens) on end-points
B73: Remediation capabilities
B74: 3.7.26 | C74: URL filtering / blocking | N74: =VLOOKUP(_Output!D1265,_Guidance!$B$2234:$C$2240,2,FALSE) | O74: Block traffic to specific URL
B75: 3.7.27 | C75: Web content filtering | N75: =VLOOKUP(_Output!D1266,_Guidance!$B$2234:$C$2240,2,FALSE) | O75: Block specific web content
B76: 3.7.28 | C76: Machine isolation | N76: =VLOOKUP(_Output!D1267,_Guidance!$B$2234:$C$2240,2,FALSE) | O76: Isolate a machine from the network
B77: 3.7.29 | C77: Process termination / suspension | N77: =VLOOKUP(_Output!D1268,_Guidance!$B$2234:$C$2240,2,FALSE) | O77: Terminate or suspend a running process
B78: 3.7.30 | C78: File / registry key deletion | N78: =VLOOKUP(_Output!D1269,_Guidance!$B$2234:$C$2240,2,FALSE) | O78: Delete local files or registry key (in case of Windows)
B79: 3.7.31 | C79: Forced user logoff | N79: =VLOOKUP(_Output!D1270,_Guidance!$B$2234:$C$2240,2,FALSE) | O79: Force a user to log off to terminate any user-associated processes
B81: Integrations
B82: 3.7.32 | C82: Threat Intelligence integration | N82: =VLOOKUP(_Output!D1271,_Guidance!$B$2234:$C$2240,2,FALSE) | O82: Integration of threat intelligence information (observables / IoCs) into the system for reputation-based monitoring
B83: 3.7.33 | C83: Vulnerability intelligence integration | N83: =VLOOKUP(_Output!D1272,_Guidance!$B$2234:$C$2240,2,FALSE) | O83: Integration of vulnerability intelligence information into the system for vulnerability monitoring purposes
B84: 3.7.34 | C84: Threat hunting integration - TTPs | N84: =VLOOKUP(_Output!D1273,_Guidance!$B$2234:$C$2240,2,FALSE) | O84: Integration of the tooling into the threat hunting process to support threat hunting investigations on the TTP level
B85: 3.7.35 | C85: Threat hunting integration - Tools & artifacts | N85: =VLOOKUP(_Output!D1274,_Guidance!$B$2234:$C$2240,2,FALSE) | O85: Integration of the tooling into the threat hunting process to support threat hunting investigations on the Tools & artifacts level
B86: 3.7.36 | C86: Threat hunting integration - Technical indicators | N86: =VLOOKUP(_Output!D1275,_Guidance!$B$2234:$C$2240,2,FALSE) | O86: Integration of the tooling into the threat hunting process to support threat hunting investigations on the indicator level (IP, domain, hash)
B87: 3.7.37 | C87: Security incident management integration | N87: =VLOOKUP(_Output!D1276,_Guidance!$B$2234:$C$2240,2,FALSE) | O87: Integration of the security incident management process to support incident investigation
B88: 3.7.38 | C88: Log monitoring integration | N88: =VLOOKUP(_Output!D1277,_Guidance!$B$2234:$C$2240,2,FALSE) | O88: Integration with the log monitoring tooling (e.g. SIEM or XDR) for centralised correlation
B89: 3.7.39 | C89: Malware sandbox integration | N89: =VLOOKUP(_Output!D1278,_Guidance!$B$2234:$C$2240,2,FALSE) | O89: Detonate potential malware samples in a sandbox environment
B91: Rule-based detection
B92: 3.7.40 | C92: Online signature-based detection | N92: =VLOOKUP(_Output!D1279,_Guidance!$B$2234:$C$2240,2,FALSE) | O92: Signature-based malware detection requiring an active internet connection
B93: 3.7.41 | C93: Offline signature-based detection | N93: =VLOOKUP(_Output!D1280,_Guidance!$B$2234:$C$2240,2,FALSE) | O93: Signature-based malware detection not requiring an active internet connection
B94: 3.7.42 | C94: Custom rules | N94: =VLOOKUP(_Output!D1281,_Guidance!$B$2234:$C$2240,2,FALSE) | O94: Creation of custom rules for the detection of specific Indicators of Attack
B96: Anomaly detection
B97: 3.7.43 | C97: Behavioural detection | N97: =VLOOKUP(_Output!D1282,_Guidance!$B$2234:$C$2240,2,FALSE) | O97: Detection of potentially malicious behaviour using machine learning technologies
B99: Visualisation & output
B100: 3.7.44 | C100: Reporting | N100: =VLOOKUP(_Output!D1283,_Guidance!$B$2234:$C$2240,2,FALSE) | O100: Custom reports for SOC customers and SOC analysts
B101: 3.7.45 | C101: Dashboards | N101: =VLOOKUP(_Output!D1284,_Guidance!$B$2234:$C$2240,2,FALSE) | O101: Custom dashboards used by analysts and managers
B102: 3.7.46 | C102: Data visualization techniques | N102: =VLOOKUP(_Output!D1285,_Guidance!$B$2234:$C$2240,2,FALSE) | O102: Graphing capabilities to support analysis
B103: 3.7.47 | C103: Data drilldowns | N103: =VLOOKUP(_Output!D1286,_Guidance!$B$2234:$C$2240,2,FALSE) | O103: Drilldowns on graphs to quickly 'zoom in' on details of visual anomalies
B104: 3.7.48 | C104: Central analysis console | N104: =VLOOKUP(_Output!D1287,_Guidance!$B$2234:$C$2240,2,FALSE) | O104: A central console used by SOC analysts
B105: 3.7.49 | C105: Advanced searching and querying | N105: =VLOOKUP(_Output!D1288,_Guidance!$B$2234:$C$2240,2,FALSE) | O105: Searching capabilities that support finding specific information based on characteristics, especially useful for end-point threat hunting
C106: Completeness (%) | L106: =IFERROR(ROUND(_Output!K473,0),0) -> 0
B108: Comments and/or Remarks
B109: 3.8 | C109: Specify rationale for chosen values or any additional comments | K109: Maturity | L109: 3.1.1
L110: 3.1.2
B111: [1] see: | L111: 3.2.1
...

Sheet Technology - AUT
B1: Technology
B3: 1. Log Monitoring
B4: 2. Network Monitoring
B5: 3. Endpoint Monitoring
B6: 4. SecOps Automation
A9: 4 | B9: SecOps Automation | L9: Answer | N9: Guidance | O9: Remarks
B10: Maturity
B11: 4.1 | C11: Accountability
B12: 4.1.1 | C12: Has functional ownership of the solution been formally assigned? | N12: =VLOOKUP(_Output!D479,_Guidance!B1507:C1512,2,FALSE) | O12: Functional ownership includes functional accountability
B13: 4.1.2 | C13: Has technical ownership of the solution been formally assigned? | N13: =VLOOKUP(_Output!D480,_Guidance!B1513:C1518,2,FALSE) | O13: Technical ownership includes technical accountability
B14: 4.2 | C14: Documentation
B15: 4.2.1 | C15: Has the solution been technically documented? | N15: =VLOOKUP(_Output!D482,_Guidance!B1519:C1524,2,FALSE) | O15: A technical description of the system's components and configuration
B16: 4.2.2 | C16: Has the solution been functionally documented? | N16: =VLOOKUP(_Output!D483,_Guidance!B1525:C1530,2,FALSE) | O16: A description of the system's functional configuration (workflows, integrations, etc.)
B17: 4.3 | C17: Personnel & support
B18: 4.3.1 | C18: Is there dedicated personnel for support? | N18: =VLOOKUP(_Output!D485,_Guidance!B1531:C1536,2,FALSE) | O18: Dedicated personnel should be in place to ensure that support is always available. Can also be staff with outsourced provider
B19: 4.3.2 | C19: Is the personnel for support formally trained? | N19: =VLOOKUP(_Output!D486,_Guidance!B1537:C1542,2,FALSE) | O19: Training helps to jump start new hires, and to learn a proper way of working with the tool
B20: 4.3.3 | C20: Is the personnel for support certified? | N20: =VLOOKUP(_Output!D487,_Guidance!B1543:C1548,2,FALSE) | O20: Certification demonstrates ability to handle the tooling properly
B21: 4.3.4 | C21: Is there a support contract for the solution? | N21: =VLOOKUP(_Output!D488,_Guidance!B1549:C1554,2,FALSE) | O21: A support contract may cover on-site support, support availability, response times, escalation and full access to resources
B22: 4.4 | C22: Maintenance & configuration
B23: 4.4.1 | C23: Is the system regularly maintained? | N23: =VLOOKUP(_Output!D1060,_Guidance!B1555:C1560,2,FALSE) | O23: Systems should be regularly maintained to keep up with the latest features and bug fixes
B24: 4.4.2 | C24: Is remote maintenance on the system managed? | N24: =VLOOKUP(_Output!D1061,_Guidance!B1561:C1566,2,FALSE) | O24: Remote maintenance by a third party may be part of system maintenance procedures
B25: 4.4.3 | C25: Are maintenance & configuration updates executed through the change management process? | N25: =VLOOKUP(_Output!D1062,_Guidance!B1567:C1572,2,FALSE) | O25: Maintenance and configuration updates should follow the formal change management process
B26: 4.4.4 | C26: Have you established maintenance and change windows? | N26: =VLOOKUP(_Output!D1063,_Guidance!B1573:C1578,2,FALSE) | O26: Setting maintenance windows helps to structure the maintenance process and make it more predictable
B27: 4.4.5 | C27: Is maintenance performed using authorised and trusted tooling? | N27: =VLOOKUP(_Output!D1064,_Guidance!B1579:C1584,2,FALSE) | O27: Performing maintenance with authorised and trusted tooling helps to ensure security and integrity of the system
B28: 4.5 | C28: Availability, integrity & continuity
B29: 4.5.1 | C29: Is there high availability (HA) in place for the solution? | N29: =VLOOKUP(_Output!D490,_Guidance!B1585:C1590,2,FALSE) | O29: Can be fully implemented HA, partially implemented, hot spare, etc.
B30: 4.5.2 | C30: Is there data backup / replication in place for the solution? | N30: =VLOOKUP(_Output!D491,_Guidance!B1591:C1596,2,FALSE) | O30: May not be required for this particular solution
B31: 4.5.3 | C31: Is there configuration backup / replication in place for the solution? | N31: =VLOOKUP(_Output!D492,_Guidance!B1597:C1602,2,FALSE) | O31: Configuration synchronization could be part of a HA setup
B32: 4.5.4 | C32: Is there a Disaster Recovery plan in place for this solution? | N32: =VLOOKUP(_Output!D493,_Guidance!B1603:C1608,2,FALSE) | O32: A DR plan is required to restore service in case of catastrophic events
B33: 4.5.5 | C33: Is the Disaster Recovery plan regularly tested? | N33: =VLOOKUP(_Output!D494,_Guidance!B1609:C1614,2,FALSE) | O33: Testing the DR plan is required to ensure that it is complete, functional and tasks and responsibilities for involved personnel are understood
B34: 4.5.6 | C34: Is there a separate development / test environment for this solution? | N34: =VLOOKUP(_Output!D495,_Guidance!B1615:C1620,2,FALSE) | O34: A separate test environment allows for testing of new configurations before deployment in production
B35: 4.6 | C35: Access management
B36: 4.6.1 | C36: Is access to the solution limited to authorized personnel? | N36: =VLOOKUP(_Output!D497,_Guidance!B1621:C1626,2,FALSE) | O36: The system may have automated actions that can impact the usage of systems and should be restricted
B37: 4.6.2 | C37: Are access rights regularly reviewed and revoked if required? | N37: =VLOOKUP(_Output!D499,_Guidance!B1627:C1632,2,FALSE) | O37: Revocation is part of normal employee termination. Special emergency revocation should be in place for suspected misuse
B38: 4.6.3 | C38: Is a break glass procedure in place? | N38: =VLOOKUP(_Output!D1142,_Guidance!B1633:C1638,2,FALSE) | O38: A break glass procedure and account is required to gain access to the tooling even in case of major IT outages
B40: Capability
B41: 4.7 | C41: Specify which technological capabilities and artefacts are present and implemented:
B42: Technical capabilities
B43: 4.7.1 | C43: Historical event matching | N43: =VLOOKUP(_Output!D507,_Guidance!$B$2234:$C$2240,2,FALSE) | O43: Contextualize potential incidents using similar historical events
B44: 4.7.2 | C44: Risk-based event prioritization | N44: =VLOOKUP(_Output!D509,_Guidance!$B$2234:$C$2240,2,FALSE) | O44: Risk-based prioritization of security events using contextualized information
B45: 4.7.3 | C45: Ticket workflow support | N45: =VLOOKUP(_Output!D516,_Guidance!$B$2234:$C$2240,2,FALSE) | O45: Automated ticket creation and workflow support
B47: Data integrations
B48: 4.7.4 | C48: Log monitoring data integration | N48: =VLOOKUP(_Output!D502,_Guidance!$B$2234:$C$2240,2,FALSE) | O48: The SecOps automation tool receives events or cases from the log monitoring system
B49: 4.7.5 | C49: Threat intelligence integration | N49: =VLOOKUP(_Output!D503,_Guidance!$B$2234:$C$2240,2,FALSE) | O49: Contextualize potential incidents using threat intelligence
B50: 4.7.6 | C50: Asset context integration | N50: =VLOOKUP(_Output!D504,_Guidance!$B$2234:$C$2240,2,FALSE) | O50: Contextualize potential incidents using asset information
B51: 4.7.7 | C51: Identity context integration | N51: =VLOOKUP(_Output!D505,_Guidance!$B$2234:$C$2240,2,FALSE) | O51: Contextualize potential incidents using user information
B52: 4.7.8 | C52: Vulnerability management integration | N52: =VLOOKUP(_Output!D506,_Guidance!$B$2234:$C$2240,2,FALSE) | O52: Contextualize potential incidents using vulnerability management information
B54: Response integrations
B55: 4.7.9 | C55: Knowledge base integration | N55: =VLOOKUP(_Output!D508,_Guidance!$B$2234:$C$2240,2,FALSE) | O55: Automatically update the knowledge base using event information
B56: 4.7.10 | C56: Firewall integration | N56: =VLOOKUP(_Output!D510,_Guidance!$B$2234:$C$2240,2,FALSE) | O56: Automated remediation by blocking attackers on the firewall
B57: 4.7.11 | C57: Network response integration | N57: =VLOOKUP(_Output!D511,_Guidance!$B$2234:$C$2240,2,FALSE) | O57: Automated remediation by blocking attackers in the network
B58: 4.7.12 | C58: Endpoint response integration | N58: =VLOOKUP(_Output!D1289,_Guidance!$B$2234:$C$2240,2,FALSE) | O58: Automated remediation by blocking attackers on the end-point
B59: 4.7.13 | C59: Email protection integration | N59: =VLOOKUP(_Output!D512,_Guidance!$B$2234:$C$2240,2,FALSE) | O59: Automated remediation by blocking email senders
B60: 4.7.14 | C60: Malware protection integration | N60: =VLOOKUP(_Output!D513,_Guidance!$B$2234:$C$2240,2,FALSE) | O60: Automated remediation by quarantining malware and scanning end-points for malware threats
B61: 4.7.15 | C61: Sandbox integration | N61: =VLOOKUP(_Output!D514,_Guidance!$B$2234:$C$2240,2,FALSE) | O61: Automated delivery of malware samples to sandbox environments for extensive analysis
B62: 4.7.16 | C62: Active Directory / IAM integration | N62: =VLOOKUP(_Output!D515,_Guidance!$B$2234:$C$2240,2,FALSE) | O62: Automated locking and suspension of user accounts or revocation of access rights based on event outcome
B63: 4.7.17 | C63: Log monitoring integration | N63: =VLOOKUP(_Output!D1290,_Guidance!$B$2234:$C$2240,2,FALSE) | O63: Querying log monitoring tool (e.g. SIEM or XDR) to obtain information for ticket context or automated triage
B65: Playbooks [1]
B66: 4.7.18 | C66: Standard playbooks | N66: =VLOOKUP(_Output!D1291,_Guidance!$B$2234:$C$2240,2,FALSE) | O66: Application of standard (out of the box) response playbooks the platform
B67: 4.7.19 | C67: Customised playbooks | N67: =VLOOKUP(_Output!D1292,_Guidance!$B$2234:$C$2240,2,FALSE) | O67: Application of customized and fully response customized playbooks in the platform
B68: 4.7.20 | C68: Playbook automation | N68: =VLOOKUP(_Output!D1293,_Guidance!B1639:C1645,2,FALSE) | O68: Application of automation in playbooks
B69: 4.7.21 | C69: Playbook development process | N69: =VLOOKUP(_Output!D1294,_Guidance!$B$2234:$C$2240,2,FALSE) | O69: A development, refinement and life cycle management process for SOC playbooks for usage in platform
B71: Visualisation and ouput
B72: 4.7.22 | C72: Reporting | N72: =VLOOKUP(_Output!D1295,_Guidance!$B$2234:$C$2240,2,FALSE) | O72: Custom reports for SOC customers and SOC analysts
B73: 4.7.23 | C73: Dashboards | N73: =VLOOKUP(_Output!D1296,_Guidance!$B$2234:$C$2240,2,FALSE) | O73: Custom dashboards used by analysts and managers
B74: 4.7.24 | C74: Performance tracking | N74: =VLOOKUP(_Output!D520,_Guidance!$B$2234:$C$2240,2,FALSE) | O74: Application of KPIs and metrics to ticket workflow
C75: Completeness (%) | L75: =IFERROR(ROUND(_Output!K522,0),0) -> 0
B77: Comments and/or Remarks
B78: 4.8 | C78: Specify rationale for chosen values or any additional comments | L78: 4.1.1
L79: 4.1.2
L80: 4.2.1
L81: 4.2.2
L82: 4.3.1
L83: 4.3.2
L84: 4.3.3
L85: 4.3.4
L86: 4.4.1
L87: 4.4.2
L88: 4.4.3
L89: 4.4.4
L90: 4.4.5
... L124: 4.7.24

Sheet Services - SCM
B1: Services
B3: 1. Security Monitoring | G3: 5. Threat Hunting
B4: 2. Security Incident Management | G4: 6. Vulnerability Management
B5: 3. Forensic Analysis
B6: 4. Cyber Threat Intelligence
A9: 1 | B9: Security Monitoring | L9: Answer | N9: Guidance | O9: Remarks
B10: Maturity
B11: 1.1 | C11: Have you formally described the security monitoring service? | N11: =VLOOKUP(_Output!D528,_Guidance!B1649:C1654,2,FALSE) | O11: A service description should be in place
B12: 1.2 | C12: Please specify elements of the security monitoring service document:
B13: 1.2.1 | C13: Key performance indicators | O13: Indicators to establish the performance of the service
B14: 1.2.2 | C14: Quality indicators | O14: Indicators to establish the quality of service delivery
B15: 1.2.3 | C15: Service dependencies | O15: A clear understanding of which people / process / technologies are required for adequate service delivery
B16: 1.2.4 | C16: Service levels | O16: Agreements on minimum performance, capacity, availability, etc.
B17: 1.2.5 | C17: Hours of operation | O17: The operational hours for this service (e.g. 24/7)
B18: 1.2.6 | C18: Service customers and stakeholders | O18: The customers and stakeholders for this service (e.g. IT management)
B19: 1.2.7 | C19: Purpose | O19: The purpose and objectives for this service
B20: 1.2.8 | C20: Service input / triggers | O20: The service input: what triggers this service to run?
B21: 1.2.9 | C21: Service output / deliverables | O21: The service output: what does the service deliver? Can be tangible (e.g. reports) or intangible (e.g. situational awareness )
B22: 1.2.10 | C22: Service activities | O22: Which activities are carried out within the scope of the service?
B23: 1.2.11 | C23: Service roles & responsibilities | O23: Which roles and responsibilities apply to this service?
C24: Completeness | L24: =VLOOKUP(SUM(_Output!D538:D548),_SUM_Completeness!A84:B95,2,FALSE) -> Incomplete | O24: Use this outcome to determine the score for 1.2
B25: 1.3 | C25: Is the service measured for quality? | N25: =VLOOKUP(_Output!D549,_Guidance!B1655:C1660,2,FALSE) | O25: Are the quality indicators from the previous questions used for reporting on the service?
B26: 1.4 | C26: Is the service measured for service delivery in accordance with service levels? | N26: =VLOOKUP(_Output!D550,_Guidance!B1661:C1666,2,FALSE) | O26: Service levels should be used to formally commit the SOC to service delivery
B27: 1.5 | C27: Are customers and/or stakeholders regularly updated about the service? | N27: =VLOOKUP(_Output!D551,_Guidance!B1667:C1672,2,FALSE) | O27: Changes to the service scope, delivery, etc.
B28: 1.6 | C28: Is there a contractual agreement between the SOC and the customers? | N28: =VLOOKUP(_Output!D552,_Guidance!B1673:C1678,2,FALSE) | O28: Contractual agreements should also cover penalties
B29: 1.7 | C29: Is sufficient personnel allocated to the process to ensure required service delivery? | N29: =VLOOKUP(_Output!D553,_Guidance!B1679:C1684,2,FALSE) | O29: Allocation of dedicated personnel will ensure highest service quality
B30: 1.8 | C30: Is the service aligned with other relevant processes? | N30: =VLOOKUP(_Output!D554,_Guidance!B1685:C1690,2,FALSE) | O30: e.g. alignment with configuration management, incident management, etc.
B31: 1.9 | C31: Is there a incident resolution / service continuity process in place for this service? | N31: =VLOOKUP(_Output!D555,_Guidance!B1691:C1696,2,FALSE) | O31: Service continuity is important to comply with contractual agreements, even in case of major incidents
B32: 1.10 | C32: Has a set of procedures been created for this service? | N32: =VLOOKUP(_Output!D557,_Guidance!B1697:C1702,2,FALSE) | O32: Procedures support process standardization and quality. Personnel should be trained to use procedures correctly and structurally
B33: 1.11 | C33: Is there an onboarding and offloading procedure for this service? | N33: =VLOOKUP(_Output!D1066,_Guidance!B1703:C1708,2,FALSE) | O33: Customer onboarding and offloading procedures support efficient service delivery and ensure customers are (dis)connected properly
B34: 1.12 | C34: Are best practices applied to the service? | N34: =VLOOKUP(_Output!D558,_Guidance!B1709:C1714,2,FALSE) | O34: Best practices should be used to optimize this service
B35: 1.13 | C35: Are use cases used in the security monitoring service? | N35: =VLOOKUP(_Output!D559,_Guidance!B1715:C1720,2,FALSE) | O35: e.g. user login brute-force, denial of service, non-compliance, etc.
B36: 1.14 | C36: Is process data gathered for prediction of service performance? | N36: =VLOOKUP(_Output!D568,_Guidance!B1721:C1726,2,FALSE) | O36: Service performance measurement requires establishment of performance goals
B37: 1.15 | C37: Is the service continuously being improved based on improvement goals? | N37: =VLOOKUP(_Output!D569,_Guidance!B1727:C1732,2,FALSE) | O37: Improvement based on based evaluation, (maturity) assessment, tests, etc.
B39: Capability
B40: 1.16 | C40: Please specify capabilities of the security monitoring service:
B41: 1.16.1 | C41: Early detection | N41: =VLOOKUP(_Output!D571,_Guidance!$B$2234:$C$2240,2,FALSE) | O41: Capability to detect incidents in an early stage
B42: 1.16.2 | C42: Intrusion detection | N42: =VLOOKUP(_Output!D572,_Guidance!$B$2234:$C$2240,2,FALSE) | O42: Capability to detect intrusion attempts
B43: 1.16.3 | C43: Exfiltration detection | N43: =VLOOKUP(_Output!D573,_Guidance!$B$2234:$C$2240,2,FALSE) | O43: Capability to detect information leaving the organization
B44: 1.16.4 | C44: Subtle event detection | N44: =VLOOKUP(_Output!D574,_Guidance!$B$2234:$C$2240,2,FALSE) | O44: Capability to detect slight changes in systems, applications or network that may indicate malicious behavior
B45: 1.16.5 | C45: Malware detection | N45: =VLOOKUP(_Output!D575,_Guidance!$B$2234:$C$2240,2,FALSE) | O45: Capability to detect malware in the infrastructure
B46: 1.16.6 | C46: Anomaly detection | N46: =VLOOKUP(_Output!D577,_Guidance!$B$2234:$C$2240,2,FALSE) | O46: Capability to detect anomalies
B47: 1.16.7 | C47: Real-time detection | N47: =VLOOKUP(_Output!D578,_Guidance!$B$2234:$C$2240,2,FALSE) | O47: Can also be near real-time (e.g. 15 minutes delay)
B48: 1.16.8 | C48: Alerting & notification | N48: =VLOOKUP(_Output!D579,_Guidance!$B$2234:$C$2240,2,FALSE) | O48: Capability to automatically send alerts for all security monitoring components
B49: 1.16.9 | C49: False-positive reduction | N49: =VLOOKUP(_Output!D593,_Guidance!$B$2234:$C$2240,2,FALSE) | O49: A process for reducing the amount of false-positives
B50: 1.16.10 | C50: Continuous tuning | N50: =VLOOKUP(_Output!D594,_Guidance!$B$2234:$C$2240,2,FALSE) | O50: A continuous tuning process for the correlation rules
B51: 1.16.11 | C51: Coverage management | N51: =VLOOKUP(_Output!D595,_Guidance!$B$2234:$C$2240,2,FALSE) | O51: Coverage indicates how well the service covers the assets in your environment
B52: 1.16.12 | C52: Status monitoring | N52: =VLOOKUP(_Output!D580,_Guidance!$B$2242:$C$2248,2,FALSE) | O52: Monitoring of the status of the system
B53: 1.16.13 | C53: Perimeter monitoring | N53: =VLOOKUP(_Output!D581,_Guidance!$B$2242:$C$2248,2,FALSE) | O53: Monitoring of the network perimeter for attempted intrusions and exfiltration
B54: 1.16.14 | C54: Host monitoring | N54: =VLOOKUP(_Output!D582,_Guidance!$B$2242:$C$2248,2,FALSE) | O54: Monitoring of endpoints in the networks (servers, clients, etc.)
B55: 1.16.15 | C55: Network & traffic monitoring | N55: =VLOOKUP(_Output!D583,_Guidance!$B$2242:$C$2248,2,FALSE) | O55: Monitoring of network and traffic flows and anomalies
B56: 1.16.16 | C56: Access & usage monitoring | N56: =VLOOKUP(_Output!D584,_Guidance!$B$2242:$C$2248,2,FALSE) | O56: Monitoring of access attempts
B57: 1.16.17 | C57: User / identity monitoring | N57: =VLOOKUP(_Output!D585,_Guidance!$B$2242:$C$2248,2,FALSE) | O57: Monitoring of user actions
B58: 1.16.18 | C58: Application & service monitoring | N58: =VLOOKUP(_Output!D586,_Guidance!$B$2242:$C$2248,2,FALSE) | O58: Monitoring of applications & services
B59: 1.16.19 | C59: Behavior monitoring | N59: =VLOOKUP(_Output!D587,_Guidance!$B$2242:$C$2248,2,FALSE) | O59: Monitoring of behavior against baselines (can be host, network and user behavior)
B60: 1.16.20 | C60: Database monitoring | N60: =VLOOKUP(_Output!D588,_Guidance!$B$2242:$C$2248,2,FALSE) | O60: Monitoring of databases
B61: 1.16.21 | C61: Data loss monitoring | N61: =VLOOKUP(_Output!D589,_Guidance!$B$2242:$C$2248,2,FALSE) | O61: Monitoring for loss of information
B62: 1.16.22 | C62: Device loss / theft monitoring | N62: =VLOOKUP(_Output!D590,_Guidance!$B$2242:$C$2248,2,FALSE) | O62: Monitoring for loss or theft of company assets
B63: 1.16.23 | C63: Third-party monitoring | N63: =VLOOKUP(_Output!D591,_Guidance!$B$2242:$C$2248,2,FALSE) | O63: Monitoring of trusted third-parties to detect possible breach attempts through the supply chain
B64: 1.16.24 | C64: Physical environment monitoring | N64: =VLOOKUP(_Output!D592,_Guidance!$B$2242:$C$2248,2,FALSE) | O64: Monitoring of the physical environment to detect cyber security incidents
B65: 1.16.25 | C65: Cloud monitoring | N65: =VLOOKUP(_Output!D973,_Guidance!$B$2242:$C$2248,2,FALSE) | O65: Monitoring of private and public cloud environment: SAAS, IAAS and PAAS
B66: 1.16.26 | C66: Mobile device monitoring | N66: =VLOOKUP(_Output!D975,_Guidance!$B$2242:$C$2248,2,FALSE) | O66: Monitoring of corporate owned mobile devices or mobile devices containing corporate information
B67: 1.16.27 | C67: OT monitoring | N67: =VLOOKUP(_Output!D1335,_Guidance!$B$2242:$C$2248,2,FALSE) | O67: Monitoring of Operational Technology environments, including ICS, SCADA, DPC and PLC systems
C68: Completeness (%) | L68: =IFERROR(ROUND(_Output!K597,0),0) -> 0
B70: Comments and/or Remarks
B71: 1.17 | C71: Specify rationale for chosen values or any additional comments | K71: Maturity | L71: 1.1
L72: 1.3
L73: 1.4
L74: 1.5
L75: 1.6
L76: 1.7
L77: 1.8
L78: 1.9
L79: 1.10
L80: 1.11
L81: 1.12
L82: 1.13
L83: 1.14
L84: 1.15
K86: Capability | L86: 1.16.1
L87: 1.16.2
L88: 1.16.3
L89: 1.16.4
L90: 1.16.5
L91: 1.16.6
L92: 1.16.7
L93: 1.16.8
L94: 1.16.9
L95: 1.16.10
L96: 1.16.11
L97: 1.16.12
L98: 1.16.13
... L111: 1.16.26

Sheet Services - SIM
B1: Services
B3: 1. Security Monitoring | G3: 5. Threat Hunting
B4: 2. Security Incident Management | G4: 6. Vulnerability Management
B5: 3. Forensic Analysis
B6: 4. Cyber Threat Intelligence
A9: 2 | B9: Security Incident Management | L9: Answer | N9: Guidance | O9: Remarks
B10: Maturity
B11: 2.1 | C11: Have you adopted a maturity assessment methodology for Security Incident Management?
B12: 2.1.1 | C12: If yes, please specify the methodology | O12: e.g., SIM3, CREST, etc.
B13: 2.1.2 | C13: If yes, please specify the maturity level (can have up to 2 digits) | O13: Please convert to a 5-point scale if required. For example: 3.6 on a 4-point scale = 4.5 on a 5-point scale
C14: If yes, skip directly to 2.17 (capabilities) | O14: The score in 2.1.2 overrules any maturity scoring in this section
B15: 2.2 | C15: Have you adopted a standard for the Security Incident Management process? | N15: =VLOOKUP(_Output!D605,_Guidance!B1735:C1740,2,FALSE) | O15: e.g. NIST 800-62r3, CERT handbook, etc.
B16: 2.3 | C16: Have you formally described the security incident management process? | N16: =VLOOKUP(_Output!D606,_Guidance!B1741:C1746,2,FALSE) | O16: A service description should be in place
B17: 2.4 | C17: Please specify elements of the security incident management document:
B18: 2.4.1 | C18: Security incident definition | O18: A clear and unambiguous definition of a security incident
B19: 2.4.2 | C19: Service levels | O19: e.g. response times
B20: 2.4.3 | C20: Workflow | O20: The process steps that are part of the security incident management process (e.g. detection, triage, etc.)
B21: 2.4.4 | C21: Decision tree | O21: Decision tree for escalation and starting of the process
B22: 2.4.5 | C22: Hours of operation | O22: When can the security incident response process be started?
B23: 2.4.6 | C23: Service customers and stakeholders | O23: The customers and stakeholders for this service (e.g. IT management)
B24: 2.4.7 | C24: Purpose | O24: The purpose and objectives for this service
B25: 2.4.8 | C25: Service input / triggers | O25: The service input: what triggers this service to run?
B26: 2.4.9 | C26: Service output / deliverables | O26: The service output: what does the service deliver? Can be tangible (e.g. reports) or intangible (e.g. situational awareness )
B27: 2.4.10 | C27: Service activities | O27: Which activities are carried out within the scope of the service?
B28: 2.4.11 | C28: Service roles & responsibilities | O28: Which roles and responsibilities apply to this service?
C29: Completeness | L29: =VLOOKUP(SUM(_Output!D608:D618),_SUM_Completeness!A113:B124,2,FALSE) -> Incomplete | O29: Use this outcome to determine the score for 2.4
B30: 2.5 | C30: Is the service measured for quality? | N30: =VLOOKUP(_Output!D619,_Guidance!B1747:C1752,2,FALSE) | O30: Are the quality indicators from the previous questions used for reporting on the service?
B31: 2.6 | C31: Is the service measured for service delivery in accordance with service levels? | N31: =VLOOKUP(_Output!D620,_Guidance!B1753:C1758,2,FALSE) | O31: Service levels should be used to formally commit the SOC to service delivery
B32: 2.7 | C32: Are customers and/or stakeholders regularly updated about the service? | N32: =VLOOKUP(_Output!D621,_Guidance!B1759:C1764,2,FALSE) | O32: Changes to the service scope, delivery, etc.
B33: 2.8 | C33: Is there a contractual agreement between the SOC and the customers? | N33: =VLOOKUP(_Output!D625,_Guidance!B1765:C1770,2,FALSE) | O33: Contractual agreements should also cover penalties
B34: 2.9 | C34: Is sufficient personnel allocated to the process to ensure required service delivery? | N34: =VLOOKUP(_Output!D626,_Guidance!B1771:C1776,2,FALSE) | O34: Allocation of dedicated personnel will ensure highest service quality
B35: 2.10 | C35: Is the service aligned with other relevant processes? | N35: =VLOOKUP(_Output!D627,_Guidance!B1777:C1782,2,FALSE) | O35: e.g. alignment with configuration management, incident management, etc.
B36: 2.11 | C36: Is the incident response team authorized to perform (invasive) actions when required? | N36: =VLOOKUP(_Output!D628,_Guidance!B1783:C1788,2,FALSE) | O36: This is a mandate issue. The team should have mandate beforehand to optimize incident response times
B37: 2.12 | C37: Is there an onboarding and offloading procedure for this service? | N37: =VLOOKUP(_Output!D1067,_Guidance!B1789:C1794,2,FALSE) | O37: Customer onboarding and offloading procedures support efficient service delivery and ensure customers are (dis)connected properly
B38: 2.13 | C38: Are best practices applied to the service? | N38: =VLOOKUP(_Output!D631,_Guidance!B1795:C1800,2,FALSE) | O38: Best practices should be used to optimize this service
B39: 2.14 | C39: Is the service supported by predefined workflows or scenarios? | N39: =VLOOKUP(_Output!D632,_Guidance!B1801:C1806,2,FALSE) | O39: Workflows and scenario's can be used to structure follow-up and determine expected incident progression
B40: 2.15 | C40: Is process data gathered for prediction of service performance? | N40: =VLOOKUP(_Output!D633,_Guidance!B1807:C1812,2,FALSE) | O40: Service performance measurement requires establishment of performance goals
B41: 2.16 | C41: Is the service continuously being improved based on improvement goals? | N41: =VLOOKUP(_Output!D634,_Guidance!B1813:C1818,2,FALSE) | O41: Improvement based on based evaluation, (maturity) assessment, tests, etc.
B42: Capability
B43: 2.17 | C43: Please specify capabilities and artefacts of the security incident management service:
B44: Preparation
B45: 2.17.1 | C45: Incident logging procedure | N45: =VLOOKUP(_Output!D637,_Guidance!$B$2234:$C$2240,2,FALSE) | O45: Part of preparation procedures
B46: 2.17.2 | C46: Incident resolution procedure | N46: =VLOOKUP(_Output!D638,_Guidance!$B$2234:$C$2240,2,FALSE) | O46: Part of preparation procedures. Likely involves a checklist and a workflow for incident handling
B47: 2.17.3 | C47: Incident investigation procedure | N47: =VLOOKUP(_Output!D639,_Guidance!$B$2234:$C$2240,2,FALSE) | O47: Part of preparation procedures. Includes triage procedure and investigation / analysis procedures
B48: 2.17.4 | C48: Escalation process | N48: =VLOOKUP(_Output!D640,_Guidance!$B$2234:$C$2240,2,FALSE) | O48: Internal escalation to upper management
B49: 2.17.5 | C49: Evidence collection procedure | N49: =VLOOKUP(_Output!D641,_Guidance!$B$2234:$C$2240,2,FALSE) | O49: Part of preparation procedures
B50: 2.17.6 | C50: Incident containment procedures | N50: =VLOOKUP(_Output!D642,_Guidance!$B$2234:$C$2240,2,FALSE) | O50: Part of preparation procedures. Can be based on RE&CT framework[1]
B51: 2.17.7 | C51: IR Training | N51: =VLOOKUP(_Output!D643,_Guidance!$B$2234:$C$2240,2,FALSE) | O51: Preparation exercises to determine service effectiveness
B52: 2.17.8 | C52: Table-top exercises | N52: =VLOOKUP(_Output!D644,_Guidance!$B$2234:$C$2240,2,FALSE) | O52: Preparation exercises to determine service effectiveness
B53: 2.17.9 | C53: Red team / blue team exercises | N53: =VLOOKUP(_Output!D645,_Guidance!$B$2234:$C$2240,2,FALSE) | O53: Preparation exercises to determine service effectiveness
B54: 2.17.10 | C54: Exercises with other incident response teams | O54: Exercises with other IR teams, for example outsourcing partners and other teams in the sector
B55: 2.17.11 | C55: External security incident support agreements | O55: Retainer for incident response as a service in case of major breaches
B56: 2.17.12 | C56: RACI matrix | N56: =VLOOKUP(_Output!D646,_Guidance!$B$2234:$C$2240,2,FALSE) | O56: Matrix with Responsibility, Accountability and Consulted and Informed entities for the process
B57: 2.17.13 | C57: Response authorization | N57: =VLOOKUP(_Output!D647,_Guidance!$B$2234:$C$2240,2,FALSE) | O57: Authorization from senior management to take any action required for incident mitigation (e.g. disconnect systems)
B58: 2.17.14 | C58: Incident template | N58: =VLOOKUP(_Output!D648,_Guidance!$B$2234:$C$2240,2,FALSE) | O58: Templates for security incident management registration
B60: Detection & Analysis
B61: 2.17.15 | C61: Incident tracking system | O61: A system that support the security incident management workflow. If possible dedicated or supporting ticket confidentiality
B62: 2.17.16 | C62: False-positive reduction | N62: =VLOOKUP(_Output!D650,_Guidance!$B$2234:$C$2240,2,FALSE) | O62: A procedure to avoid false-positives in the security incident management process
B63: 2.17.17 | C63: Priority assignment | N63: =VLOOKUP(_Output!D651,_Guidance!$B$2234:$C$2240,2,FALSE) | O63: Assignment of priority to the incident, part of impact and magnitude assessment
B64: 2.17.18 | C64: Severity assignment | N64: =VLOOKUP(_Output!D653,_Guidance!$B$2234:$C$2240,2,FALSE) | O64: Assignment of severity to the incident, part of impact and magnitude assessment
B65: 2.17.19 | C65: Categorization / classification | N65: =VLOOKUP(_Output!D655,_Guidance!$B$2234:$C$2240,2,FALSE) | O65: Categorization or classification of the incident. For example, the VERIS framework could be used for classification
B66: 2.17.20 | C66: (dedicated/consolidated) information platform | N66: =VLOOKUP(_Output!D661,_Guidance!$B$2234:$C$2240,2,FALSE) | O66: A platform for accessing all information regarding security incidenta, accesible by all IR team members
B67: 2.17.21 | C67: Malware extraction & analysis | N67: =VLOOKUP(_Output!D663,_Guidance!$B$2234:$C$2240,2,FALSE) | O67: Extraction and analysis of malware
B69: Containment, Eradication, & Recovery
B70: 2.17.22 | C70: On-site incident response | N70: =VLOOKUP(_Output!D664,_Guidance!$B$2234:$C$2240,2,FALSE) | O70: Localized incident response capability
B71: 2.17.23 | C71: Remote incident response | N71: =VLOOKUP(_Output!D666,_Guidance!$B$2234:$C$2240,2,FALSE) | O71: Remote incident response capability
B72: 2.17.24 | C72: Third-party escalation function | N72: =VLOOKUP(_Output!D668,_Guidance!$B$2234:$C$2240,2,FALSE) | O72: Escalation process to third parties (vendors, partners, etc.)
B73: 2.17.25 | C73: Escalation to press function | O73: Escalation to internal press office in case of incidents that require communicatio to the public
B74: 2.17.26 | C74: Escalation to legal function | O74: Escalation to internal legal function in case of incidents that may have legal implications
B75: 2.17.27 | C75: Critical bridge | O75: A communication bridge for continuous alignment of employees involved in security incident management
B76: 2.17.28 | C76: War room | O76: A dedicated facility for coordination of security incidents
B77: 2.17.29 | C77: Communication plan & email templates | O77: Standardized plans and templates for communication. Includes reachability in case of emergency and outreach to customers
B78: 2.17.30 | C78: Backup communication technology | O78: Backup communication technology in case of failure of primary means. Includes internet access, email systems and phones
B79: 2.17.31 | C79: Secure communication channels | O79: Encrypted and secure communications (includes email and phones) that can be used during incident response
B80: 2.17.32 | C80: Change management integration | O80: Integration with the change management process for any actions taken in the security incident management process
B81: 2.17.33 | C81: Restore integrity verification | O81: Verification that backups and restored assets do not contain IoCs or backdoors used in the initial incident
B83: Post-Incident Activity
B84: 2.17.34 | C84: Evaluation template | N84: =VLOOKUP(_Output!D670,_Guidance!$B$2234:$C$2240,2,FALSE) | O84: A template for post-incident evaluation
B85: 2.17.35 | C85: Reporting template | N85: =VLOOKUP(_Output!D671,_Guidance!$B$2234:$C$2240,2,FALSE) | O85: A template for reporting on the security incident
B86: 2.17.36 | C86: Incident closure | N86: =VLOOKUP(_Output!D672,_Guidance!$B$2234:$C$2240,2,FALSE) | O86: Formal closure of the incident, including debriefing sessions
B87: 2.17.37 | C87: Lessons learned extraction for process improvement | N87: =VLOOKUP(_Output!D673,_Guidance!$B$2234:$C$2240,2,FALSE) | O87: Continuous improvement based on previous experiences
B88: 2.17.38 | C88: Root Cause Analysis | O88: Investigation and reporting on the root cause of the incident. Required for optimizing lessons learned for the organization
C89: Completeness (%) | L89: =IFERROR(ROUND(_Output!K676,0),0) -> 0
B91: Comments and/or Remarks
B92: 2.18 | C92: Specify rationale for chosen values or any additional comments | K92: Maturity | L92: 2.2
L93: 2.3
C94: RE&CT framework: | L94: 2.5
C95: https://atc-project.github.io/atc-react/ | L95: 2.6
L96: 2.7
L97: 2.8
L98: 2.9
L99: 2.10
L100: 2.11
L101: 2.12
L102: 2.13
L103: 2.14
L104: 2.15
L105: 2.16
K107: Capability | L107: 2.17.1
L108: 2.17.2
...

Sheet Services - A&F
B1: Services
B3: 1. Security Monitoring | G3: 5. Threat Hunting
B4: 2. Security Incident Management | G4: 6. Vulnerability Management
B5: 3. Forensic Analysis
B6: 4. Cyber Threat Intelligence
A9: 3 | B9: Forensic analysis | L9: Answer | N9: Guidance | O9: Remarks
B10: Maturity
B11: 3.1 | C11: Have you formally described the forensic analysis service? | N11: =VLOOKUP(_Output!D681,_Guidance!B1821:C1826,2,FALSE) | O11: A service description should be in place
B12: 3.2 | C12: Please specify elements of the security analysis service document:
B13: 3.2.1 | C13: Key performance indicators | O13: Indicators to establish the performance of the service
B14: 3.2.2 | C14: Quality indicators | O14: Indicators to establish the quality of service delivery
B15: 3.2.3 | C15: Service dependencies | O15: A clear understanding of which people / process / technologies are required for adequate service delivery
B16: 3.2.4 | C16: Service levels | O16: Agreements on minimum performance, capacity, availability, etc.
B17: 3.2.5 | C17: Hours of operation | O17: The operational hours for this service (e.g. 24/7)
B18: 3.2.6 | C18: Service customers and stakeholders | O18: The customers and stakeholders for this service (e.g. IT management)
B19: 3.2.7 | C19: Purpose | O19: The purpose and objectives for this service
B20: 3.2.8 | C20: Service input / triggers | O20: The service input: what triggers this service to run?
B21: 3.2.9 | C21: Service output / deliverables | O21: The service output: what does the service deliver? Can be tangible (e.g. reports) or intangible (e.g. situational awareness )
B22: 3.2.10 | C22: Service activities | O22: Which activities are carried out within the scope of the service?
B23: 3.2.11 | C23: Service roles & responsibilities | O23: Which roles and responsibilities apply to this service?
C24: Completeness | L24: =VLOOKUP(SUM(_Output!D686:D696),_SUM_Completeness!A84:B95, 2, FALSE) -> Incomplete | O24: Use this outcome to determine the score for 3.2
B25: 3.3 | C25: Is the service measured for quality? | N25: =VLOOKUP(_Output!D697,_Guidance!B1827:C1832,2,FALSE) | O25: Are the quality indicators from the previous questions used for reporting on the service?
B26: 3.4 | C26: Is the service measured for service delivery in accordance with service levels? | N26: =VLOOKUP(_Output!D698,_Guidance!B1833:C1838,2,FALSE) | O26: Service levels should be used to formally commit the SOC to service delivery
B27: 3.5 | C27: Are customers and/or stakeholders regularly updated about the service? | N27: =VLOOKUP(_Output!D699,_Guidance!B1839:C1844,2,FALSE) | O27: Changes to the service scope, delivery, etc.
B28: 3.6 | C28: Is there a contractual agreement between the SOC and the customers? | N28: =VLOOKUP(_Output!D700,_Guidance!B1845:C1850,2,FALSE) | O28: Contractual agreements should also cover penalties
B29: 3.7 | C29: Is sufficient personnel allocated to the process to ensure required service delivery? | N29: =VLOOKUP(_Output!D701,_Guidance!B1851:C1856,2,FALSE) | O29: Allocation of dedicated personnel will ensure highest service quality
B30: 3.8 | C30: Is the service aligned with other relevant processes? | N30: =VLOOKUP(_Output!D702,_Guidance!B1857:C1862,2,FALSE) | O30: e.g. alignment with configuration management, incident management, etc.
B31: 3.9 | C31: Is there a incident resolution / service continuity process in place for this service? | N31: =VLOOKUP(_Output!D703,_Guidance!B1863:C1868,2,FALSE) | O31: Service continuity is important to comply with contractual agreements, even in case of major incidents
B32: 3.10 | C32: Has a set of procedures been created for this service? | N32: =VLOOKUP(_Output!D705,_Guidance!B1869:C1874,2,FALSE) | O32: Procedures support process standardization and quality. Personnel should be trained to use procedures correctly and structurally
B33: 3.11 | C33: Is there an onboarding and offloading procedure for this service? | N33: =VLOOKUP(_Output!D1068,_Guidance!B1875:C1880,2,FALSE) | O33: Customer onboarding and offloading procedures support efficient service delivery and ensure customers are (dis)connected properly
B34: 3.12 | C34: Are best practices applied to the service? | N34: =VLOOKUP(_Output!D706,_Guidance!B1881:C1886,2,FALSE) | O34: Best practices should be used to optimize this service
B35: 3.13 | C35: Is the service supported by predefined workflows or scenarios? | N35: =VLOOKUP(_Output!D707,_Guidance!B1887:C1892,2,FALSE) | O35: Use cases can be used to guide the analysis workflows
B36: 3.14 | C36: Is process data gathered for prediction of service performance? | N36: =VLOOKUP(_Output!D711,_Guidance!B1893:C1898,2,FALSE) | O36: Service performance measurement requires establishment of performance goals
B37: 3.15 | C37: Is the service continuously being improved based on improvement goals? | N37: =VLOOKUP(_Output!D712,_Guidance!B1899:C1904,2,FALSE) | O37: Improvement based on based evaluation, (maturity) assessment, tests, etc.
B38: Capability
B39: 3.16 | C39: Please specify capabilities and artefacts of the security analysis process:
B40: 3.16.1 | C40: Event analysis | N40: =VLOOKUP(_Output!D714,_Guidance!$B$2234:$C$2240,2,FALSE) | O40: Analysis of detailed events
B41: 3.16.2 | C41: Event analysis toolkit | N41: =VLOOKUP(_Output!D715,_Guidance!$B$2234:$C$2240,2,FALSE) | O41: A combination of internal and external tools that can be used for security event analysis purposes
B42: 3.16.3 | C42: Trend analysis | N42: =VLOOKUP(_Output!D716,_Guidance!$B$2234:$C$2240,2,FALSE) | O42: Analysis of trends in events or incidents
B43: 3.16.4 | C43: Incident analysis | N43: =VLOOKUP(_Output!D717,_Guidance!$B$2234:$C$2240,2,FALSE) | O43: Analysis of security incidents
B44: 3.16.5 | C44: Visual analysis | N44: =VLOOKUP(_Output!D718,_Guidance!$B$2234:$C$2240,2,FALSE) | O44: Visualization tools for data analysis
B45: 3.16.6 | C45: Static malware analysis | N45: =VLOOKUP(_Output!D719,_Guidance!$B$2234:$C$2240,2,FALSE) | O45: Reverse engineering and disassembly of malware
B46: 3.16.7 | C46: Dynamic malware analysis | N46: =VLOOKUP(_Output!D720,_Guidance!$B$2234:$C$2240,2,FALSE) | O46: Running malware in a controlled environment to determine its characteristics
B47: 3.16.8 | C47: Tradecraft analysis | N47: =VLOOKUP(_Output!D721,_Guidance!$B$2234:$C$2240,2,FALSE) | O47: Analysis of the tradecraft of the attacker. This includes the tools, tactics, techniques and procedures used by attackers
B48: 3.16.9 | C48: Historic analysis | N48: =VLOOKUP(_Output!D722,_Guidance!$B$2234:$C$2240,2,FALSE) | O48: Analysis of historic information based on new insights. APTs can span multiple months or years
B49: 3.16.10 | C49: Network analysis | N49: =VLOOKUP(_Output!D723,_Guidance!$B$2234:$C$2240,2,FALSE) | O49: Analysis of network traffic patterns and packets
B50: 3.16.11 | C50: Memory analysis | N50: =VLOOKUP(_Output!D724,_Guidance!$B$2234:$C$2240,2,FALSE) | O50: Analysis of end-point memory, for example fileless malware
B51: 3.16.12 | C51: Mobile device analysis | N51: =VLOOKUP(_Output!D725,_Guidance!$B$2234:$C$2240,2,FALSE) | O51: Capability to perform forensic analysis of mobile devices
... B63: 3.16.24 | C63: Chain of custody preservation procedure | N63: =VLOOKUP(_Output!D737,_Guidance!$B$2234:$C$2240,2,FALSE) | O63: Procedures to correctly process evidence, while preserving the chain of custody
C64: Completeness (%) | L64: =IFERROR(ROUND(_Output!K739,0),0) -> 0
B66: Comments and/or Remarks
B67: 3.17 | C67: Specify rationale for chosen values or any additional comments | K67: Maturity | L67: 3.1
L68: 3.3
L69: 3.4
L70: 3.5
L71: 3.6
L72: 3.7
L73: 3.8
L74: 3.9
L75: 3.10
L76: 3.11
L77: 3.12
L78: 3.13
L79: 3.14
L80: 3.15
K82: Capability | L82: 3.16.1
L83: 3.16.2
L84: 3.16.3
L85: 3.16.4
L86: 3.16.5
L87: 3.16.6
L88: 3.16.7
L89: 3.16.8
L90: 3.16.9
L91: 3.16.10
L92: 3.16.11
L93: 3.16.12
L94: 3.16.13
... L105: 3.16.24

Sheet Services - THR
B1: Services
B3: 1. Security Monitoring | G3: 5. Threat Hunting
B4: 2. Security Incident Management | G4: 6. Vulnerability Management
B5: 3. Forensic Analysis
B6: 4. Cyber Threat intelligence
A9: 4 | B9: Threat Intelligence | L9: Answer | N9: Guidance | O9: Remarks
B10: Maturity
B11: 4.1 | C11: Have you formally described the threat intelligence service? | N11: =VLOOKUP(_Output!D744,_Guidance!B1907:C1912,2,FALSE) | O11: A service description should be in place
B12: 4.2 | C12: Please specify elements of the threat intelligence service document:
B13: 4.2.1 | C13: Key performance indicators | O13: Indicators to establish the performance of the service
B14: 4.2.2 | C14: Quality indicators | O14: Indicators to establish the quality of service delivery
B15: 4.2.3 | C15: Service dependencies | O15: A clear understanding of which people / process / technologies are required for adequate service delivery
B16: 4.2.4 | C16: Service levels | O16: Agreements on minimum performance, capacity, availability, etc.
B17: 4.2.5 | C17: Hours of operation | O17: The operational hours for this service (e.g. 24/7)
B18: 4.2.6 | C18: Service customers and stakeholders | O18: The customers and stakeholders for this service (e.g. IT management)
B19: 4.2.7 | C19: Purpose | O19: The purpose and objectives for this service
B20: 4.2.8 | C20: Service input / triggers | O20: The service input: what triggers this service to run?
B21: 4.2.9 | C21: Service output / deliverables | O21: The service output: what does the service deliver? Can be tangible (e.g. reports) or intangible (e.g. situational awareness )
B22: 4.2.10 | C22: Service activities | O22: Which activities are carried out within the scope of the service?
B23: 4.2.11 | C23: Service roles & responsibilities | O23: Which roles and responsibilities apply to this service?
C24: Completeness | L24: =VLOOKUP(SUM(_Output!D746:D756),_SUM_Completeness!A84:B95,2,FALSE) -> Incomplete | O24: Use this outcome to determine the score for 4.2
B25: 4.3 | C25: Is the service measured for quality? | N25: =VLOOKUP(_Output!D757,_Guidance!B1913:C1918,2,FALSE) | O25: Are the quality indicators from the previous questions used for reporting on the service?
B26: 4.4 | C26: Is the service measured for service delivery in accordance with service levels? | N26: =VLOOKUP(_Output!D758,_Guidance!B1919:C1924,2,FALSE) | O26: Service levels should be used to formally commit the SOC to service delivery
B27: 4.5 | C27: Are customers and/or stakeholders regularly updated about the service? | N27: =VLOOKUP(_Output!D759,_Guidance!B1925:C1930,2,FALSE) | O27: Changes to the service scope, delivery, etc.
B28: 4.6 | C28: Is there a contractual agreement between the SOC and the customers? | N28: =VLOOKUP(_Output!D760,_Guidance!B1931:C1936,2,FALSE) | O28: Contractual agreements should also cover penalties
B29: 4.7 | C29: Is sufficient personnel allocated to the process to ensure required service delivery? | N29: =VLOOKUP(_Output!D761,_Guidance!B1937:C1942,2,FALSE) | O29: Allocation of dedicated personnel will ensure highest service quality
B30: 4.8 | C30: Is the service aligned with other relevant processes? | N30: =VLOOKUP(_Output!D762,_Guidance!B1943:C1948,2,FALSE) | O30: e.g. the security monitoring process, and mainly the security incident management process
B31: 4.9 | C31: Is there a incident resolution / service continuity process in place for this service? | N31: =VLOOKUP(_Output!D763,_Guidance!B1949:C1954,2,FALSE) | O31: Service continuity is important to comply with contractual agreements, even in case of major incidents
B32: 4.10 | C32: Has a set of procedures been created for this service? | N32: =VLOOKUP(_Output!D765,_Guidance!B1955:C1960,2,FALSE) | O32: Procedures support process standardization and quality. Personnel should be trained to use procedures correctly and structurally
B33: 4.11 | C33: Is there an onboarding and offloading procedure for this service? | N33: =VLOOKUP(_Output!D1069,_Guidance!B1961:C1966,2,FALSE) | O33: Customer onboarding and offloading procedures support efficient service delivery and ensure customers are (dis)connected properly
B34: 4.12 | C34: Are best practices applied to the service? | N34: =VLOOKUP(_Output!D766,_Guidance!B1967:C1972,2,FALSE) | O34: Best practices should be used to optimize this service
B35: 4.13 | C35: Is process data gathered for prediction of service performance? | N35: =VLOOKUP(_Output!D767,_Guidance!B1973:C1978,2,FALSE) | O35: Service performance measurement requires establishment of performance goals
B36: 4.14 | C36: Is the service continuously being improved based on improvement goals? | N36: =VLOOKUP(_Output!D768,_Guidance!B1979:C1984,2,FALSE) | O36: Improvement based on based evaluation, (maturity) assessment, tests, etc.
B37: Capability
B38: 4.15 | C38: Please specify capabilities and artefacts of the threat intelligence process:
B39: Planning & direction
B40: 4.15.1 | C40: CTI goals and objectives identification | N40: =VLOOKUP(_Output!D1455,_Guidance!$B$2234:$C$2240,2,FALSE) | O40: Determine objectives and goals for the CTI process
B41: 4.15.2 | C41: CTI stakeholder identification | N41: =VLOOKUP(_Output!D1456,_Guidance!$B$2234:$C$2240,2,FALSE) | O41: Identify relevant stakeholders in the organization for CTI
B42: 4.15.3 | C42: Intelligence requirements identification | N42: =VLOOKUP(_Output!D1457,_Guidance!$B$2234:$C$2240,2,FALSE) | O42: Identify requirements in the organization from relevant stakeholders
B43: 4.15.4 | C43: CTI scope determination | N43: =VLOOKUP(_Output!D1458,_Guidance!$B$2234:$C$2240,2,FALSE) | O43: Determine the scope of the CTI process
B44: 4.15.5 | C44: Threat landscape analysis | N44: =VLOOKUP(_Output!D1459,_Guidance!$B$2234:$C$2240,2,FALSE) | O44: Prioritize threats for the organization based on threat landscapes
B45: 4.15.6 | C45: Asset prioritization | N45: =VLOOKUP(_Output!D1460,_Guidance!$B$2234:$C$2240,2,FALSE) | O45: Prioritize assets for relevance and risk to the CTI process
B47: Collection
B48: 4.15.7 | C48: Continuous intelligence gathering | N48: =VLOOKUP(_Output!D770,_Guidance!$B$2234:$C$2240,2,FALSE) | O48: A process for continuously gathering relevant intelligence information
B49: 4.15.8 | C49: Automated intelligence gathering & processing | N49: =VLOOKUP(_Output!D771,_Guidance!$B$2234:$C$2240,2,FALSE) | O49: An automated system that collects and processes security intelligence information
